Workbook
Name Alternative_2: [1]Umsätze!#REF!
Name Alternative_2: [1]Umsätze!#REF!
Name Alternative_2: [2]Umsätze!#REF!
Name Alternative_2: [3]Umsätze!#REF!
Name Alternative_3: [1]Umsätze!#REF!
Name Alternative_3: [1]Umsätze!#REF!
Name Alternative_3: [2]Umsätze!#REF!
Name Alternative_3: [3]Umsätze!#REF!
Name Alternative_4: [1]Umsätze!#REF!
Name Alternative_4: [1]Umsätze!#REF!
Name Alternative_4: [2]Umsätze!#REF!
Name Alternative_4: [3]Umsätze!#REF!
Name Kosten: '[4]2014'!$C$61
Name Kosten: '[5]2014'!$C$61
Name Kosten: '[6]2012'!$C$62
Name Kosten: '[7]2012'!$C$62
Name Kosten: '[8]2012'!$C$62
Name Kosten: '[9]2012'!$C$62
Name Materialkosten: #REF!
Name Materialkosten: #REF!
Name Materialkosten: #REF!
Name Materialkosten_Rechner__Jahresplanung_ohne_monatsgenaue_Verteilung: #REF!
Name Materialkosten_Rechner__Jahresplanung_ohne_monatsgenaue_Verteilung: #REF!
Name Materialkosten_Rechner__Jahresplanung_ohne_monatsgenaue_Verteilung: #REF!
Name MoUm: '[4]2014'!$C$60
Name MoUm: '[5]2014'!$C$60
Name MoUm: '[6]2012'!$C$61
Name MoUm: '[7]2012'!$C$61
Name MoUm: '[8]2012'!$C$61
Name MoUm: '[9]2012'!$C$61
Name UmRe: '[4]2014'!$C$59
Name UmRe: '[5]2014'!$C$59
Name UmRe: '[6]2012'!$C$60
Name UmRe: '[7]2012'!$C$60
Name UmRe: '[8]2012'!$C$60
Name UmRe: '[9]2012'!$C$60
Name Var1_Handw_DL: '[4]2013'!$I$53
Name Var1_Handw_DL: '[7]2011'!$I$50
Name Var1_Handw_DL: '[10]2013'!$I$53
Name Var1_Handw_DL: '[5]2013'!$I$53
Name Var2_Han_Gastro: '[4]2013'!$I$54
Name Var2_Han_Gastro: '[7]2011'!$I$51
Name Var2_Han_Gastro: '[10]2013'!$I$54
Name Var2_Han_Gastro: '[5]2013'!$I$54
Name WE: '[4]2014'!$C$62
Name WE: '[5]2014'!$C$62
Name WE: '[6]2012'!$C$63
Name WE: '[7]2012'!$C$63
Name WE: '[8]2012'!$C$63
Name WE: '[9]2012'!$C$63
Name WL_BP_De: Deckblatt!#REF!
Name WL_BP_Fm: Deckblatt!#REF!
Name WL_BP_Mm: Deckblatt!$B$16
Name WL_BP_Re: Deckblatt!#REF!
Name WL_BP_To: Deckblatt!#REF!

Sheet Deckblatt
Y1: Januar | Z1: Februar | AA1: März | AB1: April | AC1: Mai | AD1: Juni | AE1: Juli | AF1: August | AG1: September | AH1: Oktober | AI1: November | AJ1: Dezember
B2: BUSINESSPLAN ZAHLENTEIL | Y2: Februar | Z2: März | AA2: April | AB2: Mai | AC2: Juni | AD2: Juli | AE2: August | AF2: September | AG2: Oktober | AH2: November | AI2: Dezember | AJ2: Januar
Y3: März | Z3: April | AA3: Mai | AB3: Juni | AC3: Juli | AD3: August | AE3: September | AF3: Oktober | AG3: November | AH3: Dezember | AI3: Januar | AJ3: Februar
B4: Firmenname: | C4: Muster GbR | Y4: April | Z4: Mai | AA4: Juni | AB4: Juli | AC4: August | AD4: September | AE4: Oktober | AF4: November | AG4: Dezember | AH4: Januar | AI4: Februar | AJ4: März
B5: GründerIn: | C5: Max Mustermann | G5: Siehe Unten >>>>>>>>> | Y5: Mai | Z5: Juni | AA5: Juli | AB5: August | AC5: September | AD5: Oktober | AE5: November | AF5: Dezember | AG5: Januar | AH5: Februar | AI5: März | AJ5: April
B6: Stand: | C6: =TODAY() -> 45978 | Y6: Juni | Z6: Juli | AA6: August | AB6: September | AC6: Oktober | AD6: November | AE6: Dezember | AF6: Januar | AG6: Februar | AH6: März | AI6: April | AJ6: Mai
B7: geplantes Jahr der Gründung : | C7: 2025 | Y7: Juli | Z7: August | AA7: September | AB7: Oktober | AC7: November | AD7: Dezember | AE7: Januar | AF7: Februar | AG7: März | AH7: April | AI7: Mai | AJ7: Juni
B8: geplanter Monat der Gründung: | C8: Jan. | Y8: August | Z8: September | AA8: Oktober | AB8: November | AC8: Dezember | AD8: Januar | AE8: Februar | AF8: März | AG8: April | AH8: Mai | AI8: Juni | AJ8: Juli
B9: Umsatzsteuersatz: | C9: 0.19 | Y9: September | Z9: Oktober | AA9: November | AB9: Dezember | AC9: Januar | AD9: Februar | AE9: März | AF9: April | AG9: Mai | AH9: Juni | AI9: Juli | AJ9: August
Y10: Oktober | Z10: November | AA10: Dezember | AB10: Januar | AC10: Februar | AD10: März | AE10: April | AF10: Mai | AG10: Juni | AH10: Juli | AI10: August | AJ10: September
Y11: November | Z11: Dezember | AA11: Januar | AB11: Februar | AC11: März | AD11: April | AE11: Mai | AF11: Juni | AG11: Juli | AH11: August | AI11: September | AJ11: Oktober
Y12: Dezember | Z12: Januar | AA12: Februar | AB12: März | AC12: April | AD12: Mai | AE12: Juni | AF12: Juli | AG12: August | AH12: September | AI12: Oktober | AJ12: November
B15: INHALT
B18: Deckblatt | C18: Seite 0
B19: Gewinn- u. Verlustrechnung 1. Geschäftsjahr | C19: Seite 1
B20: Gewinn- u. Verlustrechnung 2. Geschäftsjahr | C20: Seite 2
B21: Gewinn- u. Verlustrechnung 3. Geschäftsjahr | C21: Seite 3 | E21: Businessplan relevant
B22: Umsatzplanung 1.-3. Geschäftsjahr | C22: Seite 4
B23: Liquiditätsrechnung 1.-3. Jahr | C23: Seite 5
B24: Privatentnahmen | C24: Seite 6
B25: Finanzen_AfA_Investitionen | C25: Seite 7
B26: ArbStd_MA | C26: Seite 8
B27: Einzelkalkulation Gastronomie | C27: Seite 9
B28: Einzelkalkulation Handwerk | C28: Seite 10
B29: Einzelkalkulation Handel | C29: Seite 11 | E29: Kalkulationsteil
B30: Einzelkalkulation DL | C30: Seite 12
B31: Kalkul.Einzelpreise | C31: Seite 13
B32: Zusammenfassung | C32: Seite 14
G99: Jan. | H99: Febr. | I99: März | J99: April | K99: Mai | L99: Juni | M99: Juli | N99: Aug. | O99: Sept. | P99: Okt. | Q99: Nov. | R99: Dez.
G100: Febr. | H100: März | I100: April | J100: Mai | K100: Juni | L100: Juli | M100: Aug. | N100: Sept. | O100: Okt. | P100: Nov. | Q100: Dez. | R100: Jan.
G101: März | H101: April | I101: Mai | J101: Juni | K101: Juli | L101: Aug. | M101: Sept. | N101: Okt. | O101: Nov. | P101: Dez. | Q101: Jan. | R101: Febr.
G102: April | H102: Mai | I102: Juni | J102: Juli | K102: Aug. | L102: Sept. | M102: Okt. | N102: Nov. | O102: Dez. | P102: Jan. | Q102: Febr. | R102: März
G103: Mai | H103: Juni | I103: Juli | J103: Aug. | K103: Sept. | L103: Okt. | M103: Nov. | N103: Dez. | O103: Jan. | P103: Febr. | Q103: März | R103: April
G104: Juni | H104: Juli | I104: Aug. | J104: Sept. | K104: Okt. | L104: Nov. | M104: Dez. | N104: Jan. | O104: Febr. | P104: März | Q104: April | R104: Mai
G105: Juli | H105: Aug. | I105: Sept. | J105: Okt. | K105: Nov. | L105: Dez. | M105: Jan. | N105: Febr. | O105: März | P105: April | Q105: Mai | R105: Juni
G106: Aug. | H106: Sept. | I106: Okt. | J106: Nov. | K106: Dez. | L106: Jan. | M106: Febr. | N106: März | O106: April | P106: Mai | Q106: Juni | R106: Juli
G107: Sept. | H107: Okt. | I107: Nov. | J107: Dez. | K107: Jan. | L107: Febr. | M107: März | N107: April | O107: Mai | P107: Juni | Q107: Juli | R107: Aug.
G108: Okt. | H108: Nov. | I108: Dez. | J108: Jan. | K108: Febr. | L108: März | M108: April | N108: Mai | O108: Juni | P108: Juli | Q108: Aug. | R108: Sept.
G109: Nov. | H109: Dez. | I109: Jan. | J109: Febr. | K109: März | L109: April | M109: Mai | N109: Juni | O109: Juli | P109: Aug. | Q109: Sept. | R109: Okt.
G110: Dez. | H110: Jan. | I110: Febr. | J110: März | K110: April | L110: Mai | M110: Juni | N110: Juli | O110: Aug. | P110: Sept. | Q110: Okt. | R110: Nov.

Sheet Selbstverständnis
A1: Memo | D1: =TODAY() -> 45978 | L1: Es ist nicht genug zu wissen, man muss es auch anwenden! Es ist nicht genug zu wollen, man muß es auch tun! Johann Wolfgang von Goethe
A2: An: Alle Benutzer der Tabelle
A3: Von: Rüdiger ADAMY
A6: Betreff: | B6: Finanzplanung, wie ich sie verstehe, heißt:
B8: Sinn und Zweck der Planungen ist es, Ihnen einen möglichst genauen und umfassenden Überblick über die künftige Entwicklung der Unternehmung, über Kosten, Erlöse und Gewinne zu geben.
A9: ► 1
A12: ► 2 | B12: Die vorliegende Planungstabelle, (auch Umsatz- und Ertragsvorschau genannt) ist Teil der Gesamtplanung eines Unternehmens, sie besteht aus 2 Gruppen von Datenblättern. Zum einen: Finanzplanung; darunter verstehen man die Kostenplanung, die Umsatzplanung, die Liquiditätsplanung und die Kapitalbedarfsplanung (für die notwendigen Investitionen)
A16: ► 3 | B16: Zum zweiten erhalten Sie eine wichtige Basis für die Gesamtkalkulation, danach für die Einzelkalkulation von Preisen und Dienstleistungen (in verschiedener Art für Handwerk, Handel, Dienstleistung und Gastronomie.
A20: ► 4 | B20: Sie beginnen mit der Kostenplanung, danach folgt die Umsatzplanung ( ausgehend von Einzelleistunen je Tag, Woche oder Monat und soweit nötig mit dem dazu gehörenden Zeitbedarf). Zum Schluß sollten Sie die Umsatzplanung mit einem Marketing+Aktivitätenplan unterlegen, im dem Sie beschreiben, wie Sie zu Kunden und Abschlüssen kommen. Alle hieraus gewonnenen Daten bilden die Grundlage zur Erstellung der Liquidtätsrechnung .
A26: ► 5 | B26: Zum Abschluß dieser Planungsschritte sind Sie in der Lage, ausgehend von Ihren eigenen Zahlen eine Kalkulation Ihrer Preise zu machen. Dann können Sie prüfen, wie Ihre Situation am Markt ist. Die Planungstabelle ist ein Werkzeug mit dessen Hilfe Sie zuverlässig erkennen können, ob Sie rentabel arbeiten, wo Spielräume im täglichen Preiskampf sind, und wo Ihre Stärken und Schwächen liegen!

Sheet Richtig Planen

Sheet Vorblatt Auftragsakquise 
B3: Tipps und Hinweise zur Kunden/Auftragsakquisition
B7: Umsatzplanung bei der Gründung ist der wohl schwierigste und anspruchsvollste Teil der Finanzplanung, weil keine Vergleichswerte noch Erfahrungen vorhanden sind! Trotzdem ist es notwendig dies zu tun, und dabei kaufmännische Vorsicht walten zu lassen.
A8: ►1
A12: ►2 | B12: Eine möglichst zutreffende Planung wird durch folgende Fakten untermauert: 1) welche Daten und Erkenntnisse hat die Markterkundung gebracht? 2) welche Akquisitionswege habe ich für mein Gewerk als richtig erkannt und festgelegt? 3) Welche Ansprache mache ich bei Kunden und Nichtkunden?
B17: Das beigefügte Rechentool geht davon aus, daß Ansprachen regelmäßig in gewisser Anzahl gemacht werden; und daß davon nur Teilmengen für weiterführende Akquisition und für Auftragserteilung in Frage kommen
A18: ►3
B22: Sie erhalten bei Nutzung und Einstellung der Datei auf Ihre Werte wichtige Hindweise zur Anzahl der Ansprachen (neutral ausgedrückt, also Telefonate, Mails, Briefe usw) und zum Zeitbedarf!
A23: ►4
B27: Alle Maßnahmen und Aktionen sollten dann in einem Aktivitäten- und Marketingplan zusammengefasst werden und in monatlichen Teilen abgearbeitet werden!
A29: ►5

Sheet Fachbegriffe
B1: Erläuterungen von Fachbegriffen in den Tabellenblättern
B2: Ertragsvorschau
C4: Stundenverkaufssatz | J4: Mindeststundensatz:
B6: `+1) | C6: PRIVATE KOSTEN | I6: `+1) | J6: PRIVATE KOSTEN
B7: +2) | C7: GEWERBLICHE KOSTEN + WARENEINSATZ | I7: +2) | J7: GEWERBLICHE KOSTEN + WARENEINSATZ
B8: `+3) | C8: 3% RISIKOZUSCHLAG UNTERNEHM. TÄTIGKEIT (SOZIALE SICHERUNG)
B9: +4) | C9: 10% EIGENKAPITALVERZINSUNG
B10: `+5) | C10: KALKULATORISCHE STEUERN | I10: `+5) | J10: KALKULATORISCHE STEUERN
B11: +6) | C11: 5% REINGEWINNANSPRUCH
B12: `+7) | C12: 2% GARANTIE UND GEWÄHRLEISTUNG
B13: +8) | C13: RISIKOZUSCHLAG FÜR SAISON-/SONDERVERKÄUFE / NACHLÄSSE
B14: `+9) | C14: RISIKOZUSCHLAG FÜR UMSATZLOSE ZEIT
C15: dividiert durch Prod. Stunden | J15: dividiert durch Prod. Stunden
C16: dividiert durch Anzahl Prod. MA | J16: dividiert durch Prod. MA
B19: Liquiditätsplan
C21: Vorsteuer:
C23: Material/Waren
B24: + | C24: Anlageninvestitionen
B25: + | C25: Betriebsausgaben
B26: - | C26: Kfz Steuer
B27: - | C27: Versicherungen/Beiträge
B28: - | C28: Zinsen
B29: - | C29: Personalkosten
C30: multipliziert mit 19%
B32: Zusammenfassung
C34: realisierter Stundensatz:
C36: Summe Aufwendungen
B37: - | C37: Material
B38: + | C38: Abschreibungen
B39: + | C39: Gewinn/Verlust
C40: dividiert durch Prod. Stunden
C41: dividiert durch Anzahl Prod. MA
C43: Nettocashflow:
C45: Gewinn/Verlust
B46: + | C46: Abschreibungen
B47: - | C47: Kalk. Steuern
B48: - | C48: Unternehmerlohn

Sheet AnalyseFragen
A1: =Deckblatt!C5 -> Max Mustermann
A3: Umsatz
A7: Liquidität
A13: Wareneinsatz
A17: Kosten o.WE
A21: Prod.Std +MA
A25: Privatentnahme
A29: Gewinn
A33: Kalkulation
A37: Controlling

Sheet Abfolge der Einzelblätter

Sheet ZusammenführErgebn
B1: ZUSAMMENFÜHRUNG VON ERGEBNISZAHLEN
B3: WICHTIGE ERGEBNISZAHLEN | C3: 2025 | D3: 2026 | E3: 2027
B5: Umsätze/Erlöse | C5: ='Ertragsv. 2025'!O3 -> 0 | D5: ='Ertragsv. 2026'!O3 -> 0 | E5: ='Ertragsv. 2027'!O3 -> 0
B7: Wareneinkauf : Umsatz | C7: ='Ertragsv. 2025'!P4/100 -> #DIV/0! | D7: ='Ertragsv. 2026'!P4% -> #DIV/0! | E7: ='Ertragsv. 2027'!P4/100 -> #DIV/0!
B8: Mindestumsatz : Umsatz | C8: ='Ertragsv. 2025'!O3/('Ertragsv. 2025'!M38*12) -> #DIV/0! | D8: ='Ertragsv. 2026'!O3/('Ertragsv. 2026'!M37*12) -> #DIV/0! | E8: ='Ertragsv. 2027'!O3/('Ertragsv. 2027'!M37*12) -> #DIV/0!
B9: Gewinn : Umsatz | C9: ='Ertragsv. 2025'!P23/100 -> #DIV/0! | D9: ='Ertragsv. 2026'!P23/100 -> #DIV/0! | E9: ='Ertragsv. 2027'!P23/100 -> #DIV/0!
B10: Kosten (o. WE) : Umsatz | C10: =('Ertragsv. 2025'!O20-'Ertragsv. 2025'!O4)/'Ertragsv. 2025'!O3 -> #DIV/0! | D10: =('Ertragsv. 2026'!O20-'Ertragsv. 2026'!O4)/'Ertragsv. 2026'!O3 -> #DIV/0! | E10: =('Ertragsv. 2027'!O20-'Ertragsv. 2027'!O4)/'Ertragsv. 2027'!O3 -> #DIV/0!
B12: Durchschn. realisierte Stundensätze | C12: =('Ertragsv. 2025'!O20-'Ertragsv. 2025'!O4+'Ertragsv. 2025'!O22+'Ertragsv. 2025'!O23)/12/'Ertragsv. 2025'!L41/ArbStd_MA!F49 -> 0 | D12: =('Ertragsv. 2026'!O20-'Ertragsv. 2026'!O4+'Ertragsv. 2026'!O22+'Ertragsv. 2026'!O23)/12/'Ertragsv. 2026'!L40/ArbStd_MA!G49 -> 0 | E12: =('Ertragsv. 2027'!O20-'Ertragsv. 2027'!O4+'Ertragsv. 2027'!O22+'Ertragsv. 2027'!O23)/12/'Ertragsv. 2027'!L40/ArbStd_MA!H49 -> 0
B13: Durchschn. notwendige Stundensätze | C13: ='Ertragsv. 2025'!M41 -> 0 | D13: ='Ertragsv. 2026'!M40 -> 0 | E13: ='Ertragsv. 2027'!M40 -> 0
B15: Durchschn.Realisierte Rohaufschläge in % | C15: =IF(Einzelkalk_Handel!D5>0,Einzelkalk_Handel!D5) -> #DIV/0! | D15: =Einzelkalk_Handel!G5 -> #DIV/0! | E15: =Einzelkalk_Handel!J5 -> #DIV/0!
B16: Notwendige Rohaufschläge in % | C16: =Einzelkalk_Handel!D6 -> #DIV/0! | D16: =Einzelkalk_Handel!G6 -> #DIV/0! | E16: =Einzelkalk_Handel!J6 -> #DIV/0!
B18: Gewinn vor Steuern | C18: ='Ertragsv. 2025'!O23 -> 0 | D18: ='Ertragsv. 2026'!O23 -> 0 | E18: ='Ertragsv. 2027'!O23 -> 0
B20: Gewinn nach Steuern | C20: ='Ertragsv. 2025'!O26 -> 0 | D20: ='Ertragsv. 2026'!O26 -> 0 | E20: ='Ertragsv. 2027'!O26 -> 0
B22: Entnahmen d. Unternehmerlohn | C22: ='Ertragsv. 2025'!O27 -> 0 | D22: ='Ertragsv. 2026'!O27 -> 0 | E22: ='Ertragsv. 2027'!O27 -> 0
B24: Ergebnis nach Unternehmerlohn | C24: =C20-C22 -> 0 | D24: =D20-D22 -> 0 | E24: =E20-E22 -> 0
B26: Nettocashflow | C26: ='Ertragsv. 2025'!O23+'Ertragsv. 2025'!O22-'Ertragsv. 2025'!O25-'Ertragsv. 2025'!O27 -> 0 | D26: ='Ertragsv. 2026'!O23+'Ertragsv. 2026'!O22-'Ertragsv. 2026'!O25-'Ertragsv. 2026'!O27 -> 0 | E26: ='Ertragsv. 2027'!O23+'Ertragsv. 2027'!O22-'Ertragsv. 2027'!O25-'Ertragsv. 2027'!O27 -> 0
B28: Bereits für Tilgung verplante Beträge | C28: =Finanz_AfA_Investitionen!$G$38*12 -> 0 | D28: =Finanz_AfA_Investitionen!$G$38*12 -> 0 | E28: =Finanz_AfA_Investitionen!$G$38*12 -> 0
B30: Noch verfügbare Finanzmittel | C30: =C26-C28 -> 0 | D30: =D26-D28 -> 0 | E30: =E26-E28 -> 0
B34: Realisierte Stundensätze im Jahresverlauf
B35: Aus Vorschau
B36: Januar
B37: Februar
B38: März
B39: April
B40: Mai
B41: Juni
B42: Juli
B43: August
B44: September
B45: Oktober
... B62: Dezember

Sheet Privatentnahmen
O1: Hinweise und Plausibilitäten für Darlehensprogramm Microstarter der N-Bank
B2: PRIVATENTNAHME | D2: Bei Kostensprüngen in Folgejahren sollte ein Eingriff in die jeweiligen Formeln erfolgen . Fragen Sie Ihren Berater/Dozenten! | U2: Statistische Durchschnittsrechnung 2013
C4: PRIVATENTNAHME | D4: =ZusammenführErgebn!C3 -> 2025 | F4: =ZusammenführErgebn!D3 -> 2026 | H4: =ZusammenführErgebn!E3 -> 2027 | J4: 4. Jahr | M4: ERLÄUTERUNGEN | V4: =ZusammenführErgebn!U3 -> 0
E5: 12 | F5: Teuerung: | G5: 0.02 | H5: Teuerung: | I5: 0.03 | J5: Teuerung: | K5: 0.05 | N5: Info | W5: 12 | X5: %
D6: MONAT | E6: JAHR | F6: MONAT | G6: JAHR | H6: MONAT | I6: JAHR | J6: Monat | K6: Jahr | N6: MiStart | V6: MONAT | W6: JAHR
C7: Miete/Zins-Tilgung | E7: =D7*$E$5 -> 0 | F7: =D7*(1+G$5) -> 0 | G7: =F7*12 -> 0 | H7: =F7*(1+I$5) -> 0 | I7: =H7*12 -> 0 | J7: =H7*(1+K$5) -> 0 | K7: =J7*12 -> 0 | M7: nur private Wohnungsmiete | U7: Miete/Zins-Tilgung | V7: 845 | W7: =V7*$E$5 -> 10140 | X7: =V7/$V$29% -> 34.517974
C8: Nebenkosten | E8: =D8*$E$5 -> 0 | F8: =D8*(1+G$5) -> 0 | G8: =F8*12 -> 0 | H8: =F8*(1+I$5) -> 0 | I8: =H8*12 -> 0 | J8: =H8*(1+K$5) -> 0 | K8: =J8*12 -> 0 | M8: Heizung, Wasser, Strom, GEZ | U8: Nebenkosten | W8: =V8*$E$5 -> 0 | X8: =V8/$V$29% -> 0
C9: Telefon, Handy, Internet | E9: =D9*$E$5 -> 0 | F9: =D9*(1+G$5) -> 0 | G9: =F9*12 -> 0 | H9: =F9*(1+I$5) -> 0 | I9: =H9*12 -> 0 | J9: =H9*(1+K$5) -> 0 | K9: =J9*12 -> 0 | U9: Telefon, Handy, Internet | W9: =V9*$E$5 -> 0 | X9: =V9/$V$29% -> 0
B10: 1 | C10: SUMME WOHNKOSTEN | D10: =SUM(D7:D9) -> 0 | E10: =SUM(E7:E9) -> 0 | F10: =SUM(F7:F9) -> 0 | G10: =SUM(G7:G9) -> 0 | H10: =SUM(H7:H9) -> 0 | I10: =SUM(I7:I9) -> 0 | J10: =SUM(J7:J9) -> 0 | K10: =SUM(K7:K9) -> 0 | T10: 1 | U10: SUMME WOHNKOSTEN | V10: =SUM(V7:V9) -> 845 | W10: =SUM(W7:W9) -> 10140 | X10: =V10/$V$29% -> 34.517974
C11: Haushaltsgeld | E11: =D11*$E$5 -> 0 | F11: =D11*(1+G$5) -> 0 | G11: =F11*12 -> 0 | H11: =F11*(1+I$5) -> 0 | I11: =H11*12 -> 0 | J11: =H11*(1+K$5) -> 0 | K11: =J11*12 -> 0 | M11: Lebensmittel, Getränke | U11: Haushaltsgeld | V11: 486 | W11: =V11*$E$5 -> 5832 | X11: =V11/$V$29% -> 19.852941
C12: Kleidung, Körperpflege | E12: =D12*$E$5 -> 0 | F12: =D12*(1+G$5) -> 0 | G12: =F12*12 -> 0 | H12: =F12*(1+I$5) -> 0 | I12: =H12*12 -> 0 | J12: =H12*(1+K$5) -> 0 | K12: =J12*12 -> 0 | U12: Kleidung, Körperpflege | W12: =V12*$E$5 -> 0 | X12: =V12/$V$29% -> 0
C13: Freizeit, Sport, Hobby | E13: =D13*$E$5 -> 0 | F13: =D13*(1+G$5) -> 0 | G13: =F13*12 -> 0 | H13: =F13*(1+I$5) -> 0 | I13: =H13*12 -> 0 | J13: =H13*(1+K$5) -> 0 | K13: =J13*12 -> 0 | U13: Freizeit, Sport, Hobby | V13: 261 | W13: =V13*$E$5 -> 3132 | X13: =V13/$V$29% -> 10.661765
B14: 2 | C14: SUMME LEBENSHALTUNG | D14: =SUM(D11:D13) -> 0 | E14: =SUM(E11:E13) -> 0 | F14: =SUM(F11:F13) -> 0 | G14: =SUM(G11:G13) -> 0 | H14: =SUM(H11:H13) -> 0 | I14: =SUM(I11:I13) -> 0 | J14: =SUM(J11:J13) -> 0 | K14: =SUM(K11:K13) -> 0 | T14: 2 | U14: SUMME LEBENSHALTUNG | V14: =SUM(V11:V13) -> 747 | W14: =SUM(W11:W13) -> 8964 | X14: =V14/$V$29% -> 30.514706
C15: Krankenversicherung (KV+PV) | E15: =D15*$E$5 -> 0 | F15: =D15*(1+G$5) -> 0 | G15: =F15*12 -> 0 | H15: =F15*(1+I$5) -> 0 | I15: =H15*12 -> 0 | J15: =H15*(1+K$5) -> 0 | K15: =J15*12 -> 0 | M15: Welche Risiken sind zu versichern? | N15: KV+PV | O15: ='Ertragsv. 2025'!O23*Privatentnahmen!Q15/12 -> 0 | Q15: 0.1755 | U15: Krankenversicherung (KV+PV) | W15: =V15*$E$5 -> 0 | X15: =V15/$V$29% -> 0
C16: Berufsunfähigkeit, Unfall | E16: =D16*$E$5 -> 0 | F16: =D16*(1+G$5) -> 0 | G16: =F16*12 -> 0 | H16: =F16*(1+I$5) -> 0 | I16: =H16*12 -> 0 | J16: =H16*(1+K$5) -> 0 | K16: =J16*12 -> 0 | U16: Berufsunfähigkeit, Unfall | W16: =V16*$E$5 -> 0 | X16: =V16/$V$29% -> 0
C17: Altersvorsorge | E17: =D17*$E$5 -> 0 | F17: =D17*(1+G$5) -> 0 | G17: =F17*12 -> 0 | H17: =F17*(1+I$5) -> 0 | I17: =H17*12 -> 0 | J17: =H17*(1+K$5) -> 0 | K17: =J17*12 -> 0 | M17: Wie hoch muss die Versorgung sein? | N17: RV | O17: 85.05 | R17: Regelsätze nach SGB II +10% | U17: Altersvorsorge | V17: 300 | W17: =V17*$E$5 -> 3600 | X17: =V17/$V$29% -> 12.254902
C18: Sonst. Versicherungen | D18: 0 | E18: =D18*$E$5 -> 0 | F18: =D18*(1+G$5) -> 0 | G18: =F18*12 -> 0 | H18: =F18*(1+I$5) -> 0 | I18: =H18*12 -> 0 | J18: =H18*(1+K$5) -> 0 | K18: =J18*12 -> 0 | M18: Haftpflicht, Hausrat, Rechtsschutz | U18: Sonst. Versicherungen | V18: 56 | W18: =V18*$E$5 -> 672 | X18: =V18/$V$29% -> 2.2875817
B19: 3 | C19: SUMME VERSICHERUNGEN | D19: =SUM(D15:D18) -> 0 | E19: =SUM(E15:E18) -> 0 | F19: =SUM(F15:F18) -> 0 | G19: =SUM(G15:G18) -> 0 | H19: =SUM(H15:H18) -> 0 | I19: =SUM(I15:I18) -> 0 | J19: =SUM(J15:J18) -> 0 | K19: =SUM(K15:K18) -> 0 | T19: 3 | U19: SUMME VERSICHERUNGEN | V19: =SUM(V15:V18) -> 356 | W19: =SUM(W15:W18) -> 4272 | X19: =V19/$V$29% -> 14.542484
C20: KfZ-Kosten | E20: =D20*$E$5 -> 0 | F20: =D20*(1+G$5) -> 0 | G20: =F20*12 -> 0 | H20: =F20*(1+I$5) -> 0 | I20: =H20*12 -> 0 | J20: =H20*(1+K$5) -> 0 | K20: =J20*12 -> 0 | M20: Steuern, Versicherung, lfd. Kosten | O20: =P20*Q20 -> 0 | P20: 0 | Q20: =399*110% -> 438.9 | U20: KfZ-Kosten | W20: =V20*$E$5 -> 0 | X20: =V20/$V$29% -> 0
C21: Bahncard, ÖPNV | E21: =D21*$E$5 -> 0 | F21: =D21*(1+G$5) -> 0 | G21: =F21*12 -> 0 | H21: =F21*(1+I$5) -> 0 | I21: =H21*12 -> 0 | J21: =H21*(1+K$5) -> 0 | K21: =J21*12 -> 0 | O21: =P21*Q21 -> 792 | P21: 2 | Q21: =360*110% -> 396 | U21: Bahncard, ÖPNV | W21: =V21*$E$5 -> 0 | X21: =V21/$V$29% -> 0
B22: 4 | C22: SUMME FAHRTKOSTEN | D22: =SUM(D20:D21) -> 0 | E22: =SUM(E20:E21) -> 0 | F22: =SUM(F20:F21) -> 0 | G22: =SUM(G20:G21) -> 0 | H22: =SUM(H20:H21) -> 0 | I22: =SUM(I20:I21) -> 0 | J22: =SUM(J20:J21) -> 0 | K22: =SUM(K20:K21) -> 0 | O22: =P22*Q22 -> 0 | Q22: =320*110% -> 352 | T22: 4 | U22: SUMME FAHRTKOSTEN | V22: =SUM(V20:V21) -> 0 | W22: =SUM(W20:W21) -> 0 | X22: =V22/$V$29% -> 0
C23: Unterhaltsverpflichtungen | E23: =D23*$E$5 -> 0 | F23: =D23*(1+G$5) -> 0 | G23: =F23*12 -> 0 | H23: =F23*(1+I$5) -> 0 | I23: =H23*12 -> 0 | J23: =H23*(1+K$5) -> 0 | K23: =J23*12 -> 0 | O23: =P23*Q23 -> 0 | Q23: =302*110% -> 332.2 | U23: Unterhaltsverpflichtungen | W23: =V23*$E$5 -> 0 | X23: =V23/$V$29% -> 0
C24: Private Kredite, Kontoführung | E24: =D24*$E$5 -> 0 | F24: =D24*(1+G$5) -> 0 | G24: =F24*12 -> 0 | H24: =F24*(1+I$5) -> 0 | I24: =H24*12 -> 0 | J24: =H24*(1+K$5) -> 0 | K24: =J24*12 -> 0 | O24: =P24*Q24 -> 293.7 | P24: 1 | Q24: =267*110% -> 293.7 | U24: Private Kredite, Kontoführung | V24: 57 | W24: =V24*$E$5 -> 684 | X24: =V24/$V$29% -> 2.3284314
C25: Kindergarten, Schule | E25: =D25*$E$5 -> 0 | F25: =D25*(1+G$5) -> 0 | G25: =F25*12 -> 0 | H25: =F25*(1+I$5) -> 0 | I25: =H25*12 -> 0 | J25: =H25*(1+K$5) -> 0 | K25: =J25*12 -> 0 | O25: =P25*Q25 -> 257.4 | P25: 1 | Q25: =234*110% -> 257.4 | U25: Kindergarten, Schule | W25: =V25*$E$5 -> 0 | X25: =V25/$V$29% -> 0
C26: Sonstiges | D26: 0 | E26: =D26*$E$5 -> 0 | F26: =D26*(1+G$5) -> 0 | G26: =F26*12 -> 0 | H26: =F26*(1+I$5) -> 0 | I26: =H26*12 -> 0 | U26: Sonstiges/Kauf v.Möbeln usw | V26: 124 | W26: =V26*$E$5 -> 1488 | X26: =V26/$V$29% -> 5.0653595
C27: Sparen | E27: =D27*$E$5 -> 0 | F27: =D27*(1+G$5) -> 0 | G27: =F27*12 -> 0 | H27: =F27*(1+I$5) -> 0 | I27: =H27*12 -> 0 | J27: =H27*(1+K$5) -> 0 | K27: =J27*12 -> 0 | M27: Urlaub, Anschaffungen | U27: Sparen | V27: 319 | W27: =V27*$E$5 -> 3828 | X27: =V27/$V$29% -> 13.031046
B28: 5 | C28: SUMME SONST. AUSGABEN | D28: =SUM(D23:D27) -> 0 | E28: =SUM(E23:E27) -> 0 | F28: =SUM(F23:F27) -> 0 | G28: =SUM(G23:G27) -> 0 | H28: =SUM(H23:H27) -> 0 | I28: =SUM(I23:I27) -> 0 | J28: =SUM(J23:J27) -> 0 | K28: =SUM(K23:K27) -> 0 | T28: 5 | U28: SUMME SONST. AUSGABEN | V28: =SUM(V23:V27) -> 500 | W28: =SUM(W23:W27) -> 6000 | X28: =V28/$V$29% -> 20.424837
C29: SUMME AUSGABEN | D29: =SUM(D28,D22,D19,D14,D10) -> 0 | E29: =SUM(E28,E22,E19,E14,E10) -> 0 | F29: =SUM(F28,F22,F19,F14,F10) -> 0 | G29: =SUM(G28,G22,G19,G14,G10) -> 0 | H29: =SUM(H28,H22,H19,H14,H10) -> 0 | I29: =SUM(I28,I22,I19,I14,I10) -> 0 | J29: =SUM(J28,J22,J19,J14,J10) -> 0 | K29: =SUM(K28,K22,K19,K14,K10) -> 0 | O29: =SUM(O7:O28) -> 1428.15 | U29: SUMME AUSGABEN | V29: =SUM(V28,V22,V19,V14,V10) -> 2448 | W29: =SUM(W28,W22,W19,W14,W10) -> 29376 | X29: =V29/$V$29% -> 100
C30: Kindergeld, Unterhalt | D30: 0 | E30: =D30*$E$5 -> 0 | F30: =D30 -> 0 | G30: =F30*12 -> 0 | H30: =F30 -> 0 | I30: =H30*12 -> 0 | J30: =H30 -> 0 | K30: =J30*12 -> 0
C31: Netto-Einkommen PartnerIn | E31: =D31*$E$5 -> 0 | F31: =D31 -> 0 | G31: =F31*12 -> 0 | H31: =F31 -> 0 | I31: =H31*12 -> 0 | J31: =H31 -> 0 | K31: =J31*12 -> 0
C32: Nebentätigkeit, Sonstiges | E32: =D32*$E$5 -> 0 | F32: =D32 -> 0 | G32: =F32*12 -> 0 | H32: =F32 -> 0 | I32: =H32*12 -> 0 | J32: =H32 -> 0 | K32: =J32*12 -> 0
C33: SUMME EINKOMMEN | D33: =SUM(D30:D32) -> 0 | E33: =SUM(E30:E32) -> 0 | F33: =SUM(F30:F32) -> 0 | G33: =SUM(G30:G32) -> 0 | H33: =SUM(H30:H32) -> 0 | I33: =SUM(I30:I32) -> 0 | J33: =SUM(J30:J32) -> 0 | K33: =SUM(K30:K32) -> 0
J34: =J46*J47/12 -> 0 | K34: =J34*12 -> 0
C35: SUMME DER PRIVATENTNAHMEN | D35: =D29-D33+D34 -> 0 | E35: =E29-E33+E34 -> 0 | F35: =F29-F33+F34 -> 0 | G35: =G29-G33+G34 -> 0 | H35: =H29-H33+H34 -> 0 | I35: =I29-I33+I34 -> 0 | J35: =J29-J33+J34 -> 0 | K35: =K29-K33+K34 -> 0

Sheet Ertragsv. 2025
B1: ERTRAGSVORSCHAU 1. Planjahr | E1: =ZusammenführErgebn!C3 -> 2025 | H1: =Deckblatt!C5 -> Max Mustermann
A2: Durchschn. Warenein-satz | B2: ALLE ANGABEN NETTO | C2: =VLOOKUP(Deckblatt!$C$8,Deckblatt!$G$99:$R$110,1,FALSE) -> Jan. | D2: =VLOOKUP(Deckblatt!$C$8,Deckblatt!$G$99:$R$110,2,FALSE) -> Febr. | E2: =VLOOKUP(Deckblatt!$C$8,Deckblatt!$G$99:$R$110,3,FALSE) -> März | F2: =VLOOKUP(Deckblatt!$C$8,Deckblatt!$G$99:$R$110,4,FALSE) -> April | G2: =VLOOKUP(Deckblatt!$C$8,Deckblatt!$G$99:$R$110,5,FALSE) -> Mai | H2: =VLOOKUP(Deckblatt!$C$8,Deckblatt!$G$99:$R$110,6,FALSE) -> Juni | I2: =VLOOKUP(Deckblatt!$C$8,Deckblatt!$G$99:$R$110,7,FALSE) -> Juli | J2: =VLOOKUP(Deckblatt!$C$8,Deckblatt!$G$99:$R$110,8,FALSE) -> Aug. | K2: =VLOOKUP(Deckblatt!$C$8,Deckblatt!$G$99:$R$110,9,FALSE) -> Sept. | L2: =VLOOKUP(Deckblatt!$C$8,Deckblatt!$G$99:$R$110,10,FALSE) -> Okt. | M2: =VLOOKUP(Deckblatt!$C$8,Deckblatt!$G$99:$R$110,11,FALSE) -> Nov. | N2: =VLOOKUP(Deckblatt!$C$8,Deckblatt!$G$99:$R$110,12,FALSE) -> Dez. | O2: SUMME | P2: % | Q2: Branchen-vergl. | R2: ERLÄUTERUNGEN / KOMMENTARE
B3: Umsatz/ Erlöse | C3: ='UmstzPlan 1.-3.Jahr'!E19 -> 0 | D3: ='UmstzPlan 1.-3.Jahr'!G19 -> 0 | E3: ='UmstzPlan 1.-3.Jahr'!I19 -> 0 | F3: ='UmstzPlan 1.-3.Jahr'!K19 -> 0 | G3: ='UmstzPlan 1.-3.Jahr'!M19 -> 0 | H3: ='UmstzPlan 1.-3.Jahr'!O19 -> 0 | I3: ='UmstzPlan 1.-3.Jahr'!Q19 -> 0 | J3: ='UmstzPlan 1.-3.Jahr'!S19 -> 0 | K3: ='UmstzPlan 1.-3.Jahr'!U19 -> 0 | L3: ='UmstzPlan 1.-3.Jahr'!W19 -> 0 | M3: ='UmstzPlan 1.-3.Jahr'!Y19 -> 0 | N3: ='UmstzPlan 1.-3.Jahr'!AA19 -> 0 | O3: =SUM(C3:N3) -> 0 | P3: 100
A4: 0.23 | B4: ./.Materialeinsatz | C4: =C3*$A$4 -> 0 | D4: =D3*$A$4 -> 0 | E4: =E3*$A$4 -> 0 | F4: =F3*$A$4 -> 0 | G4: =G3*$A$4 -> 0 | H4: =H3*$A$4 -> 0 | I4: =I3*$A$4 -> 0 | J4: =J3*$A$4 -> 0 | ... N4: =N3*$A$4 -> 0 | O4: =SUM(C4:N4) -> 0 | P4: =O4/$O$3% -> #DIV/0! | R4: Einkaufsliste erarbeiten!
B5: ./. Kosten:
B6: Raumkosten | O6: =SUM(C6:N6) -> 0 | P6: =O6/$O$3% -> #DIV/0! | R6: Beispiel: Büromiete 12% der Wohnung
B7: Kfz Steuer | O7: =SUM(C7:N7) -> 0 | P7: =O7/$O$3% -> #DIV/0! | R7: anteilig gem.Nutzung
B8: Kraftfahrzeugkosten | O8: =SUM(C8:N8) -> 0 | P8: =O8/$O$3% -> #DIV/0! | R8: gem.geschätz.mtl Kilometerleistung
B9: Leasing | C9: =Finanz_AfA_Investitionen!$H28 -> 0 | D9: =Finanz_AfA_Investitionen!$H28 -> 0 | E9: =Finanz_AfA_Investitionen!$H28 -> 0 | F9: =Finanz_AfA_Investitionen!$H28 -> 0 | G9: =Finanz_AfA_Investitionen!$H28 -> 0 | H9: =Finanz_AfA_Investitionen!$H28 -> 0 | I9: =Finanz_AfA_Investitionen!$H28 -> 0 | J9: =Finanz_AfA_Investitionen!$H28 -> 0 | ... N9: =Finanz_AfA_Investitionen!$H28 -> 0 | O9: =SUM(C9:N9) -> 0 | P9: =O9/$O$3% -> #DIV/0!
B10: Werbe- und Reisekosten | O10: =SUM(C10:N10) -> 0 | P10: =O10/$O$3% -> #DIV/0! | R10: Marketing-Aktivitätenplan erstellt?
B11: Telefon, Telefax, Internet | O11: =SUM(C11:N11) -> 0 | P11: =O11/$O$3% -> #DIV/0!
B12: Bürobedarf | O12: =SUM(C12:N12) -> 0 | P12: =O12/$O$3% -> #DIV/0!
B13: Rechts- und Beratungskosten | O13: =SUM(C13:N13) -> 0 | P13: =O13/$O$3% -> #DIV/0! | R13: Steuerberater vorhanden? Beitrag Berufsverb.
B14: Versicherungen/Beiträge | O14: =SUM(C14:N14) -> 0 | P14: =O14/$O$3% -> #DIV/0! | R14: Was muss versichert werden? Welche Risiken
B15: Reparaturen/Instandhaltung | O15: =SUM(C15:N15) -> 0 | P15: =O15/$O$3% -> #DIV/0!
B16: sonstiger Betriebsaufwand | O16: =SUM(C16:N16) -> 0 | P16: =O16/$O$3% -> #DIV/0!
B17: Zinsaufwand | C17: =Finanz_AfA_Investitionen!$F38-Finanz_AfA_Investitionen!$F37+'Mikrostarter Geschäftsplan'!D16 -> 0 | D17: =Finanz_AfA_Investitionen!$F38-Finanz_AfA_Investitionen!$F37+'Mikrostarter Geschäftsplan'!D17 -> 0 | E17: =Finanz_AfA_Investitionen!$F38-Finanz_AfA_Investitionen!$F37+'Mikrostarter Geschäftsplan'!D18 -> 0 | F17: =Finanz_AfA_Investitionen!$F38-Finanz_AfA_Investitionen!$F37+'Mikrostarter Geschäftsplan'!D20 -> 0 | G17: =Finanz_AfA_Investitionen!$F38-Finanz_AfA_Investitionen!$F37+'Mikrostarter Geschäftsplan'!D21 -> 0 | H17: =Finanz_AfA_Investitionen!$F38-Finanz_AfA_Investitionen!$F37+'Mikrostarter Geschäftsplan'!D22 -> 0 | I17: =Finanz_AfA_Investitionen!$F38-Finanz_AfA_Investitionen!$F37+'Mikrostarter Geschäftsplan'!D24 -> 0 | J17: =Finanz_AfA_Investitionen!$F38-Finanz_AfA_Investitionen!$F37+'Mikrostarter Geschäftsplan'!D25 -> 0 | K17: =Finanz_AfA_Investitionen!$F38-Finanz_AfA_Investitionen!$F37+'Mikrostarter Geschäftsplan'!D26 -> 0 | L17: =Finanz_AfA_Investitionen!$F38-Finanz_AfA_Investitionen!$F37+'Mikrostarter Geschäftsplan'!D28 -> 0 | M17: =Finanz_AfA_Investitionen!$F38-Finanz_AfA_Investitionen!$F37+'Mikrostarter Geschäftsplan'!D29 -> 0 | N17: =Finanz_AfA_Investitionen!$F38-Finanz_AfA_Investitionen!$F37+'Mikrostarter Geschäftsplan'!D30 -> 0 | O17: =SUM(C17:N17) -> 0 | P17: =O17/$O$3% -> #DIV/0! | R17: Investitiosplanung vorhanden?
B18: PersonalkostenAGA | C18: =ArbStd_MA!$I$76+ArbStd_MA!$I$81 -> 0 | D18: =ArbStd_MA!$I$76+ArbStd_MA!$I$81 -> 0 | E18: =ArbStd_MA!$I$76+ArbStd_MA!$I$81 -> 0 | F18: =ArbStd_MA!$I$76+ArbStd_MA!$I$81 -> 0 | G18: =ArbStd_MA!$I$76+ArbStd_MA!$I$81 -> 0 | H18: =ArbStd_MA!$I$76+ArbStd_MA!$I$81 -> 0 | I18: =ArbStd_MA!$I$76+ArbStd_MA!$I$81 -> 0 | J18: =ArbStd_MA!$I$76+ArbStd_MA!$I$81 -> 0 | ... N18: =ArbStd_MA!$I$76+ArbStd_MA!$I$81 -> 0 | O18: =SUM(C18:N18) -> 0 | P18: =O18/$O$3% -> #DIV/0!
B19: Einmalige (Gründungs)kosten | O19: =SUM(C19:N19) -> 0 | P19: =O19/$O$3% -> #DIV/0!
B20: Summe Aufwendungen | C20: =SUM(C4:C19) -> 0 | D20: =SUM(D4:D19) -> 0 | E20: =SUM(E4:E19) -> 0 | F20: =SUM(F4:F19) -> 0 | G20: =SUM(G4:G19) -> 0 | H20: =SUM(H4:H19) -> 0 | I20: =SUM(I4:I19) -> 0 | J20: =SUM(J4:J19) -> 0 | ... N20: =SUM(N4:N19) -> 0 | O20: =SUM(C20:N20) -> 0 | P20: =O20/$O$3% -> #DIV/0!
B21: Betriebsergebnis | C21: =C3-C20 -> 0 | D21: =D3-D20 -> 0 | E21: =E3-E20 -> 0 | F21: =F3-F20 -> 0 | G21: =G3-G20 -> 0 | H21: =H3-H20 -> 0 | I21: =I3-I20 -> 0 | J21: =J3-J20 -> 0 | ... N21: =N3-N20 -> 0 | O21: =SUM(C21:N21) -> 0 | P21: =O21/$O$3% -> #DIV/0!
B22: ./. Abschreibungen | C22: =Finanz_AfA_Investitionen!$F28 -> 0 | D22: =Finanz_AfA_Investitionen!$F28 -> 0 | E22: =Finanz_AfA_Investitionen!$F28 -> 0 | F22: =Finanz_AfA_Investitionen!$F28 -> 0 | G22: =Finanz_AfA_Investitionen!$F28 -> 0 | H22: =Finanz_AfA_Investitionen!$F28 -> 0 | I22: =Finanz_AfA_Investitionen!F28 -> 0 | J22: =Finanz_AfA_Investitionen!F28 -> 0 | K22: =Finanz_AfA_Investitionen!F28 -> 0 | L22: =Finanz_AfA_Investitionen!F28 -> 0 | M22: =Finanz_AfA_Investitionen!F28 -> 0 | N22: =Finanz_AfA_Investitionen!F28 -> 0 | O22: =SUM(C22:N22) -> 0 | P22: =O22/$O$3% -> #DIV/0!
B23: Gewinn/Verlust | C23: =C21-C22 -> 0 | D23: =D21-D22 -> 0 | E23: =E21-E22 -> 0 | F23: =F21-F22 -> 0 | G23: =G21-G22 -> 0 | H23: =H21-H22 -> 0 | I23: =I21-I22 -> 0 | J23: =J21-J22 -> 0 | ... O23: =O21-O22 -> 0 | P23: =O23/$O$3% -> #DIV/0!
B24: Aufgelaufene Werte | C24: =C23 -> 0 | D24: =C23+D23 -> 0 | E24: =C23+D23+E23 -> 0 | F24: =C23+D23+E23+F23 -> 0 | G24: =C23+D23+E23+F23+G23 -> 0 | H24: =C23+D23+E23+F23+G23+H23 -> 0 | I24: =C23+D23+E23+F23+G23+H23+I23 -> 0 | J24: =C23+D23+E23+F23+G23+H23+I23+J23 -> 0 | K24: =C23+D23+E23+F23+G23+H23+I23+J23+K23 -> 0 | L24: =C23+D23+E23+F23+G23+H23+I23+J23+K23+L23 -> 0 | M24: =C23+D23+E23+F23+G23+H23+I23+J23+K23+L23+M23 -> 0 | N24: =C23+D23+E23+F23+G23+H23+I23+J23+K23+L23+M23+N23 -> 0 | P24: =O24/$O$3% -> #DIV/0!
B25: Kalk. Steuern(ESt/Soli/GeSt) | C25: =IF($K$32=1,C23*$I$32,IF($K$32=2,C23*$I$33)) -> 0 | D25: =IF($K$32=1,D23*$I$32,IF($K$32=2,D23*$I$33)) -> 0 | E25: =IF($K$32=1,E23*$I$32,IF($K$32=2,E23*$I$33)) -> 0 | F25: =IF($K$32=1,F23*$I$32,IF($K$32=2,F23*$I$33)) -> 0 | G25: =IF($K$32=1,G23*$I$32,IF($K$32=2,G23*$I$33)) -> 0 | H25: =IF($K$32=1,H23*$I$32,IF($K$32=2,H23*$I$33)) -> 0 | I25: =IF($K$32=1,I23*$I$32,IF($K$32=2,I23*$I$33)) -> 0 | J25: =IF($K$32=1,J23*$I$32,IF($K$32=2,J23*$I$33)) -> 0 | ... N25: =IF($K$32=1,N23*$I$32,IF($K$32=2,N23*$I$33)) -> 0 | O25: =SUM(C25:N25) -> 0 | P25: =O25/$O$3% -> #DIV/0!
B26: Gewinn/Verlust n.Steuern | C26: =C23-C25 -> 0 | D26: =D23-D25 -> 0 | E26: =E23-E25 -> 0 | F26: =F23-F25 -> 0 | G26: =G23-G25 -> 0 | H26: =H23-H25 -> 0 | I26: =I23-I25 -> 0 | J26: =J23-J25 -> 0 | ... N26: =N23-N25 -> 0 | O26: =SUM(C26:N26) -> 0 | P26: =O26/$O$3% -> #DIV/0!
B27: UnternehmerInnen-Lohn | C27: =$M44 -> 0 | D27: =$M44 -> 0 | E27: =$M44 -> 0 | F27: =$M44 -> 0 | G27: =$M44 -> 0 | H27: =$M44 -> 0 | I27: =$M44 -> 0 | J27: =$M44 -> 0 | ... N27: =$M44 -> 0 | O27: =SUM(C27:N27) -> 0 | P27: =O27/$O$3% -> #DIV/0!
B28: Darstellung Risikobetrag Umsatzlose Zeit | L28: in % vom Umsatz | O28: =(O20-O4+O22)*Q43 -> 0 | P28: =O28/$O$3% -> #DIV/0!
B29: Darstellung Risikobetrag Saisonverkäufe | L29: in % vom Wareneinkauf | O29: =O4*Q42 -> 0 | P29: =O29/$O$3% -> #DIV/0!
B31: Steuern individuell | C31: je nach Einkommen für den Mindeststundensatz | I31: =C32+E32 -> 0.0844
B32: Steuern Einzelfirma | C32: 0.08 | D32: EST | E32: =C32*5.5% -> 0.0044 | F32: Soli | G32: 0 | H32: GeSt | I32: =C32+E32+G32 -> 0.0844 | K32: 1
B33: Steuern GmbH | C33: 0.15 | D33: KöSt | E33: =C33*5.5% -> 0.00825 | F33: Soli | G33: 0.14 | H33: GeSt | I33: =C33+E33+G33 -> 0.29825
B36: GESAMTKALKULATION | C36: 1) PRIVATE KOSTEN + 2) GEWERBLICHE KOSTEN + WARENEINSATZ + 3) 3% RISIKOZUSCHLAG UNTERNEHM. TÄTIGKEIT (SOZIALE SICHERUNG) + 4) 10% EIGENKAPITALVERZINSUNG + 5) KALKULATORISCHE STEUERN + 6) 5% REINGEWINNANSPRUCH ) +7) 2% RISIKOZUSCHLAG FÜR GARANTIE / GEWÄHRLEISTUNG/SCHWUND UND VORSORGE FÜR FORDERUNGSVERLUSTE, +8) RISIKOZUSCHLAG FÜR SAISON-/SONDERVERKÄUFE / NACHLÄSSE +9) RISIKOZUSCHLAG FÜR UNTERAUSLASTUNG UND UMSATZLOSE ZEIT
C37: 1) | D37: + 2) | E37: + 3) | F37: + 4) | G37: + 5) | H37: + 6) | I37: + 7) | J37: +8) | K37: +9) | L37: prod. Arbeitstd. | M37: Mindestumsatz
B38: Mindestumsatz | C38: =Privatentnahmen!D35 -> 0 | D38: =(O20+O22)/12 -> 0 | E38: =(O3/12)*Q38 -> 0 | F38: =(Finanz_AfA_Investitionen!C31*'Ertragsv. 2025'!Q39)/12 -> 0 | G38: =O25/12 -> 0 | H38: =O3/12*Q40 -> 0 | I38: =O3/12*Q41 -> 0 | J38: =O29/12 -> 0 | K38: =IF(O4>1,(O28/12),IF(O4<1,0)) -> 0 | M38: =SUM(C38:K38) -> 0 | P38: 3) | Q38: 0.03
C39: 1) | D39: + 2a) | E39: + 3) | F39: + 4) | G39: + 5) | H39: + 6) | I39: +7) | J39: +8) | K39: +9) | L39: =IF(ArbStd_MA!$E$33>=1,ArbStd_MA!$E$33,IF(ArbStd_MA!$E$33<=1,ArbStd_MA!$D$23)) -> 144 | M39: Stundensatz | P39: 4) | Q39: 0.05
B40: Mindeststundensatz | C40: =Privatentnahmen!D35 -> 0 | D40: =(O20-O4+O22)/12 -> 0 | G40: =C40*I31 -> 0 | L40: =IF(ArbStd_MA!$E$33>=1,ArbStd_MA!$E$33,IF(ArbStd_MA!$E$33<=1,ArbStd_MA!$D$23)) -> 144 | M40: =(C40+D40+G40+K40)/L40/ArbStd_MA!F49 -> 0 | P40: 6) | Q40: 0.05
B41: Stundenverkaufssatz | C41: =Privatentnahmen!D35 -> 0 | D41: =D40 -> 0 | E41: =(O3/12)*Q38 -> 0 | F41: =(Finanz_AfA_Investitionen!C31*'Ertragsv. 2025'!Q39)/12 -> 0 | G41: =O25/12 -> 0 | H41: =O3/12*Q40 -> 0 | I41: =O3/12*Q41 -> 0 | L41: =IF(ArbStd_MA!$E$33>=1,ArbStd_MA!$E$33,IF(ArbStd_MA!$E$33<=1,ArbStd_MA!$D$23)) -> 144 | M41: =(C41+D41+E41+F41+G41+H41+I41+J41+K41)/L41/ArbStd_MA!F49 -> 0 | P41: 7) | Q41: 0.02
B42: relative Stundensatzdifferenz | M42: =ROUND((M41-M40)/M40*100,1)& " %" -> #DIV/0! | P42: 8) | Q42: 0.1
B43: Rohaufschlag im Handel % | C43: =C41 -> 0 | D43: =D41 -> 0 | E43: =E41 -> 0 | F43: =F41 -> 0 | G43: =G41 -> 0 | H43: =H41 -> 0 | I43: =I41 -> 0 | J43: =J38 -> 0 | K43: =K38 -> 0 | M43: =IF(O4<1,0,(C43+D43+E43+F43+G43+H43+I43+J43+K43)*100*12/O4) -> 0 | P43: 9) | Q43: 0.15
B44: Unternehmer/innen-Lohn | C44: =Privatentnahmen!D35 -> 0 | E44: =(O3/12)*Q38 -> 0 | F44: =F38 -> 0 | M44: =C44+E44+F44+H44 -> 0

Sheet Ertragsv. 2026
B1: ERTRAGSVORSCHAU 2.Planjahr | E1: =ZusammenführErgebn!D3 -> 2026 | H1: =Deckblatt!C5 -> Max Mustermann
A2: Durchschn. Warenein-satz | B2: ALLE ANGABEN NETTO | C2: ='Ertragsv. 2025'!C2 -> Jan. | D2: ='Ertragsv. 2025'!D2 -> Febr. | E2: ='Ertragsv. 2025'!E2 -> März | F2: ='Ertragsv. 2025'!F2 -> April | G2: ='Ertragsv. 2025'!G2 -> Mai | H2: ='Ertragsv. 2025'!H2 -> Juni | I2: ='Ertragsv. 2025'!I2 -> Juli | J2: ='Ertragsv. 2025'!J2 -> Aug. | ... N2: ='Ertragsv. 2025'!N2 -> Dez. | O2: SUMME | P2: % | Q2: Branchen-vergl. | R2: ERLÄUTERUNGEN / KOMMENTARE
B3: Umsatz/ Erlöse | C3: ='UmstzPlan 1.-3.Jahr'!E38 -> 0 | D3: ='UmstzPlan 1.-3.Jahr'!G38 -> 0 | E3: ='UmstzPlan 1.-3.Jahr'!I38 -> 0 | F3: ='UmstzPlan 1.-3.Jahr'!K38 -> 0 | G3: ='UmstzPlan 1.-3.Jahr'!M38 -> 0 | H3: ='UmstzPlan 1.-3.Jahr'!O38 -> 0 | I3: ='UmstzPlan 1.-3.Jahr'!Q38 -> 0 | J3: ='UmstzPlan 1.-3.Jahr'!S38 -> 0 | K3: ='UmstzPlan 1.-3.Jahr'!U38 -> 0 | L3: ='UmstzPlan 1.-3.Jahr'!W38 -> 0 | M3: ='UmstzPlan 1.-3.Jahr'!Y38 -> 0 | N3: ='UmstzPlan 1.-3.Jahr'!AA38 -> 0 | O3: =SUM(C3:N3) -> 0 | P3: 100
A4: 0.12 | B4: ./.Materialeinsatz | C4: =C3*$A$4 -> 0 | D4: =D3*$A$4 -> 0 | E4: =E3*$A$4 -> 0 | F4: =F3*$A$4 -> 0 | G4: =G3*$A$4 -> 0 | H4: =H3*$A$4 -> 0 | I4: =I3*$A$4 -> 0 | J4: =J3*$A$4 -> 0 | ... N4: =N3*$A$4 -> 0 | O4: =SUM(C4:N4) -> 0 | P4: =O4/$O$3% -> #DIV/0!
B5: ./. Kosten:
B6: Raumkosten | D6: 0 | E6: 0 | F6: 0 | G6: 0 | H6: 0 | I6: 0 | J6: 0 | K6: 0 | L6: 0 | M6: 0 | N6: 0 | O6: =SUM(C6:N6) -> 0 | P6: =O6/$O$3% -> #DIV/0! | R6: Beispiel: Büromiete 12% der Wohnung
B7: Kfz Steuer | C7: 0 | D7: 0 | E7: 0 | F7: 0 | G7: 0 | H7: 0 | I7: 0 | J7: 0 | K7: 0 | L7: 0 | M7: 0 | N7: 0 | O7: =SUM(C7:N7) -> 0 | P7: =O7/$O$3% -> #DIV/0! | R7: anteilig gem.Nutzung
B8: Kraftfahrzeugkosten | C8: 0 | D8: 0 | E8: 0 | F8: 0 | G8: 0 | H8: 0 | I8: 0 | J8: 0 | K8: 0 | L8: 0 | M8: 0 | N8: 0 | O8: =SUM(C8:N8) -> 0 | P8: =O8/$O$3% -> #DIV/0! | R8: gem.geschätz.mtl Kilometerleistung
B9: Leasing | C9: =Finanz_AfA_Investitionen!$H28 -> 0 | D9: =Finanz_AfA_Investitionen!$H28 -> 0 | E9: =Finanz_AfA_Investitionen!$H28 -> 0 | F9: =Finanz_AfA_Investitionen!$H28 -> 0 | G9: =Finanz_AfA_Investitionen!$H28 -> 0 | H9: =Finanz_AfA_Investitionen!$H28 -> 0 | I9: =Finanz_AfA_Investitionen!$H28 -> 0 | J9: =Finanz_AfA_Investitionen!$H28 -> 0 | ... N9: =Finanz_AfA_Investitionen!$H28 -> 0 | O9: =SUM(C9:N9) -> 0 | P9: =O9/$O$3% -> #DIV/0!
B10: Werbe- und Reisekosten | O10: =SUM(C10:N10) -> 0 | P10: =O10/$O$3% -> #DIV/0!
B11: Telefon, Telefax, Internet | O11: =SUM(C11:N11) -> 0 | P11: =O11/$O$3% -> #DIV/0!
B12: Bürobedarf | O12: =SUM(C12:N12) -> 0 | P12: =O12/$O$3% -> #DIV/0!
B13: Rechts- und Beratungskosten | O13: =SUM(C13:N13) -> 0 | P13: =O13/$O$3% -> #DIV/0!
B14: Versicherungen/Beiträge | O14: =SUM(C14:N14) -> 0 | P14: =O14/$O$3% -> #DIV/0!
B15: Reparaturen/Instandhaltung | O15: =SUM(C15:N15) -> 0 | P15: =O15/$O$3% -> #DIV/0!
B16: sonstiger Betriebsaufwand | O16: =SUM(C16:N16) -> 0 | P16: =O16/$O$3% -> #DIV/0!
B17: Zinsaufwand | C17: =Finanz_AfA_Investitionen!$H$38-Finanz_AfA_Investitionen!H37+'Mikrostarter Geschäftsplan'!D33 -> 0 | D17: =Finanz_AfA_Investitionen!$H$38-Finanz_AfA_Investitionen!H37+'Mikrostarter Geschäftsplan'!D34 -> 0 | E17: =Finanz_AfA_Investitionen!$H$38-Finanz_AfA_Investitionen!H37+'Mikrostarter Geschäftsplan'!D35 -> 0 | F17: =Finanz_AfA_Investitionen!$H$38-Finanz_AfA_Investitionen!H37+'Mikrostarter Geschäftsplan'!D36 -> 0 | G17: =Finanz_AfA_Investitionen!$H$38-Finanz_AfA_Investitionen!H37+'Mikrostarter Geschäftsplan'!D37 -> 0 | H17: =Finanz_AfA_Investitionen!$H$38-Finanz_AfA_Investitionen!H37+'Mikrostarter Geschäftsplan'!D38 -> 0 | I17: =Finanz_AfA_Investitionen!$H$38-Finanz_AfA_Investitionen!H37+'Mikrostarter Geschäftsplan'!D39 -> 0 | J17: =Finanz_AfA_Investitionen!$H$38-Finanz_AfA_Investitionen!H37+'Mikrostarter Geschäftsplan'!D40 -> 0 | K17: =Finanz_AfA_Investitionen!$H$38-Finanz_AfA_Investitionen!H37+'Mikrostarter Geschäftsplan'!D41 -> 0 | L17: =Finanz_AfA_Investitionen!$H$38-Finanz_AfA_Investitionen!H37+'Mikrostarter Geschäftsplan'!D42 -> 0 | M17: =Finanz_AfA_Investitionen!$H$38-Finanz_AfA_Investitionen!H37+'Mikrostarter Geschäftsplan'!D43 -> 0 | N17: =Finanz_AfA_Investitionen!$H$38-Finanz_AfA_Investitionen!H37+'Mikrostarter Geschäftsplan'!D44 -> 0 | O17: =SUM(C17:N17) -> 0 | P17: =O17/$O$3% -> #DIV/0!
B18: PersonalkostenAGA | C18: =ArbStd_MA!$I$94+ArbStd_MA!$I$99 -> 0 | D18: =ArbStd_MA!$I$94+ArbStd_MA!$I$99 -> 0 | E18: =ArbStd_MA!$I$94+ArbStd_MA!$I$99 -> 0 | F18: =ArbStd_MA!$I$94+ArbStd_MA!$I$99 -> 0 | G18: =ArbStd_MA!$I$94+ArbStd_MA!$I$99 -> 0 | H18: =ArbStd_MA!$I$94+ArbStd_MA!$I$99 -> 0 | I18: =ArbStd_MA!$I$94+ArbStd_MA!$I$99 -> 0 | J18: =ArbStd_MA!$I$94+ArbStd_MA!$I$99 -> 0 | ... N18: =ArbStd_MA!$I$94+ArbStd_MA!$I$99 -> 0 | O18: =SUM(C18:N18) -> 0 | P18: =O18/$O$3% -> #DIV/0!
P19: =O19/$O$3% -> #DIV/0!
B20: Summe Aufwendungen | C20: =SUM(C4:C19) -> 0 | D20: =SUM(D4:D19) -> 0 | E20: =SUM(E4:E19) -> 0 | F20: =SUM(F4:F19) -> 0 | G20: =SUM(G4:G19) -> 0 | H20: =SUM(H4:H19) -> 0 | I20: =SUM(I4:I19) -> 0 | J20: =SUM(J4:J19) -> 0 | ... N20: =SUM(N4:N19) -> 0 | O20: =SUM(C20:N20) -> 0 | P20: =O20/$O$3% -> #DIV/0!
B21: Betriebsergebnis | C21: =C3-C20 -> 0 | D21: =D3-D20 -> 0 | E21: =E3-E20 -> 0 | F21: =F3-F20 -> 0 | G21: =G3-G20 -> 0 | H21: =H3-H20 -> 0 | I21: =I3-I20 -> 0 | J21: =J3-J20 -> 0 | ... N21: =N3-N20 -> 0 | O21: =SUM(C21:N21) -> 0 | P21: =O21/$O$3% -> #DIV/0!
B22: ./. Abschreibungen | C22: =Finanz_AfA_Investitionen!F28 -> 0 | D22: =Finanz_AfA_Investitionen!F28 -> 0 | E22: =Finanz_AfA_Investitionen!F28 -> 0 | F22: =Finanz_AfA_Investitionen!F28 -> 0 | G22: =Finanz_AfA_Investitionen!F28 -> 0 | H22: =Finanz_AfA_Investitionen!F28 -> 0 | I22: =Finanz_AfA_Investitionen!F28 -> 0 | J22: =Finanz_AfA_Investitionen!F28 -> 0 | K22: =Finanz_AfA_Investitionen!F28 -> 0 | L22: =Finanz_AfA_Investitionen!F28 -> 0 | M22: =Finanz_AfA_Investitionen!F28 -> 0 | N22: =Finanz_AfA_Investitionen!F28 -> 0 | O22: =SUM(C22:N22) -> 0 | P22: =O22/$O$3% -> #DIV/0!
B23: Gewinn/Verlust | C23: =C21-C22 -> 0 | D23: =D21-D22 -> 0 | E23: =E21-E22 -> 0 | F23: =F21-F22 -> 0 | G23: =G21-G22 -> 0 | H23: =H21-H22 -> 0 | I23: =I21-I22 -> 0 | J23: =J21-J22 -> 0 | ... O23: =O21-O22 -> 0 | P23: =O23/$O$3% -> #DIV/0! | R23: Die Vorlage dieser Datei wurde zur Verfügung gestellt durch die Wirtschafts-Senioren Hannover
B24: Aufgelaufene Werte | C24: ='Ertragsv. 2026'!C23 -> 0 | D24: =C24+D23 -> 0 | E24: =D24+E23 -> 0 | F24: =E24+F23 -> 0 | G24: =F24+G23 -> 0 | H24: =G24+H23 -> 0 | I24: =H24+I23 -> 0 | J24: =I24+J23 -> 0 | K24: =J24+K23 -> 0 | ... N24: =M24+N23 -> 0 | P24: =O24/$O$3% -> #DIV/0!
B25: Kalk. Steuern(ESt/Soli/GeSt) | C25: =IF($K$32=1,C23*$I$32,IF($K$32=2,C23*$I$33)) -> 0 | D25: =IF($K$32=1,D23*$I$32,IF($K$32=2,D23*$I$33)) -> 0 | E25: =IF($K$32=1,E23*$I$32,IF($K$32=2,E23*$I$33)) -> 0 | F25: =IF($K$32=1,F23*$I$32,IF($K$32=2,F23*$I$33)) -> 0 | G25: =IF($K$32=1,G23*$I$32,IF($K$32=2,G23*$I$33)) -> 0 | H25: =IF($K$32=1,H23*$I$32,IF($K$32=2,H23*$I$33)) -> 0 | I25: =IF($K$32=1,I23*$I$32,IF($K$32=2,I23*$I$33)) -> 0 | J25: =IF($K$32=1,J23*$I$32,IF($K$32=2,J23*$I$33)) -> 0 | ... N25: =IF($K$32=1,N23*$I$32,IF($K$32=2,N23*$I$33)) -> 0 | O25: =SUM(C25:N25) -> 0 | P25: =O25/$O$3% -> #DIV/0!
B26: Gewinn/Verlust n.Steuern | C26: =C23-C25 -> 0 | D26: =D23-D25 -> 0 | E26: =E23-E25 -> 0 | F26: =F23-F25 -> 0 | G26: =G23-G25 -> 0 | H26: =H23-H25 -> 0 | I26: =I23-I25 -> 0 | J26: =J23-J25 -> 0 | ... N26: =N23-N25 -> 0 | O26: =SUM(C26:N26) -> 0 | P26: =O26/$O$3% -> #DIV/0!
B27: UnternehmerInnen-Lohn | C27: =M43 -> 0 | D27: =M43 -> 0 | E27: =M43 -> 0 | F27: =M43 -> 0 | G27: =M43 -> 0 | H27: =M43 -> 0 | I27: =M43 -> 0 | J27: =M43 -> 0 | K27: =M43 -> 0 | L27: =M43 -> 0 | M27: =M43 -> 0 | N27: =M43 -> 0 | O27: =SUM(C27:N27) -> 0 | P27: =O27/$O$3% -> #DIV/0!
B28: Darstellung Risikobetrag Umsatzlose Zeit | L28: in % vom Umsatz | O28: =(O20-O4+O22)*Q42 -> 0 | P28: =O28/$O$3% -> #DIV/0!
B29: Darstellung Risikobetrag Saisonverkäufe | L29: in % vom Wareneinkauf | O29: =O4*Q41 -> 0 | P29: =O29/$O$3% -> #DIV/0!
B31: Steuern individuell | C31: je nach Einkommen für den Mindeststundensatz | I31: =C32+E32 -> 0.1477
B32: Steuern Einzelfirma | C32: 0.14 | D32: EST | E32: =C32*5.5% -> 0.0077 | F32: Soli | G32: 0.11 | H32: GeSt | I32: =C32+E32+G32 -> 0.2577 | K32: 1
B33: Steuern GmbH | C33: 0.15 | D33: KöSt | E33: =C33*5.5% -> 0.00825 | F33: Soli | G33: 0.14 | H33: GeSt | I33: =C33+E33+G33 -> 0.29825
B35: GESAMTKALKULATION | C35: 1) PRIVATE KOSTEN + 2) GEWERBLICHE KOSTEN + WARENEINSATZ + 3) 3% RISIKOZUSCHLAG UNTERNEHM. TÄTIGKEIT (SOZIALE SICHERUNG) + 4) 10% EIGENKAPITALVERZINSUNG + 5) KALKULATORISCHE STEUERN + 6) 5% REINGEWINNANSPRUCH ) +7) 2% GARANTIE / GEWÄHRLEISTUNG/ SCHWUND UND VORSORGE FÜR FORDERUNGSVERLUSTE , +8) RISIKOZUSCHLAG FÜR SAISON-/SONDERVERKÄUFE / NACHLÄSSE +9) RISIKOZUSCHLAG FÜR UNTERAUSLASTUNG UND UMSATZLOSE ZEIT
C36: 1) | D36: + 2) | E36: + 3) | F36: + 4) | G36: + 5) | H36: + 6) | I36: + 7) | J36: +8) | K36: +9) | M36: Mindestumsatz
B37: Mindestumsatz | C37: =Privatentnahmen!F35 -> 0 | D37: =(O20+O22)/12 -> 0 | E37: =(O3/12)*Q37 -> 0 | F37: =Finanz_AfA_Investitionen!C31*Q38/12 -> 0 | G37: =O25/12 -> 0 | H37: =O3/12*Q39 -> 0 | I37: =O3/12*Q40 -> 0 | J37: =O29/12 -> 0 | K37: =IF(O4>1,(O28/12),IF(O4<1,0)) -> 0 | M37: =SUM(C37:K37) -> 0 | P37: 3) | Q37: 0.01
C38: 1) | D38: + 2a) | E38: + 3) | F38: + 4) | G38: + 5) | H38: + 6) | I38: +7) | J38: +8) | K38: +9) | L38: =IF(ArbStd_MA!$G$33>=1,ArbStd_MA!$G$33,IF(ArbStd_MA!$G$33<=1,ArbStd_MA!$F$23)) -> 144 | M38: Stundensatz | P38: 4) | Q38: 0.2
B39: Mindeststundensatz | C39: =Privatentnahmen!F35 -> 0 | D39: =(O20-O4+O22)/12 -> 0 | G39: =C39*I31 -> 0 | L39: =IF(ArbStd_MA!$G$33>=1,ArbStd_MA!$G$33,IF(ArbStd_MA!$G$33<=1,ArbStd_MA!$F$23)) -> 144 | M39: =(C39+D39+G39+K39)/L39/ArbStd_MA!G49 -> 0 | P39: 6) | Q39: 0.05
B40: Stundenverkaufssatz | C40: =Privatentnahmen!F35 -> 0 | D40: =D39 -> 0 | E40: =(O3/12)*Q37 -> 0 | F40: =F37 -> 0 | G40: =O25/12 -> 0 | H40: =O3/12*Q39 -> 0 | I40: =I37 -> 0 | L40: =IF(ArbStd_MA!$G$33>=1,ArbStd_MA!$G$33,IF(ArbStd_MA!$G$33<=1,ArbStd_MA!$F$23)) -> 144 | M40: =(C40+D40+E40+F40+G40+H40+I40+J40+K40)/L40/ArbStd_MA!G49 -> 0 | P40: 7) | Q40: 0.02
B41: relative Stundensatzdifferenz | M41: =ROUND((M40-M39)/M39*100,1)& " %" -> #DIV/0! | P41: 8) | Q41: 0.1
B42: Rohaufschlag im Handel % | C42: =C40 -> 0 | D42: =D40 -> 0 | E42: =E40 -> 0 | F42: =F40 -> 0 | G42: =G40 -> 0 | H42: =H40 -> 0 | I42: =I40 -> 0 | J42: =J37 -> 0 | K42: =K37 -> 0 | M42: =IF(O4<1,0,(C42+D42+E42+F42+G42+H42+I42+J42+K42)*100*12/O4) -> 0 | P42: 9) | Q42: 0.1
B43: Unternehmer/innen-Lohn | C43: =Privatentnahmen!F35 -> 0 | E43: =E40 -> 0 | F43: =F40 -> 0 | M43: =C43+E43+F43+H43 -> 0

Sheet Ertragsv. 2027
B1: ERTRAGSVORSCHAU 3. Planjahr | E1: =ZusammenführErgebn!E3 -> 2027 | H1: =Deckblatt!C5 -> Max Mustermann
A2: Durchschn. Warenein-satz | B2: ALLE ANGABEN NETTO | C2: ='Ertragsv. 2025'!C2 -> Jan. | D2: ='Ertragsv. 2025'!D2 -> Febr. | E2: ='Ertragsv. 2025'!E2 -> März | F2: ='Ertragsv. 2025'!F2 -> April | G2: ='Ertragsv. 2025'!G2 -> Mai | H2: ='Ertragsv. 2025'!H2 -> Juni | I2: ='Ertragsv. 2025'!I2 -> Juli | J2: ='Ertragsv. 2025'!J2 -> Aug. | ... N2: ='Ertragsv. 2025'!N2 -> Dez. | O2: SUMME | P2: % | Q2: Branchen-vergl. | R2: ERLÄUTERUNGEN / KOMMENTARE
B3: Umsatz/ Erlöse | C3: ='UmstzPlan 1.-3.Jahr'!E57 -> 0 | D3: ='UmstzPlan 1.-3.Jahr'!G57 -> 0 | E3: ='UmstzPlan 1.-3.Jahr'!I57 -> 0 | F3: ='UmstzPlan 1.-3.Jahr'!K57 -> 0 | G3: ='UmstzPlan 1.-3.Jahr'!M57 -> 0 | H3: ='UmstzPlan 1.-3.Jahr'!O57 -> 0 | I3: ='UmstzPlan 1.-3.Jahr'!Q57 -> 0 | J3: ='UmstzPlan 1.-3.Jahr'!S57 -> 0 | K3: ='UmstzPlan 1.-3.Jahr'!U57 -> 0 | L3: ='UmstzPlan 1.-3.Jahr'!W57 -> 0 | M3: ='UmstzPlan 1.-3.Jahr'!Y57 -> 0 | N3: ='UmstzPlan 1.-3.Jahr'!AA57 -> 0 | O3: =SUM(C3:N3) -> 0 | P3: 100
A4: 0.12 | B4: ./.Materialeinsatz | C4: =C3*$A$4 -> 0 | D4: =D3*$A$4 -> 0 | E4: =E3*$A$4 -> 0 | F4: =F3*$A$4 -> 0 | G4: =G3*$A$4 -> 0 | H4: =H3*$A$4 -> 0 | I4: =I3*$A$4 -> 0 | J4: =J3*$A$4 -> 0 | ... N4: =N3*$A$4 -> 0 | O4: =SUM(C4:N4) -> 0 | P4: =O4/$O$3% -> #DIV/0!
B5: ./. Kosten:
B6: Raumkosten | C6: 0 | D6: 0 | E6: 0 | F6: 0 | G6: 0 | H6: 0 | I6: 0 | J6: 0 | K6: 0 | L6: 0 | M6: 0 | N6: 0 | O6: =SUM(C6:N6) -> 0 | P6: =O6/$O$3% -> #DIV/0! | R6: Beispiel: Büromiete 12% der Wohnung
B7: Kfz Steuer | C7: 0 | D7: 0 | E7: 0 | F7: 0 | G7: 0 | H7: 0 | I7: 0 | J7: 0 | K7: 0 | L7: 0 | M7: 0 | N7: 0 | O7: =SUM(C7:N7) -> 0 | P7: =O7/$O$3% -> #DIV/0! | R7: anteilig gem.Nutzung
B8: Kraftfahrzeugkosten | C8: 0 | D8: 0 | E8: 0 | F8: 0 | G8: 0 | H8: 0 | I8: 0 | J8: 0 | K8: 0 | L8: 0 | M8: 0 | N8: 0 | O8: =SUM(C8:N8) -> 0 | P8: =O8/$O$3% -> #DIV/0! | R8: gem.geschätz.mtl Kilometerleistung
B9: Leasing | C9: =Finanz_AfA_Investitionen!$H28 -> 0 | D9: =Finanz_AfA_Investitionen!$H28 -> 0 | E9: =Finanz_AfA_Investitionen!$H28 -> 0 | F9: =Finanz_AfA_Investitionen!$H28 -> 0 | G9: =Finanz_AfA_Investitionen!$H28 -> 0 | H9: =Finanz_AfA_Investitionen!$H28 -> 0 | I9: =Finanz_AfA_Investitionen!$H28 -> 0 | J9: =Finanz_AfA_Investitionen!$H28 -> 0 | ... N9: =Finanz_AfA_Investitionen!$H28 -> 0 | O9: =SUM(C9:N9) -> 0 | P9: =O9/$O$3% -> #DIV/0!
B10: Werbe- und Reisekosten | O10: =SUM(C10:N10) -> 0 | P10: =O10/$O$3% -> #DIV/0!
B11: Telefon, Telefax, Internet | O11: =SUM(C11:N11) -> 0 | P11: =O11/$O$3% -> #DIV/0!
B12: Bürobedarf | O12: =SUM(C12:N12) -> 0 | P12: =O12/$O$3% -> #DIV/0!
B13: Rechts- und Beratungskosten | O13: =SUM(C13:N13) -> 0 | P13: =O13/$O$3% -> #DIV/0! | R13: Beitrag Berufsverb.
B14: Versicherungen/Beiträge | O14: =SUM(C14:N14) -> 0 | P14: =O14/$O$3% -> #DIV/0!
B15: Reparaturen/Instandhaltung | O15: =SUM(C15:N15) -> 0 | P15: =O15/$O$3% -> #DIV/0!
B16: sonstiger Betriebsaufwand | O16: =SUM(C16:N16) -> 0 | P16: =O16/$O$3% -> #DIV/0!
B17: Zinsaufwand | C17: =Finanz_AfA_Investitionen!$I$38-Finanz_AfA_Investitionen!I37+'Mikrostarter Geschäftsplan'!D46 -> 0 | D17: =Finanz_AfA_Investitionen!$I$38-Finanz_AfA_Investitionen!I37+'Mikrostarter Geschäftsplan'!D47 -> 0 | E17: =Finanz_AfA_Investitionen!$I$38-Finanz_AfA_Investitionen!I37+'Mikrostarter Geschäftsplan'!D48 -> 0 | F17: =Finanz_AfA_Investitionen!$I$38-Finanz_AfA_Investitionen!I37+'Mikrostarter Geschäftsplan'!D49 -> 0 | G17: =Finanz_AfA_Investitionen!$I$38-Finanz_AfA_Investitionen!I37+'Mikrostarter Geschäftsplan'!D50 -> 0 | H17: =Finanz_AfA_Investitionen!$I$38-Finanz_AfA_Investitionen!I37+'Mikrostarter Geschäftsplan'!D51 -> 0 | I17: =Finanz_AfA_Investitionen!$I$38-Finanz_AfA_Investitionen!I37+'Mikrostarter Geschäftsplan'!D52 -> 0 | J17: =Finanz_AfA_Investitionen!$I$38-Finanz_AfA_Investitionen!I37+'Mikrostarter Geschäftsplan'!D53 -> 0 | K17: =Finanz_AfA_Investitionen!$I$38-Finanz_AfA_Investitionen!I37+'Mikrostarter Geschäftsplan'!D54 -> 0 | L17: =Finanz_AfA_Investitionen!$I$38-Finanz_AfA_Investitionen!I37+'Mikrostarter Geschäftsplan'!D55 -> 0 | M17: =Finanz_AfA_Investitionen!$I$38-Finanz_AfA_Investitionen!I37+'Mikrostarter Geschäftsplan'!D56 -> 0 | N17: =Finanz_AfA_Investitionen!$I$38-Finanz_AfA_Investitionen!I37+'Mikrostarter Geschäftsplan'!D57 -> 0 | O17: =SUM(C17:N17) -> 0 | P17: =O17/$O$3% -> #DIV/0!
B18: PersonalkostenAGA | C18: =ArbStd_MA!$I$112+ArbStd_MA!$I$117 -> 0 | D18: =ArbStd_MA!$I$112+ArbStd_MA!$I$117 -> 0 | E18: =ArbStd_MA!$I$112+ArbStd_MA!$I$117 -> 0 | F18: =ArbStd_MA!$I$112+ArbStd_MA!$I$117 -> 0 | G18: =ArbStd_MA!$I$112+ArbStd_MA!$I$117 -> 0 | H18: =ArbStd_MA!$I$112+ArbStd_MA!$I$117 -> 0 | I18: =ArbStd_MA!$I$112+ArbStd_MA!$I$117 -> 0 | J18: =ArbStd_MA!$I$112+ArbStd_MA!$I$117 -> 0 | ... N18: =ArbStd_MA!$I$112+ArbStd_MA!$I$117 -> 0 | O18: =SUM(C18:N18) -> 0 | P18: =O18/$O$3% -> #DIV/0!
P19: =O19/$O$3% -> #DIV/0!
B20: Summe Aufwendungen | C20: =SUM(C4:C19) -> 0 | D20: =SUM(D4:D19) -> 0 | E20: =SUM(E4:E19) -> 0 | F20: =SUM(F4:F19) -> 0 | G20: =SUM(G4:G19) -> 0 | H20: =SUM(H4:H19) -> 0 | I20: =SUM(I4:I19) -> 0 | J20: =SUM(J4:J19) -> 0 | ... N20: =SUM(N4:N19) -> 0 | O20: =SUM(C20:N20) -> 0 | P20: =O20/$O$3% -> #DIV/0!
B21: Betriebsergebnis | C21: =C3-C20 -> 0 | D21: =D3-D20 -> 0 | E21: =E3-E20 -> 0 | F21: =F3-F20 -> 0 | G21: =G3-G20 -> 0 | H21: =H3-H20 -> 0 | I21: =I3-I20 -> 0 | J21: =J3-J20 -> 0 | ... N21: =N3-N20 -> 0 | O21: =SUM(C21:N21) -> 0 | P21: =O21/$O$3% -> #DIV/0!
B22: ./. Abschreibungen | C22: =Finanz_AfA_Investitionen!F28 -> 0 | D22: =Finanz_AfA_Investitionen!F28 -> 0 | E22: =Finanz_AfA_Investitionen!F28 -> 0 | F22: =Finanz_AfA_Investitionen!F28 -> 0 | G22: =Finanz_AfA_Investitionen!F28 -> 0 | H22: =Finanz_AfA_Investitionen!F28 -> 0 | I22: =Finanz_AfA_Investitionen!F28 -> 0 | J22: =Finanz_AfA_Investitionen!F28 -> 0 | K22: =Finanz_AfA_Investitionen!F28 -> 0 | L22: =Finanz_AfA_Investitionen!F28 -> 0 | M22: =Finanz_AfA_Investitionen!F28 -> 0 | N22: =Finanz_AfA_Investitionen!F28 -> 0 | O22: =SUM(C22:N22) -> 0 | P22: =O22/$O$3% -> #DIV/0!
B23: Gewinn/Verlust | C23: =C21-C22 -> 0 | D23: =D21-D22 -> 0 | E23: =E21-E22 -> 0 | F23: =F21-F22 -> 0 | G23: =G21-G22 -> 0 | H23: =H21-H22 -> 0 | I23: =I21-I22 -> 0 | J23: =J21-J22 -> 0 | ... O23: =O21-O22 -> 0 | P23: =O23/$O$3% -> #DIV/0!
B24: Aufgelaufene Werte | C24: ='Ertragsv. 2027'!C23 -> 0 | D24: =C24+D23 -> 0 | E24: =D24+E23 -> 0 | F24: =E24+F23 -> 0 | G24: =F24+G23 -> 0 | H24: =G24+H23 -> 0 | I24: =H24+I23 -> 0 | J24: =I24+J23 -> 0 | K24: =J24+K23 -> 0 | ... N24: =M24+N23 -> 0 | P24: =O24/$O$3% -> #DIV/0!
B25: Kalk. Steuern(ESt/Soli/GeSt) | C25: =IF($K$32=1,C23*$I$32,IF($K$32=2,C23*$I$33)) -> 0 | D25: =IF($K$32=1,D23*$I$32,IF($K$32=2,D23*$I$33)) -> 0 | E25: =IF($K$32=1,E23*$I$32,IF($K$32=2,E23*$I$33)) -> 0 | F25: =IF($K$32=1,F23*$I$32,IF($K$32=2,F23*$I$33)) -> 0 | G25: =IF($K$32=1,G23*$I$32,IF($K$32=2,G23*$I$33)) -> 0 | H25: =IF($K$32=1,H23*$I$32,IF($K$32=2,H23*$I$33)) -> 0 | I25: =IF($K$32=1,I23*$I$32,IF($K$32=2,I23*$I$33)) -> 0 | J25: =IF($K$32=1,J23*$I$32,IF($K$32=2,J23*$I$33)) -> 0 | ... N25: =IF($K$32=1,N23*$I$32,IF($K$32=2,N23*$I$33)) -> 0 | O25: =SUM(C25:N25) -> 0 | P25: =O25/$O$3% -> #DIV/0!
B26: Gewinn/Verlust n.Steuern | C26: =C23-C25 -> 0 | D26: =D23-D25 -> 0 | E26: =E23-E25 -> 0 | F26: =F23-F25 -> 0 | G26: =G23-G25 -> 0 | H26: =H23-H25 -> 0 | I26: =I23-I25 -> 0 | J26: =J23-J25 -> 0 | ... N26: =N23-N25 -> 0 | O26: =SUM(C26:N26) -> 0 | P26: =O26/$O$3% -> #DIV/0!
B27: UnternehmerInnen-Lohn | C27: =M43 -> 0 | D27: =M43 -> 0 | E27: =M43 -> 0 | F27: =M43 -> 0 | G27: =M43 -> 0 | H27: =M43 -> 0 | I27: =M43 -> 0 | J27: =M43 -> 0 | K27: =M43 -> 0 | L27: =M43 -> 0 | M27: =M43 -> 0 | N27: =M43 -> 0 | O27: =SUM(C27:N27) -> 0 | P27: =O27/$O$3% -> #DIV/0!
B28: Darstellung Risikobetrag Umsatzlose Zeit | L28: in % vom Umsatz | O28: =(O20-O4+O22)*Q42 -> 0 | P28: =O28/$O$3% -> #DIV/0!
B29: Darstellung Risikobetrag Saisonverkäufe | L29: in % vom Wareneinkauf | O29: =O4*Q41 -> 0 | P29: =O29/$O$3% -> #DIV/0!
B31: Steuern individuell | C31: je nach Einkommen für den Mindeststundensatz | I31: =C32+E32 -> 0.1477
B32: Steuern Einzelfirma | C32: 0.14 | D32: EST | E32: =C32*5.5% -> 0.0077 | F32: Soli | G32: 0.1 | H32: GeSt | I32: =C32+E32+G32 -> 0.2477 | K32: 1
B33: Steuern GmbH | C33: 0.15 | D33: KöSt | E33: =C33*5.5% -> 0.00825 | F33: Soli | G33: 0.14 | H33: GeSt | I33: =C33+E33+G33 -> 0.29825
B35: GESAMTKALKULATION | C35: 1) PRIVATE KOSTEN + 2) GEWERBLICHE KOSTEN + WARENEINSATZ + 3) 3% RISIKOZUSCHLAG UNTERNEHM. TÄTIGKEIT (SOZIALE SICHERUNG) + 4) 10% EIGENKAPITALVERZINSUNG + 5) KALKULATORISCHE STEUERN + 6) 5% REINGEWINNANSPRUCH ) +7) 2% GARANTIE/ GEWÄHRLEISTUNG/SCHWUND UND VORSORGE FÜR FORDERUNGSVERLUSTE, +8) RISIKOZUSCHLAG FÜR SAISON-/SONDERVERKÄUFE / NACHLÄSSE +9) RISIKOZUSCHLAG FÜR UNTERAUSLASTUNG UND UMSATZLOSE ZEIT
C36: 1) | D36: + 2) | E36: + 3) | F36: + 4) | G36: + 5) | H36: + 6) | I36: + 7) | J36: +8) | K36: +9) | M36: Mindestumsatz
B37: Mindestumsatz | C37: =Privatentnahmen!H35 -> 0 | D37: =(O20+O22)/12 -> 0 | E37: =(O3/12)*Q37 -> 0 | F37: =Finanz_AfA_Investitionen!C31*Q38/12 -> 0 | G37: =O25/12 -> 0 | H37: =O3/12*Q39 -> 0 | I37: =O3/12*Q40 -> 0 | J37: =O29/12 -> 0 | K37: =IF(O4>1,(O28/12),IF(O4<1,0)) -> 0 | M37: =SUM(C37:K37) -> 0 | P37: 3) | Q37: 0.03
C38: 1) | D38: + 2a) | E38: + 3) | F38: + 4) | G38: + 5) | H38: + 6) | I38: +7) | J38: +8) | K38: +9) | L38: =IF(ArbStd_MA!$I$33>=1,ArbStd_MA!$I$33,IF(ArbStd_MA!$I$33<=1,ArbStd_MA!$H$23)) -> 144 | M38: Stundensatz | P38: 4) | Q38: 0.1
B39: Mindeststundensatz | C39: =Privatentnahmen!H35 -> 0 | D39: =(O20-O4+O22)/12 -> 0 | G39: =C39*I31 -> 0 | L39: =IF(ArbStd_MA!$I$33>=1,ArbStd_MA!$I$33,IF(ArbStd_MA!$I$33<=1,ArbStd_MA!$H$23)) -> 144 | M39: =(C39+D39+G39+K39)/L39/ArbStd_MA!H49 -> 0 | P39: 6) | Q39: 0.05
B40: Stundenverkaufssatz | C40: =Privatentnahmen!H35 -> 0 | D40: =D39 -> 0 | E40: =(O3/12)*Q37 -> 0 | F40: =F37 -> 0 | G40: =O25/12 -> 0 | H40: =O3/12*Q39 -> 0 | I40: =I37 -> 0 | L40: =IF(ArbStd_MA!$I$33>=1,ArbStd_MA!$I$33,IF(ArbStd_MA!$I$33<=1,ArbStd_MA!$H$23)) -> 144 | M40: =(C40+D40+E40+F40+G40+H40+I40+J40+K40)/L40/ArbStd_MA!H49 -> 0 | P40: 7) | Q40: 0.02
B41: relative Stundensatzdifferenz | M41: =ROUND((M40-M39)/M39*100,1)& " %" -> #DIV/0! | P41: 8) | Q41: 0.1
B42: Rohaufschlag im Handel % | C42: =C40 -> 0 | D42: =D40 -> 0 | E42: =E40 -> 0 | F42: =F40 -> 0 | G42: =G40 -> 0 | H42: =H40 -> 0 | I42: =I40 -> 0 | J42: =J37 -> 0 | K42: =K37 -> 0 | M42: =IF(O4<1,0,(C42+D42+E42+F42+G42+H42+I42+J42+K42)*100*12/O4) -> 0 | P42: 9) | Q42: 0.1
B43: Unternehmer/innen-Lohn | C43: =Privatentnahmen!H35 -> 0 | E43: =E40 -> 0 | F43: =F40 -> 0 | M43: =C43+E43+F43+H43 -> 0

Sheet UmstzPlan 1.-3.Jahr
B1: Bei länger laufenden Aufträgen (mehr als ein Monat) können die Stunden oder die Umsätze aufgeteilt werden, oder das Produkt gestückelt werden!
B2: UMSATZPLANUNG
B3: 1. GESCHÄFTSJAHR | C3: =ZusammenführErgebn!C3 -> 2025 | E3: ='Ertragsv. 2025'!C2 -> Jan. | G3: ='Ertragsv. 2025'!D2 -> Febr. | I3: ='Ertragsv. 2025'!E2 -> März | K3: ='Ertragsv. 2025'!F2 -> April | M3: ='Ertragsv. 2025'!G2 -> Mai | O3: ='Ertragsv. 2025'!H2 -> Juni | Q3: ='Ertragsv. 2025'!I2 -> Juli | S3: ='Ertragsv. 2025'!J2 -> Aug. | U3: ='Ertragsv. 2025'!K2 -> Sept. | W3: ='Ertragsv. 2025'!L2 -> Okt. | Y3: ='Ertragsv. 2025'!M2 -> Nov. | AA3: ='Ertragsv. 2025'!N2 -> Dez. | AC3: SUMME PRODUKTE / DL | AD3: SUMME DER EINZEL- UMSÄTZE | AE3: UMSATZ- STRUKTUR IN % | AG3: STRUKTUR DER EINKAUFSPREISE (Handel+Gastronomie)
B5: Prod.Std./Monat_Soll | F5: =IF(ArbStd_MA!$D$33>=1,ArbStd_MA!$D$33,IF(ArbStd_MA!$D$33<1,ArbStd_MA!$D$23)) -> 144 | H5: =IF(ArbStd_MA!$D$33>=1,ArbStd_MA!$D$33,IF(ArbStd_MA!$D$33<1,ArbStd_MA!$D$23)) -> 144 | J5: =IF(ArbStd_MA!$D$33>=1,ArbStd_MA!$D$33,IF(ArbStd_MA!$D$33<1,ArbStd_MA!$D$23)) -> 144 | L5: =IF(ArbStd_MA!$D$33>=1,ArbStd_MA!$D$33,IF(ArbStd_MA!$D$33<1,ArbStd_MA!$D$23)) -> 144 | N5: =IF(ArbStd_MA!$D$33>=1,ArbStd_MA!$D$33,IF(ArbStd_MA!$D$33<1,ArbStd_MA!$D$23)) -> 144 | P5: =IF(ArbStd_MA!$D$33>=1,ArbStd_MA!$D$33,IF(ArbStd_MA!$D$33<1,ArbStd_MA!$D$23)) -> 144 | R5: =IF(ArbStd_MA!$D$33>=1,ArbStd_MA!$D$33,IF(ArbStd_MA!$D$33<1,ArbStd_MA!$D$23)) -> 144 | T5: =IF(ArbStd_MA!$D$33>=1,ArbStd_MA!$D$33,IF(ArbStd_MA!$D$33<1,ArbStd_MA!$D$23)) -> 144 | V5: =IF(ArbStd_MA!$D$33>=1,ArbStd_MA!$D$33,IF(ArbStd_MA!$D$33<1,ArbStd_MA!$D$23)) -> 144 | X5: =IF(ArbStd_MA!$D$33>=1,ArbStd_MA!$D$33,IF(ArbStd_MA!$D$33<1,ArbStd_MA!$D$23)) -> 144 | Z5: =IF(ArbStd_MA!$D$33>=1,ArbStd_MA!$D$33,IF(ArbStd_MA!$D$33<1,ArbStd_MA!$D$23)) -> 144 | AB5: =IF(ArbStd_MA!$D$33>=1,ArbStd_MA!$D$33,IF(ArbStd_MA!$D$33<1,ArbStd_MA!$D$23)) -> 144
B6: LeistungStd. Ist | F6: =SUM(F9:F18) -> 0 | H6: =SUM(H9:H18) -> 0 | J6: =SUM(J9:J18) -> 0 | L6: =SUM(L9:L18) -> 0 | N6: =SUM(N9:N18) -> 0 | P6: =SUM(P9:P18) -> 0 | R6: =SUM(R9:R18) -> 0 | T6: =SUM(T9:T18) -> 0 | V6: =SUM(V9:V18) -> 0 | X6: =SUM(X9:X18) -> 0 | Z6: =SUM(Z9:Z18) -> 0 | AB6: =SUM(AB9:AB18) -> 0 | AC6: =SUM(E6:AB6)/12 -> 0
C7: Einzel- preis | D7: Prod. Stunden | E7: verk. Stück | F7: Prod.Std. gesamt | G7: verk. Stück | H7: Prod.Std. gesamt | I7: verk. Stück | J7: Prod.Std. gesamt | K7: verk. Stück | L7: Prod.Std. gesamt | M7: verk. Stück | N7: Prod.Std. gesamt | O7: verk. Stück | P7: Prod.Std. gesamt | Q7: verk. Stück | R7: Prod.Std. gesamt | S7: verk. Stück | T7: Prod.Std. gesamt | U7: verk. Stück | V7: Prod.Std. gesamt | W7: verk. Stück | X7: Prod.Std. gesamt | Y7: verk. Stück | Z7: Prod.Std. gesamt | AA7: verk. Stück | AB7: Prod.Std. gesamt | AG7: Einzelpreis | AH7: EK Gesamt
B9: Webseite Teil I | F9: =D9*E9 -> 0 | H9: =D9*G9 -> 0 | J9: =D9*I9 -> 0 | L9: =D9*K9 -> 0 | N9: =D9*M9 -> 0 | P9: =D9*O9 -> 0 | R9: =D9*Q9 -> 0 | T9: =D9*S9 -> 0 | V9: =D9*U9 -> 0 | X9: =D9*W9 -> 0 | Z9: =D9*Y9 -> 0 | AB9: =D9*AA9 -> 0 | AC9: =E9+G9+I9+K9+M9+O9+Q9+S9+U9+W9+Y9+AA9 -> 0 | AD9: =(E9+G9+I9+K9+M9+O9+Q9+S9+U9+W9+Y9+AA9)*C9 -> 0 | AE9: =AD9/$AD$19 -> #DIV/0! | AG9: 300 | AH9: =AC9*AG9 -> 0
B10: Webseite Teil II | F10: =D10*E10 -> 0 | H10: =D10*G10 -> 0 | J10: =D10*I10 -> 0 | L10: =D10*K10 -> 0 | N10: =D10*M10 -> 0 | P10: =D10*O10 -> 0 | R10: =D10*Q10 -> 0 | T10: =D10*S10 -> 0 | V10: =D10*U10 -> 0 | X10: =D10*W10 -> 0 | Z10: =D10*Y10 -> 0 | AB10: =D10*AA10 -> 0 | AC10: =E10+G10+I10+K10+M10+O10+Q10+S10+U10+W10+Y10+AA10 -> 0 | AD10: =(E10+G10+I10+K10+M10+O10+Q10+S10+U10+W10+Y10+AA10)*C10 -> 0 | AE10: =AD10/$AD$19 -> #DIV/0! | AG10: 1.9 | AH10: =AC10*AG10 -> 0
B11: Damenschnitt | F11: =D11*E11 -> 0 | H11: =D11*G11 -> 0 | J11: =D11*I11 -> 0 | L11: =D11*K11 -> 0 | N11: =D11*M11 -> 0 | P11: =D11*O11 -> 0 | R11: =D11*Q11 -> 0 | T11: =D11*S11 -> 0 | V11: =D11*U11 -> 0 | X11: =D11*W11 -> 0 | Z11: =D11*Y11 -> 0 | AB11: =D11*AA11 -> 0 | AC11: =E11+G11+I11+K11+M11+O11+Q11+S11+U11+W11+Y11+AA11 -> 0 | AD11: =(E11+G11+I11+K11+M11+O11+Q11+S11+U11+W11+Y11+AA11)*C11 -> 0 | AE11: =AD11/$AD$19 -> #DIV/0! | AG11: 8.2 | AH11: =AC11*AG11 -> 0
B12: Dauerwelle | F12: =D12*E12 -> 0 | H12: =D12*G12 -> 0 | J12: =D12*I12 -> 0 | L12: =D12*K12 -> 0 | N12: =D12*M12 -> 0 | P12: =D12*O12 -> 0 | R12: =D12*Q12 -> 0 | T12: =D12*S12 -> 0 | V12: =D12*U12 -> 0 | X12: =D12*W12 -> 0 | Z12: =D12*Y12 -> 0 | AB12: =D12*AA12 -> 0 | AC12: =E12+G12+I12+K12+M12+O12+Q12+S12+U12+W12+Y12+AA12 -> 0 | AD12: =(E12+G12+I12+K12+M12+O12+Q12+S12+U12+W12+Y12+AA12)*C12 -> 0 | AE12: =AD12/$AD$19 -> #DIV/0! | AG12: 3.2 | AH12: =AC12*AG12 -> 0
B13: Produkt 5 | F13: =D13*E13 -> 0 | H13: =D13*G13 -> 0 | J13: =D13*I13 -> 0 | L13: =D13*K13 -> 0 | N13: =D13*M13 -> 0 | P13: =D13*O13 -> 0 | R13: =D13*Q13 -> 0 | T13: =D13*S13 -> 0 | V13: =D13*U13 -> 0 | X13: =D13*W13 -> 0 | Z13: =D13*Y13 -> 0 | AB13: =D13*AA13 -> 0 | AC13: =E13+G13+I13+K13+M13+O13+Q13+S13+U13+W13+Y13+AA13 -> 0 | AD13: =(E13+G13+I13+K13+M13+O13+Q13+S13+U13+W13+Y13+AA13)*C13 -> 0 | AE13: =AD13/$AD$19 -> #DIV/0! | AG13: 0.25 | AH13: =AC13*AG13 -> 0
B14: Leistung 1 | F14: =D14*E14 -> 0 | H14: =D14*G14 -> 0 | J14: =D14*I14 -> 0 | L14: =D14*K14 -> 0 | N14: =D14*M14 -> 0 | P14: =D14*O14 -> 0 | R14: =D14*Q14 -> 0 | T14: =D14*S14 -> 0 | V14: =D14*U14 -> 0 | X14: =D14*W14 -> 0 | Z14: =D14*Y14 -> 0 | AB14: =D14*AA14 -> 0 | AC14: =E14+G14+I14+K14+M14+O14+Q14+S14+U14+W14+Y14+AA14 -> 0 | AD14: =(E14+G14+I14+K14+M14+O14+Q14+S14+U14+W14+Y14+AA14)*C14 -> 0 | AE14: =AD14/$AD$19 -> #DIV/0! | AG14: 4.5 | AH14: =AC14*AG14 -> 0
B15: Leistung 2 | F15: =D15*E15 -> 0 | H15: =D15*G15 -> 0 | J15: =D15*I15 -> 0 | L15: =D15*K15 -> 0 | N15: =D15*M15 -> 0 | P15: =D15*O15 -> 0 | R15: =D15*Q15 -> 0 | T15: =D15*S15 -> 0 | V15: =D15*U15 -> 0 | X15: =D15*W15 -> 0 | Z15: =D15*Y15 -> 0 | AB15: =D15*AA15 -> 0 | AC15: =E15+G15+I15+K15+M15+O15+Q15+S15+U15+W15+Y15+AA15 -> 0 | AD15: =(E15+G15+I15+K15+M15+O15+Q15+S15+U15+W15+Y15+AA15)*C15 -> 0 | AE15: =AD15/$AD$19 -> #DIV/0! | AG15: 1.25 | AH15: =AC15*AG15 -> 0
B16: Leistung 3 | F16: =D16*E16 -> 0 | H16: =D16*G16 -> 0 | J16: =D16*I16 -> 0 | L16: =D16*K16 -> 0 | N16: =D16*M16 -> 0 | P16: =D16*O16 -> 0 | R16: =D16*Q16 -> 0 | T16: =D16*S16 -> 0 | V16: =D16*U16 -> 0 | X16: =D16*W16 -> 0 | Z16: =D16*Y16 -> 0 | AB16: =D16*AA16 -> 0 | AC16: =E16+G16+I16+K16+M16+O16+Q16+S16+U16+W16+Y16+AA16 -> 0 | AD16: =(E16+G16+I16+K16+M16+O16+Q16+S16+U16+W16+Y16+AA16)*C16 -> 0 | AE16: =AD16/$AD$19 -> #DIV/0! | AG16: 1 | AH16: =AC16*AG16 -> 0
B17: Leistung 4 | F17: =D17*E17 -> 0 | H17: =D17*G17 -> 0 | J17: =D17*I17 -> 0 | L17: =D17*K17 -> 0 | N17: =D17*M17 -> 0 | P17: =D17*O17 -> 0 | R17: =D17*Q17 -> 0 | T17: =D17*S17 -> 0 | V17: =D17*U17 -> 0 | X17: =D17*W17 -> 0 | Z17: =D17*Y17 -> 0 | AB17: =D17*AA17 -> 0 | AC17: =E17+G17+I17+K17+M17+O17+Q17+S17+U17+W17+Y17+AA17 -> 0 | AD17: =(E17+G17+I17+K17+M17+O17+Q17+S17+U17+W17+Y17+AA17)*C17 -> 0 | AE17: =AD17/$AD$19 -> #DIV/0! | AG17: 0.88 | AH17: =AC17*AG17 -> 0
B18: Leistung 5 | F18: =D18*E18 -> 0 | H18: =D18*G18 -> 0 | J18: =D18*I18 -> 0 | L18: =D18*K18 -> 0 | N18: =D18*M18 -> 0 | P18: =D18*O18 -> 0 | R18: =D18*Q18 -> 0 | T18: =D18*S18 -> 0 | V18: =D18*U18 -> 0 | X18: =D18*W18 -> 0 | Z18: =D18*Y18 -> 0 | AB18: =D18*AA18 -> 0 | AC18: =E18+G18+I18+K18+M18+O18+Q18+S18+U18+W18+Y18+AA18 -> 0 | AD18: =(E18+G18+I18+K18+M18+O18+Q18+S18+U18+W18+Y18+AA18)*C18 -> 0 | AE18: =AD18/$AD$19 -> #DIV/0! | AG18: 7.8 | AH18: =AC18*AG18 -> 0
B19: SUMME | E19: =SUM($C$9*E9)+($C$10*E10)+($C$11*E11)+($C$12*E12)+($C$18*E18)+($C$13*E13)+($C$14*E14)+($C$15*E15)+($C$16*E16)+($C$17*E17) -> 0 | G19: =SUM($C$9*G9)+($C$10*G10)+($C$11*G11)+($C$12*G12)+($C$18*G18)+($C$13*G13)+($C$14*G14)+($C$15*G15)+($C$16*G16)+($C$17*G17) -> 0 | I19: =SUM($C$9*I9)+($C$10*I10)+($C$11*I11)+($C$12*I12)+($C$18*I18)+($C$13*I13)+($C$14*I14)+($C$15*I15)+($C$16*I16)+($C$17*I17) -> 0 | K19: =SUM($C$9*K9)+($C$10*K10)+($C$11*K11)+($C$12*K12)+($C$18*K18)+($C$13*K13)+($C$14*K14)+($C$15*K15)+($C$16*K16)+($C$17*K17) -> 0 | M19: =SUM($C$9*M9)+($C$10*M10)+($C$11*M11)+($C$12*M12)+($C$18*M18)+($C$13*M13)+($C$14*M14)+($C$15*M15)+($C$16*M16)+($C$17*M17) -> 0 | O19: =SUM($C$9*O9)+($C$10*O10)+($C$11*O11)+($C$12*O12)+($C$18*O18)+($C$13*O13)+($C$14*O14)+($C$15*O15)+($C$16*O16)+($C$17*O17) -> 0 | Q19: =SUM($C$9*Q9)+($C$10*Q10)+($C$11*Q11)+($C$12*Q12)+($C$18*Q18)+($C$13*Q13)+($C$14*Q14)+($C$15*Q15)+($C$16*Q16)+($C$17*Q17) -> 0 | S19: =SUM($C$9*S9)+($C$10*S10)+($C$11*S11)+($C$12*S12)+($C$18*S18)+($C$13*S13)+($C$14*S14)+($C$15*S15)+($C$16*S16)+($C$17*S17) -> 0 | U19: =SUM($C$9*U9)+($C$10*U10)+($C$11*U11)+($C$12*U12)+($C$18*U18)+($C$13*U13)+($C$14*U14)+($C$15*U15)+($C$16*U16)+($C$17*U17) -> 0 | W19: =SUM($C$9*W9)+($C$10*W10)+($C$11*W11)+($C$12*W12)+($C$18*W18)+($C$13*W13)+($C$14*W14)+($C$15*W15)+($C$16*W16)+($C$17*W17) -> 0 | Y19: =SUM($C$9*Y9)+($C$10*Y10)+($C$11*Y11)+($C$12*Y12)+($C$18*Y18)+($C$13*Y13)+($C$14*Y14)+($C$15*Y15)+($C$16*Y16)+($C$17*Y17) -> 0 | AA19: =SUM($C$9*AA9)+($C$10*AA10)+($C$11*AA11)+($C$12*AA12)+($C$18*AA18)+($C$13*AA13)+($C$14*AA14)+($C$15*AA15)+($C$16*AA16)+($C$17*AA17) -> 0 | AC19: =SUM(AC8:AC18) -> 0 | AD19: =SUM(AD9:AD18) -> 0 | AE19: =SUM(AE9:AE18) -> #DIV/0! | AH19: =SUM(AH9:AH18) -> 0 | AI19: =AH19/AD19 -> #DIV/0!
B21: UMSATZPLANUNG
B22: 2. GESCHÄFTSJAHR | C22: =ZusammenführErgebn!D3 -> 2026 | E22: =E3 -> Jan. | G22: =G3 -> Febr. | I22: =I3 -> März | K22: =K3 -> April | M22: =M3 -> Mai | O22: =O3 -> Juni | Q22: =Q3 -> Juli | S22: =S3 -> Aug. | U22: =U3 -> Sept. | W22: =W3 -> Okt. | Y22: =Y3 -> Nov. | AA22: =AA3 -> Dez. | AC22: SUMME PRODUKTE / DL | AD22: SUMME DER EINZEL- UMSÄTZE | AE22: UMSATZ- STRUKTUR IN %
B24: Prod.Std./Monat_Soll | F24: =IF(ArbStd_MA!$F$33>=1,ArbStd_MA!$F$33,IF(ArbStd_MA!$F$33<1,ArbStd_MA!$F$23)) -> 144 | H24: =IF(ArbStd_MA!$F$33>=1,ArbStd_MA!$F$33,IF(ArbStd_MA!$F$33<1,ArbStd_MA!$F$23)) -> 144 | J24: =IF(ArbStd_MA!$F$33>=1,ArbStd_MA!$F$33,IF(ArbStd_MA!$F$33<1,ArbStd_MA!$F$23)) -> 144 | L24: =IF(ArbStd_MA!$F$33>=1,ArbStd_MA!$F$33,IF(ArbStd_MA!$F$33<1,ArbStd_MA!$F$23)) -> 144 | N24: =IF(ArbStd_MA!$F$33>=1,ArbStd_MA!$F$33,IF(ArbStd_MA!$F$33<1,ArbStd_MA!$F$23)) -> 144 | P24: =IF(ArbStd_MA!$F$33>=1,ArbStd_MA!$F$33,IF(ArbStd_MA!$F$33<1,ArbStd_MA!$F$23)) -> 144 | R24: =IF(ArbStd_MA!$F$33>=1,ArbStd_MA!$F$33,IF(ArbStd_MA!$F$33<1,ArbStd_MA!$F$23)) -> 144 | T24: =IF(ArbStd_MA!$F$33>=1,ArbStd_MA!$F$33,IF(ArbStd_MA!$F$33<1,ArbStd_MA!$F$23)) -> 144 | V24: =IF(ArbStd_MA!$F$33>=1,ArbStd_MA!$F$33,IF(ArbStd_MA!$F$33<1,ArbStd_MA!$F$23)) -> 144 | X24: =IF(ArbStd_MA!$F$33>=1,ArbStd_MA!$F$33,IF(ArbStd_MA!$F$33<1,ArbStd_MA!$F$23)) -> 144 | Z24: =IF(ArbStd_MA!$F$33>=1,ArbStd_MA!$F$33,IF(ArbStd_MA!$F$33<1,ArbStd_MA!$F$23)) -> 144 | AB24: =IF(ArbStd_MA!$F$33>=1,ArbStd_MA!$F$33,IF(ArbStd_MA!$F$33<1,ArbStd_MA!$F$23)) -> 144
B25: LeistungStd. Ist | F25: =SUM(F28:F37) -> 0 | H25: =SUM(H28:H37) -> 0 | J25: =SUM(J28:J37) -> 0 | L25: =SUM(L28:L37) -> 0 | N25: =SUM(N28:N37) -> 0 | P25: =SUM(P28:P37) -> 0 | R25: =SUM(R28:R37) -> 0 | T25: =SUM(T28:T37) -> 0 | V25: =SUM(V28:V37) -> 0 | X25: =SUM(X28:X37) -> 0 | Z25: =SUM(Z28:Z37) -> 0 | AB25: =SUM(AB28:AB37) -> 0 | AC25: =SUM(E25:AB25)/12 -> 0
C26: Einzel- preis | D26: Prod. Stunden | E26: verk. Stück | F26: Prod.Std. gesamt | G26: verk. Stück | H26: Prod.Std. gesamt | I26: verk. Stück | J26: Prod.Std. gesamt | K26: verk. Stück | L26: Prod.Std. gesamt | M26: verk. Stück | N26: Prod.Std. gesamt | O26: verk. Stück | P26: Prod.Std. gesamt | Q26: verk. Stück | R26: Prod.Std. gesamt | S26: verk. Stück | T26: Prod.Std. gesamt | U26: verk. Stück | V26: Prod.Std. gesamt | W26: verk. Stück | X26: Prod.Std. gesamt | Y26: verk. Stück | Z26: Prod.Std. gesamt | AA26: verk. Stück | AB26: Prod.Std. gesamt
B28: Produkt 1 | F28: =D28*E28 -> 0 | H28: =D28*G28 -> 0 | J28: =D28*I28 -> 0 | L28: =D28*K28 -> 0 | N28: =D28*M28 -> 0 | P28: =D28*O28 -> 0 | R28: =D28*Q28 -> 0 | T28: =D28*S28 -> 0 | V28: =D28*U28 -> 0 | X28: =D28*W28 -> 0 | Z28: =D28*Y28 -> 0 | AB28: =D28*AA28 -> 0 | AC28: =E28+G28+I28+K28+M28+O28+Q28+S28+U28+W28+Y28+AA28 -> 0 | AD28: =(E28+G28+I28+K28+M28+O28+Q28+S28+U28+W28+Y28+AA28)*C28 -> 0 | AE28: =AD28/$AD$38 -> #DIV/0!
B29: Produkt 2 | F29: =D29*E29 -> 0 | H29: =D29*G29 -> 0 | J29: =D29*I29 -> 0 | L29: =D29*K29 -> 0 | N29: =D29*M29 -> 0 | P29: =D29*O29 -> 0 | R29: =D29*Q29 -> 0 | T29: =D29*S29 -> 0 | V29: =D29*U29 -> 0 | X29: =D29*W29 -> 0 | Z29: =D29*Y29 -> 0 | AB29: =D29*AA29 -> 0 | AC29: =E29+G29+I29+K29+M29+O29+Q29+S29+U29+W29+Y29+AA29 -> 0 | AD29: =(E29+G29+I29+K29+M29+O29+Q29+S29+U29+W29+Y29+AA29)*C29 -> 0 | AE29: =AD29/$AD$38 -> #DIV/0!
B30: Produkt 3 | F30: =D30*E30 -> 0 | H30: =D30*G30 -> 0 | J30: =D30*I30 -> 0 | L30: =D30*K30 -> 0 | N30: =D30*M30 -> 0 | P30: =D30*O30 -> 0 | R30: =D30*Q30 -> 0 | T30: =D30*S30 -> 0 | V30: =D30*U30 -> 0 | X30: =D30*W30 -> 0 | Z30: =D30*Y30 -> 0 | AB30: =D30*AA30 -> 0 | AC30: =E30+G30+I30+K30+M30+O30+Q30+S30+U30+W30+Y30+AA30 -> 0 | AD30: =(E30+G30+I30+K30+M30+O30+Q30+S30+U30+W30+Y30+AA30)*C30 -> 0 | AE30: =AD30/$AD$38 -> #DIV/0!
B31: Produkt 4 | F31: =D31*E31 -> 0 | H31: =D31*G31 -> 0 | J31: =D31*I31 -> 0 | L31: =D31*K31 -> 0 | N31: =D31*M31 -> 0 | P31: =D31*O31 -> 0 | R31: =D31*Q31 -> 0 | T31: =D31*S31 -> 0 | V31: =D31*U31 -> 0 | X31: =D31*W31 -> 0 | Z31: =D31*Y31 -> 0 | AB31: =D31*AA31 -> 0 | AC31: =E31+G31+I31+K31+M31+O31+Q31+S31+U31+W31+Y31+AA31 -> 0 | AD31: =(E31+G31+I31+K31+M31+O31+Q31+S31+U31+W31+Y31+AA31)*C31 -> 0 | AE31: =AD31/$AD$38 -> #DIV/0!
B32: Produkt 5 | F32: =D32*E32 -> 0 | H32: =D32*G32 -> 0 | J32: =D32*I32 -> 0 | L32: =D32*K32 -> 0 | N32: =D32*M32 -> 0 | P32: =D32*O32 -> 0 | R32: =D32*Q32 -> 0 | T32: =D32*S32 -> 0 | V32: =D32*U32 -> 0 | X32: =D32*W32 -> 0 | Z32: =D32*Y32 -> 0 | AB32: =D32*AA32 -> 0 | AC32: =E32+G32+I32+K32+M32+O32+Q32+S32+U32+W32+Y32+AA32 -> 0 | AD32: =(E32+G32+I32+K32+M32+O32+Q32+S32+U32+W32+Y32+AA32)*C32 -> 0 | AE32: =AD32/$AD$38 -> #DIV/0!
B33: Leistung 1 | F33: =D33*E33 -> 0 | H33: =D33*G33 -> 0 | J33: =D33*I33 -> 0 | L33: =D33*K33 -> 0 | N33: =D33*M33 -> 0 | P33: =D33*O33 -> 0 | R33: =D33*Q33 -> 0 | T33: =D33*S33 -> 0 | V33: =D33*U33 -> 0 | X33: =D33*W33 -> 0 | Z33: =D33*Y33 -> 0 | AB33: =D33*AA33 -> 0 | AC33: =E33+G33+I33+K33+M33+O33+Q33+S33+U33+W33+Y33+AA33 -> 0 | AD33: =(E33+G33+I33+K33+M33+O33+Q33+S33+U33+W33+Y33+AA33)*C33 -> 0 | AE33: =AD33/$AD$38 -> #DIV/0!
B34: Leistung 2 | F34: =D34*E34 -> 0 | H34: =D34*G34 -> 0 | J34: =D34*I34 -> 0 | L34: =D34*K34 -> 0 | N34: =D34*M34 -> 0 | P34: =D34*O34 -> 0 | R34: =D34*Q34 -> 0 | T34: =D34*S34 -> 0 | V34: =D34*U34 -> 0 | X34: =D34*W34 -> 0 | Z34: =D34*Y34 -> 0 | AB34: =D34*AA34 -> 0 | AC34: =E34+G34+I34+K34+M34+O34+Q34+S34+U34+W34+Y34+AA34 -> 0 | AD34: =(E34+G34+I34+K34+M34+O34+Q34+S34+U34+W34+Y34+AA34)*C34 -> 0 | AE34: =AD34/$AD$38 -> #DIV/0!
B35: Leistung 3 | F35: =D35*E35 -> 0 | H35: =D35*G35 -> 0 | J35: =D35*I35 -> 0 | L35: =D35*K35 -> 0 | N35: =D35*M35 -> 0 | P35: =D35*O35 -> 0 | R35: =D35*Q35 -> 0 | T35: =D35*S35 -> 0 | V35: =D35*U35 -> 0 | X35: =D35*W35 -> 0 | Z35: =D35*Y35 -> 0 | AB35: =D35*AA35 -> 0 | AC35: =E35+G35+I35+K35+M35+O35+Q35+S35+U35+W35+Y35+AA35 -> 0 | AD35: =(E35+G35+I35+K35+M35+O35+Q35+S35+U35+W35+Y35+AA35)*C35 -> 0 | AE35: =AD35/$AD$38 -> #DIV/0!
B36: Leistung 4 | F36: =D36*E36 -> 0 | H36: =D36*G36 -> 0 | J36: =D36*I36 -> 0 | L36: =D36*K36 -> 0 | N36: =D36*M36 -> 0 | P36: =D36*O36 -> 0 | R36: =D36*Q36 -> 0 | T36: =D36*S36 -> 0 | V36: =D36*U36 -> 0 | X36: =D36*W36 -> 0 | Z36: =D36*Y36 -> 0 | AB36: =D36*AA36 -> 0 | AC36: =E36+G36+I36+K36+M36+O36+Q36+S36+U36+W36+Y36+AA36 -> 0 | AD36: =(E36+G36+I36+K36+M36+O36+Q36+S36+U36+W36+Y36+AA36)*C36 -> 0 | AE36: =AD36/$AD$38 -> #DIV/0!
B37: Leistung 5 | F37: =D37*E37 -> 0 | H37: =D37*G37 -> 0 | J37: =D37*I37 -> 0 | L37: =D37*K37 -> 0 | N37: =D37*M37 -> 0 | P37: =D37*O37 -> 0 | R37: =D37*Q37 -> 0 | T37: =D37*S37 -> 0 | V37: =D37*U37 -> 0 | X37: =D37*W37 -> 0 | Z37: =D37*Y37 -> 0 | AB37: =D37*AA37 -> 0 | AC37: =E37+G37+I37+K37+M37+O37+Q37+S37+U37+W37+Y37+AA37 -> 0 | AD37: =(E37+G37+I37+K37+M37+O37+Q37+S37+U37+W37+Y37+AA37)*C37 -> 0 | AE37: =AD37/$AD$38 -> #DIV/0!
B38: SUMME | E38: =SUM($C$28*E28)+($C$29*E29)+($C$30*E30)+($C$31*E31)+($C$32*E32)+($C$33*E33)+($C$34*E34)+($C$35*E35)+($C$36*E36)+($C$37*E37) -> 0 | G38: =SUM($C$28*G28)+($C$29*G29)+($C$30*G30)+($C$31*G31)+($C$32*G32)+($C$33*G33)+($C$34*G34)+($C$35*G35)+($C$36*G36)+($C$37*G37) -> 0 | I38: =SUM($C$28*I28)+($C$29*I29)+($C$30*I30)+($C$31*I31)+($C$32*I32)+($C$33*I33)+($C$34*I34)+($C$35*I35)+($C$36*I36)+($C$37*I37) -> 0 | K38: =SUM($C$28*K28)+($C$29*K29)+($C$30*K30)+($C$31*K31)+($C$32*K32)+($C$33*K33)+($C$34*K34)+($C$35*K35)+($C$36*K36)+($C$37*K37) -> 0 | M38: =SUM($C$28*M28)+($C$29*M29)+($C$30*M30)+($C$31*M31)+($C$32*M32)+($C$33*M33)+($C$34*M34)+($C$35*M35)+($C$36*M36)+($C$37*M37) -> 0 | O38: =SUM($C$28*O28)+($C$29*O29)+($C$30*O30)+($C$31*O31)+($C$32*O32)+($C$33*O33)+($C$34*O34)+($C$35*O35)+($C$36*O36)+($C$37*O37) -> 0 | Q38: =SUM($C$28*Q28)+($C$29*Q29)+($C$30*Q30)+($C$31*Q31)+($C$32*Q32)+($C$33*Q33)+($C$34*Q34)+($C$35*Q35)+($C$36*Q36)+($C$37*Q37) -> 0 | S38: =SUM($C$28*S28)+($C$29*S29)+($C$30*S30)+($C$31*S31)+($C$32*S32)+($C$33*S33)+($C$34*S34)+($C$35*S35)+($C$36*S36)+($C$37*S37) -> 0 | U38: =SUM($C$28*U28)+($C$29*U29)+($C$30*U30)+($C$31*U31)+($C$32*U32)+($C$33*U33)+($C$34*U34)+($C$35*U35)+($C$36*U36)+($C$37*U37) -> 0 | W38: =SUM($C$28*W28)+($C$29*W29)+($C$30*W30)+($C$31*W31)+($C$32*W32)+($C$33*W33)+($C$34*W34)+($C$35*W35)+($C$36*W36)+($C$37*W37) -> 0 | Y38: =SUM($C$28*Y28)+($C$29*Y29)+($C$30*Y30)+($C$31*Y31)+($C$32*Y32)+($C$33*Y33)+($C$34*Y34)+($C$35*Y35)+($C$36*Y36)+($C$37*Y37) -> 0 | AA38: =SUM($C$28*AA28)+($C$29*AA29)+($C$30*AA30)+($C$31*AA31)+($C$32*AA32)+($C$33*AA33)+($C$34*AA34)+($C$35*AA35)+($C$36*AA36)+($C$37*AA37) -> 0 | AC38: =SUM(AC27:AC37) -> 0 | AD38: =SUM(AD28:AD37) -> 0 | AE38: =SUM(AE28:AE37) -> #DIV/0!
B40: UMSATZPLANUNG
B41: 3. GESCHÄFTSJAHR | C41: =ZusammenführErgebn!E3 -> 2027 | E41: =E22 -> Jan. | G41: =G22 -> Febr. | I41: =I22 -> März | K41: =K22 -> April | M41: =M22 -> Mai | O41: =O22 -> Juni | Q41: =Q22 -> Juli | S41: =S22 -> Aug. | U41: =U22 -> Sept. | W41: =W22 -> Okt. | Y41: =Y22 -> Nov. | AA41: =AA22 -> Dez. | AC41: SUMME PRODUKTE / DL | AD41: SUMME DER EINZEL- UMSÄTZE | AE41: UMSATZ- STRUKTUR IN %
B43: Prod.Std./Monat_Soll | F43: =IF(ArbStd_MA!$H$33>=1,ArbStd_MA!$H$33,IF(ArbStd_MA!$H$33<1,ArbStd_MA!$H$23)) -> 144 | H43: =IF(ArbStd_MA!$H$33>=1,ArbStd_MA!$H$33,IF(ArbStd_MA!$H$33<1,ArbStd_MA!$H$23)) -> 144 | J43: =IF(ArbStd_MA!$H$33>=1,ArbStd_MA!$H$33,IF(ArbStd_MA!$H$33<1,ArbStd_MA!$H$23)) -> 144 | L43: =IF(ArbStd_MA!$H$33>=1,ArbStd_MA!$H$33,IF(ArbStd_MA!$H$33<1,ArbStd_MA!$H$23)) -> 144 | N43: =IF(ArbStd_MA!$H$33>=1,ArbStd_MA!$H$33,IF(ArbStd_MA!$H$33<1,ArbStd_MA!$H$23)) -> 144 | P43: =IF(ArbStd_MA!$H$33>=1,ArbStd_MA!$H$33,IF(ArbStd_MA!$H$33<1,ArbStd_MA!$H$23)) -> 144 | R43: =IF(ArbStd_MA!$H$33>=1,ArbStd_MA!$H$33,IF(ArbStd_MA!$H$33<1,ArbStd_MA!$H$23)) -> 144 | T43: =IF(ArbStd_MA!$H$33>=1,ArbStd_MA!$H$33,IF(ArbStd_MA!$H$33<1,ArbStd_MA!$H$23)) -> 144 | V43: =IF(ArbStd_MA!$H$33>=1,ArbStd_MA!$H$33,IF(ArbStd_MA!$H$33<1,ArbStd_MA!$H$23)) -> 144 | X43: =IF(ArbStd_MA!$H$33>=1,ArbStd_MA!$H$33,IF(ArbStd_MA!$H$33<1,ArbStd_MA!$H$23)) -> 144 | Z43: =IF(ArbStd_MA!$H$33>=1,ArbStd_MA!$H$33,IF(ArbStd_MA!$H$33<1,ArbStd_MA!$H$23)) -> 144 | AB43: =IF(ArbStd_MA!$H$33>=1,ArbStd_MA!$H$33,IF(ArbStd_MA!$H$33<1,ArbStd_MA!$H$23)) -> 144
B44: LeistungStd. Ist | F44: =SUM(F47:F56) -> 0 | H44: =SUM(H47:H56) -> 0 | J44: =SUM(J47:J56) -> 0 | L44: =SUM(L47:L56) -> 0 | N44: =SUM(N47:N56) -> 0 | P44: =SUM(P47:P56) -> 0 | R44: =SUM(R47:R56) -> 0 | T44: =SUM(T47:T56) -> 0 | V44: =SUM(V47:V56) -> 0 | X44: =SUM(X47:X56) -> 0 | Z44: =SUM(Z47:Z56) -> 0 | AB44: =SUM(AB47:AB56) -> 0 | AC44: =SUM(E44:AB44)/12 -> 0
C45: Einzel- preis | D45: Prod. Stunden | E45: verk. Stück | F45: Prod.Std. gesamt | G45: verk. Stück | H45: Prod.Std. gesamt | I45: verk. Stück | J45: Prod.Std. gesamt | K45: verk. Stück | L45: Prod.Std. gesamt | M45: verk. Stück | N45: Prod.Std. gesamt | O45: verk. Stück | P45: Prod.Std. gesamt | Q45: verk. Stück | R45: Prod.Std. gesamt | S45: verk. Stück | T45: Prod.Std. gesamt | U45: verk. Stück | V45: Prod.Std. gesamt | W45: verk. Stück | X45: Prod.Std. gesamt | Y45: verk. Stück | Z45: Prod.Std. gesamt | AA45: verk. Stück | AB45: Prod.Std. gesamt
B47: Produkt 1 | F47: =D47*E47 -> 0 | H47: =D47*G47 -> 0 | J47: =D47*I47 -> 0 | L47: =D47*K47 -> 0 | N47: =D47*M47 -> 0 | P47: =D47*O47 -> 0 | R47: =D47*Q47 -> 0 | T47: =D47*S47 -> 0 | V47: =D47*U47 -> 0 | X47: =D47*W47 -> 0 | Z47: =D47*Y47 -> 0 | AB47: =D47*AA47 -> 0 | AC47: =E47+G47+I47+K47+M47+O47+Q47+S47+U47+W47+Y47+AA47 -> 0 | AD47: =(E47+G47+I47+K47+M47+O47+Q47+S47+U47+W47+Y47+AA47)*C47 -> 0 | AE47: =AD47/$AD$57 -> #DIV/0!
B48: Produkt 2 | F48: =D48*E48 -> 0 | H48: =D48*G48 -> 0 | J48: =D48*I48 -> 0 | L48: =D48*K48 -> 0 | N48: =D48*M48 -> 0 | P48: =D48*O48 -> 0 | R48: =D48*Q48 -> 0 | T48: =D48*S48 -> 0 | V48: =D48*U48 -> 0 | X48: =D48*W48 -> 0 | Z48: =D48*Y48 -> 0 | AB48: =D48*AA48 -> 0 | AC48: =E48+G48+I48+K48+M48+O48+Q48+S48+U48+W48+Y48+AA48 -> 0 | AD48: =(E48+G48+I48+K48+M48+O48+Q48+S48+U48+W48+Y48+AA48)*C48 -> 0 | AE48: =AD48/$AD$57 -> #DIV/0!
B49: Produkt 3 | F49: =D49*E49 -> 0 | H49: =D49*G49 -> 0 | J49: =D49*I49 -> 0 | L49: =D49*K49 -> 0 | N49: =D49*M49 -> 0 | P49: =D49*O49 -> 0 | R49: =D49*Q49 -> 0 | T49: =D49*S49 -> 0 | V49: =D49*U49 -> 0 | X49: =D49*W49 -> 0 | Z49: =D49*Y49 -> 0 | AB49: =D49*AA49 -> 0 | AC49: =E49+G49+I49+K49+M49+O49+Q49+S49+U49+W49+Y49+AA49 -> 0 | AD49: =(E49+G49+I49+K49+M49+O49+Q49+S49+U49+W49+Y49+AA49)*C49 -> 0 | AE49: =AD49/$AD$57 -> #DIV/0!
B50: Produkt 4 | F50: =D50*E50 -> 0 | H50: =D50*G50 -> 0 | J50: =D50*I50 -> 0 | L50: =D50*K50 -> 0 | N50: =D50*M50 -> 0 | P50: =D50*O50 -> 0 | R50: =D50*Q50 -> 0 | T50: =D50*S50 -> 0 | V50: =D50*U50 -> 0 | X50: =D50*W50 -> 0 | Z50: =D50*Y50 -> 0 | AB50: =D50*AA50 -> 0 | AC50: =E50+G50+I50+K50+M50+O50+Q50+S50+U50+W50+Y50+AA50 -> 0 | AD50: =(E50+G50+I50+K50+M50+O50+Q50+S50+U50+W50+Y50+AA50)*C50 -> 0 | AE50: =AD50/$AD$57 -> #DIV/0!
B51: Produkt 5 | F51: =D51*E51 -> 0 | H51: =D51*G51 -> 0 | J51: =D51*I51 -> 0 | L51: =D51*K51 -> 0 | N51: =D51*M51 -> 0 | P51: =D51*O51 -> 0 | R51: =D51*Q51 -> 0 | T51: =D51*S51 -> 0 | V51: =D51*U51 -> 0 | X51: =D51*W51 -> 0 | Z51: =D51*Y51 -> 0 | AB51: =D51*AA51 -> 0 | AC51: =E51+G51+I51+K51+M51+O51+Q51+S51+U51+W51+Y51+AA51 -> 0 | AD51: =(E51+G51+I51+K51+M51+O51+Q51+S51+U51+W51+Y51+AA51)*C51 -> 0 | AE51: =AD51/$AD$57 -> #DIV/0!
B52: Leistung 1 | F52: =D52*E52 -> 0 | H52: =D52*G52 -> 0 | J52: =D52*I52 -> 0 | L52: =D52*K52 -> 0 | N52: =D52*M52 -> 0 | P52: =D52*O52 -> 0 | R52: =D52*Q52 -> 0 | T52: =D52*S52 -> 0 | V52: =D52*U52 -> 0 | X52: =D52*W52 -> 0 | Z52: =D52*Y52 -> 0 | AB52: =D52*AA52 -> 0 | AC52: =E52+G52+I52+K52+M52+O52+Q52+S52+U52+W52+Y52+AA52 -> 0 | AD52: =(E52+G52+I52+K52+M52+O52+Q52+S52+U52+W52+Y52+AA52)*C52 -> 0 | AE52: =AD52/$AD$57 -> #DIV/0!
B53: Leistung 2 | F53: =D53*E53 -> 0 | H53: =D53*G53 -> 0 | J53: =D53*I53 -> 0 | L53: =D53*K53 -> 0 | N53: =D53*M53 -> 0 | P53: =D53*O53 -> 0 | R53: =D53*Q53 -> 0 | T53: =D53*S53 -> 0 | V53: =D53*U53 -> 0 | X53: =D53*W53 -> 0 | Z53: =D53*Y53 -> 0 | AB53: =D53*AA53 -> 0 | AC53: =E53+G53+I53+K53+M53+O53+Q53+S53+U53+W53+Y53+AA53 -> 0 | AD53: =(E53+G53+I53+K53+M53+O53+Q53+S53+U53+W53+Y53+AA53)*C53 -> 0 | AE53: =AD53/$AD$57 -> #DIV/0!
B54: Leistung 3 | F54: =D54*E54 -> 0 | H54: =D54*G54 -> 0 | J54: =D54*I54 -> 0 | L54: =D54*K54 -> 0 | N54: =D54*M54 -> 0 | P54: =D54*O54 -> 0 | R54: =D54*Q54 -> 0 | T54: =D54*S54 -> 0 | V54: =D54*U54 -> 0 | X54: =D54*W54 -> 0 | Z54: =D54*Y54 -> 0 | AB54: =D54*AA54 -> 0 | AC54: =E54+G54+I54+K54+M54+O54+Q54+S54+U54+W54+Y54+AA54 -> 0 | AD54: =(E54+G54+I54+K54+M54+O54+Q54+S54+U54+W54+Y54+AA54)*C54 -> 0 | AE54: =AD54/$AD$57 -> #DIV/0!
B55: Leistung 4 | F55: =D55*E55 -> 0 | H55: =D55*G55 -> 0 | J55: =D55*I55 -> 0 | L55: =D55*K55 -> 0 | N55: =D55*M55 -> 0 | P55: =D55*O55 -> 0 | R55: =D55*Q55 -> 0 | T55: =D55*S55 -> 0 | V55: =D55*U55 -> 0 | X55: =D55*W55 -> 0 | Z55: =D55*Y55 -> 0 | AB55: =D55*AA55 -> 0 | AC55: =E55+G55+I55+K55+M55+O55+Q55+S55+U55+W55+Y55+AA55 -> 0 | AD55: =(E55+G55+I55+K55+M55+O55+Q55+S55+U55+W55+Y55+AA55)*C55 -> 0 | AE55: =AD55/$AD$57 -> #DIV/0!
B56: Leistung 5 | F56: =D56*E56 -> 0 | H56: =D56*G56 -> 0 | J56: =D56*I56 -> 0 | L56: =D56*K56 -> 0 | N56: =D56*M56 -> 0 | P56: =D56*O56 -> 0 | R56: =D56*Q56 -> 0 | T56: =D56*S56 -> 0 | V56: =D56*U56 -> 0 | X56: =D56*W56 -> 0 | Z56: =D56*Y56 -> 0 | AB56: =D56*AA56 -> 0 | AC56: =E56+G56+I56+K56+M56+O56+Q56+S56+U56+W56+Y56+AA56 -> 0 | AD56: =(E56+G56+I56+K56+M56+O56+Q56+S56+U56+W56+Y56+AA56)*C56 -> 0 | AE56: =AD56/$AD$57 -> #DIV/0!
B57: SUMME | E57: =SUM($C$47*E47)+($C$48*E48)+($C$49*E49)+($C$50*E50)+($C$51*E51)+($C$52*E52)+($C$53*E53)+($C$54*E54)+($C$55*E55)+($C$56*E56) -> 0 | G57: =SUM($C$47*G47)+($C$48*G48)+($C$49*G49)+($C$50*G50)+($C$51*G51)+($C$52*G52)+($C$53*G53)+($C$54*G54)+($C$55*G55)+($C$56*G56) -> 0 | I57: =SUM($C$47*I47)+($C$48*I48)+($C$49*I49)+($C$50*I50)+($C$51*I51)+($C$52*I52)+($C$53*I53)+($C$54*I54)+($C$55*I55)+($C$56*I56) -> 0 | K57: =SUM($C$47*K47)+($C$48*K48)+($C$49*K49)+($C$50*K50)+($C$51*K51)+($C$52*K52)+($C$53*K53)+($C$54*K54)+($C$55*K55)+($C$56*K56) -> 0 | M57: =SUM($C$47*M47)+($C$48*M48)+($C$49*M49)+($C$50*M50)+($C$51*M51)+($C$52*M52)+($C$53*M53)+($C$54*M54)+($C$55*M55)+($C$56*M56) -> 0 | O57: =SUM($C$47*O47)+($C$48*O48)+($C$49*O49)+($C$50*O50)+($C$51*O51)+($C$52*O52)+($C$53*O53)+($C$54*O54)+($C$55*O55)+($C$56*O56) -> 0 | Q57: =SUM($C$47*Q47)+($C$48*Q48)+($C$49*Q49)+($C$50*Q50)+($C$51*Q51)+($C$52*Q52)+($C$53*Q53)+($C$54*Q54)+($C$55*Q55)+($C$56*Q56) -> 0 | S57: =SUM($C$47*S47)+($C$48*S48)+($C$49*S49)+($C$50*S50)+($C$51*S51)+($C$52*S52)+($C$53*S53)+($C$54*S54)+($C$55*S55)+($C$56*S56) -> 0 | U57: =SUM($C$47*U47)+($C$48*U48)+($C$49*U49)+($C$50*U50)+($C$51*U51)+($C$52*U52)+($C$53*U53)+($C$54*U54)+($C$55*U55)+($C$56*U56) -> 0 | W57: =SUM($C$47*W47)+($C$48*W48)+($C$49*W49)+($C$50*W50)+($C$51*W51)+($C$52*W52)+($C$53*W53)+($C$54*W54)+($C$55*W55)+($C$56*W56) -> 0 | Y57: =SUM($C$47*Y47)+($C$48*Y48)+($C$49*Y49)+($C$50*Y50)+($C$51*Y51)+($C$52*Y52)+($C$53*Y53)+($C$54*Y54)+($C$55*Y55)+($C$56*Y56) -> 0 | AA57: =SUM($C$47*AA47)+($C$48*AA48)+($C$49*AA49)+($C$50*AA50)+($C$51*AA51)+($C$52*AA52)+($C$53*AA53)+($C$54*AA54)+($C$55*AA55)+($C$56*AA56) -> 0 | AC57: =SUM(AC46:AC56) -> 0 | AD57: =SUM(AD47:AD56) -> 0 | AE57: =SUM(AE47:AE56) -> #DIV/0!
B59: Besonderer Hinweis
C60: Beschreiben Sie hier unter welchen Voraussetzungen Sie die Umsatzplanung gemacht haben! z.B.: Art und Umfang der Anlaufphase? Wie entwickelt sich die Umsatzstruktur? Wie beeinflusst die Konjunktur ihre Umsatzplanung? Wie ist die Branchenentwicklung? Gibt es hohen Konkurrenzdruck? Gibt es Preisdruck usw.?

Sheet LiquiRech.1-3Jahr
B1: LIQUIDITÄTSPLANUNG Jahr 1 | H1: =Deckblatt!C5 -> Max Mustermann
B2: 1 | C2: Bei Umsatzeingang bar "0" eintragen, bei Eingang nach 30 Tagen "1", bei Eingang nach 60 Tagen "2" eintragen, bei Eingang nach 45 Tagen "3" eintragen | O2: MWSt aus Deckblatt | P2: =Deckblatt!C9 -> 0.19
B3: =ZusammenführErgebn!C3 -> 2025 | D3: ='Ertragsv. 2025'!C2 -> Jan. | E3: ='Ertragsv. 2025'!D2 -> Febr. | F3: ='Ertragsv. 2025'!E2 -> März | G3: ='Ertragsv. 2025'!F2 -> April | H3: ='Ertragsv. 2025'!G2 -> Mai | I3: ='Ertragsv. 2025'!H2 -> Juni | J3: ='Ertragsv. 2025'!I2 -> Juli | K3: ='Ertragsv. 2025'!J2 -> Aug. | ... O3: ='Ertragsv. 2025'!N2 -> Dez. | P3: Summe
B4: EINZAHLUNGEN
B5: + Umsatz | D5: =IF($B$2=0,'Ertragsv. 2025'!C3,IF($B$2=1,0,IF($B$2=2,0,IF($B$2=3,0)))) -> 0 | E5: =IF($B$2=0,'Ertragsv. 2025'!D3,IF($B$2=1,'Ertragsv. 2025'!C3,IF($B$2=2,0,IF($B$2=3,'Ertragsv. 2025'!C3*50%)))) -> 0 | F5: =IF($B$2=0,'Ertragsv. 2025'!E3,IF($B$2=1,'Ertragsv. 2025'!D3,IF($B$2=2,'Ertragsv. 2025'!C3,IF($B$2=3,'Ertragsv. 2025'!C3*50%+'Ertragsv. 2025'!D3*50%)))) -> 0 | G5: =IF($B$2=0,'Ertragsv. 2025'!F3,IF($B$2=1,'Ertragsv. 2025'!E3,IF($B$2=2,'Ertragsv. 2025'!D3,IF($B$2=3,'Ertragsv. 2025'!D3*50%+'Ertragsv. 2025'!E3*50%)))) -> 0 | H5: =IF($B$2=0,'Ertragsv. 2025'!G3,IF($B$2=1,'Ertragsv. 2025'!F3,IF($B$2=2,'Ertragsv. 2025'!E3,IF($B$2=3,'Ertragsv. 2025'!E3*50%+'Ertragsv. 2025'!F3*50%)))) -> 0 | I5: =IF($B$2=0,'Ertragsv. 2025'!H3,IF($B$2=1,'Ertragsv. 2025'!G3,IF($B$2=2,'Ertragsv. 2025'!F3,IF($B$2=3,'Ertragsv. 2025'!F3*50%+'Ertragsv. 2025'!G3*50%)))) -> 0 | J5: =IF($B$2=0,'Ertragsv. 2025'!I3,IF($B$2=1,'Ertragsv. 2025'!H3,IF($B$2=2,'Ertragsv. 2025'!G3,IF($B$2=3,'Ertragsv. 2025'!G3*50%+('Ertragsv. 2025'!H3*50%))))) -> 0 | K5: =IF($B$2=0,'Ertragsv. 2025'!J3,IF($B$2=1,'Ertragsv. 2025'!I3,IF($B$2=2,'Ertragsv. 2025'!H3,IF($B$2=3,'Ertragsv. 2025'!H3*50%+('Ertragsv. 2025'!I3*50%))))) -> 0 | L5: =IF($B$2=0,'Ertragsv. 2025'!K3,IF($B$2=1,'Ertragsv. 2025'!J3,IF($B$2=2,'Ertragsv. 2025'!I3,IF($B$2=3,'Ertragsv. 2025'!I3*50%+'Ertragsv. 2025'!J3*50%)))) -> 0 | M5: =IF($B$2=0,'Ertragsv. 2025'!L3,IF($B$2=1,'Ertragsv. 2025'!K3,IF($B$2=2,'Ertragsv. 2025'!J3,IF($B$2=3,'Ertragsv. 2025'!J3*50%+'Ertragsv. 2025'!K3*50%)))) -> 0 | N5: =IF($B$2=0,'Ertragsv. 2025'!M3,IF($B$2=1,'Ertragsv. 2025'!L3,IF($B$2=2,'Ertragsv. 2025'!K3,IF($B$2=3,'Ertragsv. 2025'!K3*50%+'Ertragsv. 2025'!L3*50%)))) -> 0 | O5: =IF($B$2=0,'Ertragsv. 2025'!N3,IF($B$2=1,'Ertragsv. 2025'!M3,IF($B$2=2,'Ertragsv. 2025'!L3,IF($B$2=3,'Ertragsv. 2025'!L3*50%+'Ertragsv. 2025'!M3*50%)))) -> 0 | P5: =SUM(D5:O5) -> 0
B6: + Einzahlungen-Eigenkapital | D6: =Finanz_AfA_Investitionen!C31 -> 0 | P6: =SUM(D6:O6) -> 0
B7: + Kredite / Darlehen | P7: =SUM(D7:O7) -> 0
B8: + Gründungszuschuß | P8: =SUM(D8:O8) -> 0
B9: + MwSt | D9: =IF($P$2<0,0,IF($P$2>0,D5*19%,0)) -> 0 | E9: =IF($P$2<0,0,IF($P$2>0,E5*19%,0)) -> 0 | F9: =IF($P$2<0,0,IF($P$2>0,F5*19%,0)) -> 0 | G9: =IF($P$2<0,0,IF($P$2>0,G5*19%,0)) -> 0 | H9: =IF($P$2<0,0,IF($P$2>0,H5*19%,0)) -> 0 | I9: =IF($P$2<0,0,IF($P$2>0,I5*19%,0)) -> 0 | J9: =IF($P$2<0,0,IF($P$2>0,J5*19%,0)) -> 0 | K9: =IF($P$2<0,0,IF($P$2>0,K5*19%,0)) -> 0 | ... O9: =IF($P$2<0,0,IF($P$2>0,O5*19%,0)) -> 0 | P9: =SUM(D9:O9) -> 0
B10: = Summe Liquiditätszugang | D10: =SUM(D5:D9) -> 0 | E10: =SUM(E5:E9) -> 0 | F10: =SUM(F5:F9) -> 0 | G10: =SUM(G5:G9) -> 0 | H10: =SUM(H5:H9) -> 0 | I10: =SUM(I5:I9) -> 0 | J10: =SUM(J5:J9) -> 0 | K10: =SUM(K5:K9) -> 0 | ... O10: =SUM(O5:O9) -> 0 | P10: =SUM(D10:O10) -> 0
B11: AUSZAHLUNGEN
B12: + Anlageninvestition | P12: =SUM(D12:O12) -> 0
B13: + Vorsteuer | D13: =IF($P$2>0,(D14)*$P$2+(D12+D15)*19%-('Ertragsv. 2025'!C7+'Ertragsv. 2025'!C14+'Ertragsv. 2025'!C17+'Ertragsv. 2025'!C18)*19%,0) -> 0 | E13: =IF($P$2>0,(E14)*$P$2+(E12+E15)*19%-('Ertragsv. 2025'!D7+'Ertragsv. 2025'!D14+'Ertragsv. 2025'!D17+'Ertragsv. 2025'!D18)*19%,0) -> 0 | F13: =IF($P$2>0,(F14)*$P$2+(F12+F15)*19%-('Ertragsv. 2025'!E7+'Ertragsv. 2025'!E14+'Ertragsv. 2025'!E17+'Ertragsv. 2025'!E18)*19%,0) -> 0 | G13: =IF($P$2>0,(G14)*$P$2+(G12+G15)*19%-('Ertragsv. 2025'!F7+'Ertragsv. 2025'!F14+'Ertragsv. 2025'!F17+'Ertragsv. 2025'!F18)*19%,0) -> 0 | H13: =IF($P$2>0,(H14)*$P$2+(H12+H15)*19%-('Ertragsv. 2025'!G7+'Ertragsv. 2025'!G14+'Ertragsv. 2025'!G17+'Ertragsv. 2025'!G18)*19%,0) -> 0 | I13: =IF($P$2>0,(I14)*$P$2+(I12+I15)*19%-('Ertragsv. 2025'!H7+'Ertragsv. 2025'!H14+'Ertragsv. 2025'!H17+'Ertragsv. 2025'!H18)*19%,0) -> 0 | J13: =IF($P$2>0,(J14)*$P$2+(J12+J15)*19%-('Ertragsv. 2025'!I7+'Ertragsv. 2025'!I14+'Ertragsv. 2025'!I17+'Ertragsv. 2025'!I18)*19%,0) -> 0 | K13: =IF($P$2>0,(K14)*$P$2+(K12+K15)*19%-('Ertragsv. 2025'!J7+'Ertragsv. 2025'!J14+'Ertragsv. 2025'!J17+'Ertragsv. 2025'!J18)*19%,0) -> 0 | ... O13: =IF($P$2>0,(O14)*$P$2+(O12+O15)*19%-('Ertragsv. 2025'!N7+'Ertragsv. 2025'!N14+'Ertragsv. 2025'!N17+'Ertragsv. 2025'!N18)*19%,0) -> 0 | P13: =SUM(D13:O13) -> 0
B14: + Material/Wareneinkaurf | D14: ='Ertragsv. 2025'!C4 -> 0 | E14: ='Ertragsv. 2025'!D4 -> 0 | F14: ='Ertragsv. 2025'!E4 -> 0 | G14: ='Ertragsv. 2025'!F4 -> 0 | H14: ='Ertragsv. 2025'!G4 -> 0 | I14: ='Ertragsv. 2025'!H4 -> 0 | J14: ='Ertragsv. 2025'!I4 -> 0 | K14: ='Ertragsv. 2025'!J4 -> 0 | ... O14: ='Ertragsv. 2025'!N4 -> 0 | P14: =SUM(D14:O14) -> 0
B15: + Betriebsausgaben (PK+SK) | D15: ='Ertragsv. 2025'!C20-'Ertragsv. 2025'!C4 -> 0 | E15: ='Ertragsv. 2025'!D20-'Ertragsv. 2025'!D4 -> 0 | F15: ='Ertragsv. 2025'!E20-'Ertragsv. 2025'!E4 -> 0 | G15: ='Ertragsv. 2025'!F20-'Ertragsv. 2025'!F4 -> 0 | H15: ='Ertragsv. 2025'!G20-'Ertragsv. 2025'!G4 -> 0 | I15: ='Ertragsv. 2025'!H20-'Ertragsv. 2025'!H4 -> 0 | J15: ='Ertragsv. 2025'!I20-'Ertragsv. 2025'!I4 -> 0 | K15: ='Ertragsv. 2025'!J20-'Ertragsv. 2025'!J4 -> 0 | ... O15: ='Ertragsv. 2025'!N20-'Ertragsv. 2025'!N4 -> 0 | P15: =SUM(D15:O15) -> 0
B16: + Kredittilgung | D16: =Finanz_AfA_Investitionen!G38-Finanz_AfA_Investitionen!G37+'Mikrostarter Geschäftsplan'!C16 -> 0 | E16: =Finanz_AfA_Investitionen!G38-Finanz_AfA_Investitionen!G37+'Mikrostarter Geschäftsplan'!C17 -> 0 | F16: =Finanz_AfA_Investitionen!G38-Finanz_AfA_Investitionen!G37+'Mikrostarter Geschäftsplan'!C18 -> 0 | G16: =Finanz_AfA_Investitionen!G38-Finanz_AfA_Investitionen!G37+'Mikrostarter Geschäftsplan'!C20 -> 0 | H16: =Finanz_AfA_Investitionen!G38-Finanz_AfA_Investitionen!G37+'Mikrostarter Geschäftsplan'!C21 -> 0 | I16: =Finanz_AfA_Investitionen!G38-Finanz_AfA_Investitionen!G37+'Mikrostarter Geschäftsplan'!C22 -> 0 | J16: =Finanz_AfA_Investitionen!G38-Finanz_AfA_Investitionen!G37+'Mikrostarter Geschäftsplan'!C24 -> 0 | K16: =Finanz_AfA_Investitionen!G38-Finanz_AfA_Investitionen!G37+'Mikrostarter Geschäftsplan'!C25 -> 0 | L16: =Finanz_AfA_Investitionen!G38-Finanz_AfA_Investitionen!G37+'Mikrostarter Geschäftsplan'!C26 -> 0 | M16: =Finanz_AfA_Investitionen!G38-Finanz_AfA_Investitionen!G37+'Mikrostarter Geschäftsplan'!C28 -> 0 | N16: =Finanz_AfA_Investitionen!G38-Finanz_AfA_Investitionen!G37+'Mikrostarter Geschäftsplan'!C29 -> 0 | O16: =Finanz_AfA_Investitionen!G38-Finanz_AfA_Investitionen!G37+'Mikrostarter Geschäftsplan'!C30 -> 0 | P16: =SUM(D16:O16) -> 0
B17: + Sonst(z.B. Warenerstausstattung) | P17: =SUM(D17:O17) -> 0
B18: + MwSt Zahllast | E18: =D9-D13 -> 0 | F18: =E9-E13 -> 0 | G18: =F9-F13 -> 0 | H18: =G9-G13 -> 0 | I18: =H9-H13 -> 0 | J18: =I9-I13 -> 0 | K18: =J9-J13 -> 0 | L18: =K9-K13 -> 0 | ... O18: =N9-N13 -> 0 | P18: =SUM(E18:O18) -> 0
B19: + Steuern | D19: ='Ertragsv. 2025'!C25 -> 0 | E19: ='Ertragsv. 2025'!D25 -> 0 | F19: ='Ertragsv. 2025'!E25 -> 0 | G19: ='Ertragsv. 2025'!F25 -> 0 | H19: ='Ertragsv. 2025'!G25 -> 0 | I19: ='Ertragsv. 2025'!H25 -> 0 | J19: ='Ertragsv. 2025'!I25 -> 0 | K19: ='Ertragsv. 2025'!J25 -> 0 | ... O19: ='Ertragsv. 2025'!N25 -> 0 | P19: =SUM(D19:O19) -> 0
B20: + UnternehmerInnen- Lohn | D20: ='Ertragsv. 2025'!C27 -> 0 | E20: ='Ertragsv. 2025'!D27 -> 0 | F20: ='Ertragsv. 2025'!E27 -> 0 | G20: ='Ertragsv. 2025'!F27 -> 0 | H20: ='Ertragsv. 2025'!G27 -> 0 | I20: ='Ertragsv. 2025'!H27 -> 0 | J20: ='Ertragsv. 2025'!I27 -> 0 | K20: ='Ertragsv. 2025'!J27 -> 0 | ... O20: ='Ertragsv. 2025'!N27 -> 0 | P20: =SUM(D20:O20) -> 0
B21: + sonstige Auszahlungen | P21: =SUM(D21:O21) -> 0
B22: = Summe Liquiditätsabgang | D22: =SUM(D12:D21) -> 0 | E22: =SUM(E12:E21) -> 0 | F22: =SUM(F12:F21) -> 0 | G22: =SUM(G12:G21) -> 0 | H22: =SUM(H12:H21) -> 0 | I22: =SUM(I12:I21) -> 0 | J22: =SUM(J12:J21) -> 0 | K22: =SUM(K12:K21) -> 0 | ... O22: =SUM(O12:O21) -> 0 | P22: =SUM(D22:O22) -> 0
B23: Liquiditätssaldo | D23: =D10-D22 -> 0 | E23: =E10-E22 -> 0 | F23: =F10-F22 -> 0 | G23: =G10-G22 -> 0 | H23: =H10-H22 -> 0 | I23: =I10-I22 -> 0 | J23: =J10-J22 -> 0 | K23: =K10-K22 -> 0 | ... O23: =O10-O22 -> 0 | P23: =SUM(D23:O23) -> 0
B24: Liquiditätssaldo (kumuliert) | D24: =D23 -> 0 | E24: =D24+E23 -> 0 | F24: =E24+F23 -> 0 | G24: =F24+G23 -> 0 | H24: =G24+H23 -> 0 | I24: =H24+I23 -> 0 | J24: =I24+J23 -> 0 | K24: =J24+K23 -> 0 | L24: =K24+L23 -> 0 | ... O24: =N24+O23 -> 0 | P24: =P23 -> 0
B26: Kontokorrentlinie | D26: =Finanz_AfA_Investitionen!C34 -> 0 | E26: =D26 -> 0 | F26: =E26 -> 0 | G26: =F26 -> 0 | H26: =G26 -> 0 | I26: =H26 -> 0 | J26: =I26 -> 0 | K26: =J26 -> 0 | L26: =K26 -> 0 | ... O26: =N26 -> 0
B28: Saldo | D28: =D24+D26 -> 0 | E28: =E24+E26 -> 0 | F28: =F24+F26 -> 0 | G28: =G24+G26 -> 0 | H28: =H24+H26 -> 0 | I28: =I24+I26 -> 0 | J28: =J24+J26 -> 0 | K28: =K24+K26 -> 0 | ... O28: =O24+O26 -> 0
B30: LIQUIDITÄTSPLANUNG Jahr 2
B31: 1 | C31: Bei Umsatzeingang bar "0" eintragen,bei Eingang nach 30 Tagen "1", bei Eingang nach 60 Tagen "2" eintragen,bei Eingang nach 45 Tagen "3" eintragen
B32: =ZusammenführErgebn!D3 -> 2026 | D32: =D3 -> Jan. | E32: =E3 -> Febr. | F32: =F3 -> März | G32: =G3 -> April | H32: =H3 -> Mai | I32: =I3 -> Juni | J32: =J3 -> Juli | K32: =K3 -> Aug. | ... O32: =O3 -> Dez. | P32: Summe
B33: EINZAHLUNGEN
B34: + Umsatz | D34: =IF($B$31=0,'Ertragsv. 2026'!C3,IF($B$31=1,'Ertragsv. 2025'!N3,IF($B$31=2,'Ertragsv. 2025'!M3,IF($B$31=3,'Ertragsv. 2025'!M3*50%+'Ertragsv. 2025'!N3*50%)))) -> 0 | E34: =IF($B$31=0,'Ertragsv. 2026'!D3,IF($B$31=1,'Ertragsv. 2026'!C3,IF($B$31=2,'Ertragsv. 2025'!N3,IF($B$31=3,'Ertragsv. 2025'!N3*50%+'Ertragsv. 2026'!C3*50%)))) -> 0 | F34: =IF($B$31=0,'Ertragsv. 2026'!E3,IF($B$31=1,'Ertragsv. 2026'!D3,IF($B$31=2,'Ertragsv. 2026'!C3,IF($B$31=3,'Ertragsv. 2026'!C3*50%+'Ertragsv. 2026'!D3*50%)))) -> 0 | G34: =IF($B$31=0,'Ertragsv. 2026'!F3,IF($B$31=1,'Ertragsv. 2026'!E3,IF($B$31=2,'Ertragsv. 2026'!D3,IF($B$31=3,'Ertragsv. 2026'!E3*50%+'Ertragsv. 2026'!D3*50%)))) -> 0 | H34: =IF($B$31=0,'Ertragsv. 2026'!G3,IF($B$31=1,'Ertragsv. 2026'!F3,IF($B$31=2,'Ertragsv. 2026'!E3,IF($B$31=3,'Ertragsv. 2026'!E3*50%+'Ertragsv. 2026'!F3*50%)))) -> 0 | I34: =IF($B$31=0,'Ertragsv. 2026'!H3,IF($B$31=1,'Ertragsv. 2026'!G3,IF($B$31=2,'Ertragsv. 2026'!F3,IF($B$31=3,'Ertragsv. 2026'!F3*50%+'Ertragsv. 2026'!G3*50%)))) -> 0 | J34: =IF($B$31=0,'Ertragsv. 2026'!I3,IF($B$31=1,'Ertragsv. 2026'!H3,IF($B$31=2,'Ertragsv. 2026'!G3,IF($B$31=3,'Ertragsv. 2026'!G3*50%+'Ertragsv. 2026'!H3*50%)))) -> 0 | K34: =IF($B$31=0,'Ertragsv. 2026'!J3,IF($B$31=1,'Ertragsv. 2026'!I3,IF($B$31=2,'Ertragsv. 2026'!H3,IF($B$31=3,'Ertragsv. 2026'!H3*50%+'Ertragsv. 2026'!I3*50%)))) -> 0 | L34: =IF($B$31=0,'Ertragsv. 2026'!K3,IF($B$31=1,'Ertragsv. 2026'!J3,IF($B$31=2,'Ertragsv. 2026'!I3,IF($B$31=3,'Ertragsv. 2026'!I3*50%+'Ertragsv. 2026'!J3*50%)))) -> 0 | M34: =IF($B$31=0,'Ertragsv. 2026'!L3,IF($B$31=1,'Ertragsv. 2026'!K3,IF($B$31=2,'Ertragsv. 2026'!J3,IF($B$31=3,'Ertragsv. 2026'!J3*50%+'Ertragsv. 2026'!K3*50%)))) -> 0 | N34: =IF($B$31=0,'Ertragsv. 2026'!M3,IF($B$31=1,'Ertragsv. 2026'!L3,IF($B$31=2,'Ertragsv. 2026'!K3,IF($B$31=3,'Ertragsv. 2026'!K3*50%+'Ertragsv. 2026'!L3*50%)))) -> 0 | O34: =IF($B$31=0,'Ertragsv. 2026'!N3,IF($B$31=1,'Ertragsv. 2026'!M3,IF($B$31=2,'Ertragsv. 2026'!L3,IF($B$31=3,'Ertragsv. 2026'!L3*50%+'Ertragsv. 2026'!M3*50%)))) -> 0 | P34: =SUM(D34:O34) -> 0
B35: + Einzahlungen-Eigenkapital | P35: =SUM(D35:O35) -> 0
B36: + Kredite / Darlehen | P36: =SUM(D36:O36) -> 0
B37: + Gründungszuschuß | P37: =SUM(D37:O37) -> 0
B38: + MwSt | D38: =IF($P$2<0,0,IF($P$2>0,D34*19%,0)) -> 0 | E38: =IF($P$2<0,0,IF($P$2>0,E34*19%,0)) -> 0 | F38: =IF($P$2<0,0,IF($P$2>0,F34*19%,0)) -> 0 | G38: =IF($P$2<0,0,IF($P$2>0,G34*19%,0)) -> 0 | H38: =IF($P$2<0,0,IF($P$2>0,H34*19%,0)) -> 0 | I38: =IF($P$2<0,0,IF($P$2>0,I34*19%,0)) -> 0 | J38: =IF($P$2<0,0,IF($P$2>0,J34*19%,0)) -> 0 | K38: =IF($P$2<0,0,IF($P$2>0,K34*19%,0)) -> 0 | ... O38: =IF($P$2<0,0,IF($P$2>0,O34*19%,0)) -> 0 | P38: =SUM(D38:O38) -> 0
B39: = Summe Liquiditätszugang | D39: =SUM(D34:D38) -> 0 | E39: =SUM(E34:E38) -> 0 | F39: =SUM(F34:F38) -> 0 | G39: =SUM(G34:G38) -> 0 | H39: =SUM(H34:H38) -> 0 | I39: =SUM(I34:I38) -> 0 | J39: =SUM(J34:J38) -> 0 | K39: =SUM(K34:K38) -> 0 | ... O39: =SUM(O34:O38) -> 0 | P39: =SUM(D39:O39) -> 0
B40: AUSZAHLUNGEN
B41: + Anlageninvestition | P41: =SUM(D41:O41) -> 0
B42: + Vorsteuer | D42: =IF($P$2>0,(D43)*$P$2+(D41+D44)*19%-('Ertragsv. 2026'!C7+'Ertragsv. 2026'!C14+'Ertragsv. 2026'!C17+'Ertragsv. 2026'!C18)*19%,0) -> 0 | E42: =IF($P$2>0,(E43)*$P$2+(E41+E44)*19%-('Ertragsv. 2026'!D7+'Ertragsv. 2026'!D14+'Ertragsv. 2026'!D17+'Ertragsv. 2026'!D18)*19%,0) -> 0 | F42: =IF($P$2>0,(F43)*$P$2+(F41+F44)*19%-('Ertragsv. 2026'!E7+'Ertragsv. 2026'!E14+'Ertragsv. 2026'!E17+'Ertragsv. 2026'!E18)*19%,0) -> 0 | G42: =IF($P$2>0,(G43)*$P$2+(G41+G44)*19%-('Ertragsv. 2026'!F7+'Ertragsv. 2026'!F14+'Ertragsv. 2026'!F17+'Ertragsv. 2026'!F18)*19%,0) -> 0 | H42: =IF($P$2>0,(H43)*$P$2+(H41+H44)*19%-('Ertragsv. 2026'!G7+'Ertragsv. 2026'!G14+'Ertragsv. 2026'!G17+'Ertragsv. 2026'!G18)*19%,0) -> 0 | I42: =IF($P$2>0,(I43)*$P$2+(I41+I44)*19%-('Ertragsv. 2026'!H7+'Ertragsv. 2026'!H14+'Ertragsv. 2026'!H17+'Ertragsv. 2026'!H18)*19%,0) -> 0 | J42: =IF($P$2>0,(J43)*$P$2+(J41+J44)*19%-('Ertragsv. 2026'!I7+'Ertragsv. 2026'!I14+'Ertragsv. 2026'!I17+'Ertragsv. 2026'!I18)*19%,0) -> 0 | K42: =IF($P$2>0,(K43)*$P$2+(K41+K44)*19%-('Ertragsv. 2026'!J7+'Ertragsv. 2026'!J14+'Ertragsv. 2026'!J17+'Ertragsv. 2026'!J18)*19%,0) -> 0 | ... O42: =IF($P$2>0,(O43)*$P$2+(O41+O44)*19%-('Ertragsv. 2026'!N7+'Ertragsv. 2026'!N14+'Ertragsv. 2026'!N17+'Ertragsv. 2026'!N18)*19%,0) -> 0 | P42: =SUM(D42:O42) -> 0
B43: + Material/Wareneinkaurf | D43: ='Ertragsv. 2026'!C4 -> 0 | E43: ='Ertragsv. 2026'!D4 -> 0 | F43: ='Ertragsv. 2026'!E4 -> 0 | G43: ='Ertragsv. 2026'!F4 -> 0 | H43: ='Ertragsv. 2026'!G4 -> 0 | I43: ='Ertragsv. 2026'!H4 -> 0 | J43: ='Ertragsv. 2026'!I4 -> 0 | K43: ='Ertragsv. 2026'!J4 -> 0 | ... O43: ='Ertragsv. 2026'!N4 -> 0 | P43: =SUM(D43:O43) -> 0
B44: + Betriebsausgaben (PK+SK) | D44: ='Ertragsv. 2026'!C20-'Ertragsv. 2026'!C4 -> 0 | E44: ='Ertragsv. 2026'!D20-'Ertragsv. 2026'!D4 -> 0 | F44: ='Ertragsv. 2026'!E20-'Ertragsv. 2026'!E4 -> 0 | G44: ='Ertragsv. 2026'!F20-'Ertragsv. 2026'!F4 -> 0 | H44: ='Ertragsv. 2026'!G20-'Ertragsv. 2026'!G4 -> 0 | I44: ='Ertragsv. 2026'!H20-'Ertragsv. 2026'!H4 -> 0 | J44: ='Ertragsv. 2026'!I20-'Ertragsv. 2026'!I4 -> 0 | K44: ='Ertragsv. 2026'!J20-'Ertragsv. 2026'!J4 -> 0 | ... O44: ='Ertragsv. 2026'!N20-'Ertragsv. 2026'!N4 -> 0 | P44: =SUM(D44:O44) -> 0
B45: + Kredittilgung | D45: =Finanz_AfA_Investitionen!G38-Finanz_AfA_Investitionen!G37+'Mikrostarter Geschäftsplan'!C33 -> 0 | E45: =Finanz_AfA_Investitionen!G38-Finanz_AfA_Investitionen!G37+'Mikrostarter Geschäftsplan'!C34 -> 0 | F45: =Finanz_AfA_Investitionen!G38-Finanz_AfA_Investitionen!G37+'Mikrostarter Geschäftsplan'!C35 -> 0 | G45: =Finanz_AfA_Investitionen!G38-Finanz_AfA_Investitionen!G37+'Mikrostarter Geschäftsplan'!C36 -> 0 | H45: =Finanz_AfA_Investitionen!G38-Finanz_AfA_Investitionen!G37+'Mikrostarter Geschäftsplan'!C37 -> 0 | I45: =Finanz_AfA_Investitionen!G38-Finanz_AfA_Investitionen!G37+'Mikrostarter Geschäftsplan'!C38 -> 0 | J45: =Finanz_AfA_Investitionen!G38-Finanz_AfA_Investitionen!G37+'Mikrostarter Geschäftsplan'!C39 -> 0 | K45: =Finanz_AfA_Investitionen!G38-Finanz_AfA_Investitionen!G37+'Mikrostarter Geschäftsplan'!C40 -> 0 | L45: =Finanz_AfA_Investitionen!G38-Finanz_AfA_Investitionen!G37+'Mikrostarter Geschäftsplan'!C41 -> 0 | M45: =Finanz_AfA_Investitionen!G38-Finanz_AfA_Investitionen!G37+'Mikrostarter Geschäftsplan'!C42 -> 0 | N45: =Finanz_AfA_Investitionen!G38-Finanz_AfA_Investitionen!G37+'Mikrostarter Geschäftsplan'!C43 -> 0 | O45: =Finanz_AfA_Investitionen!G38-Finanz_AfA_Investitionen!G37+'Mikrostarter Geschäftsplan'!C44 -> 0 | P45: =SUM(D45:O45) -> 0
B46: + Sonst | P46: =SUM(D46:O46) -> 0
B47: + MwSt Zahllast | D47: =O9-O13 -> 0 | E47: =D38-D42 -> 0 | F47: =E38-E42 -> 0 | G47: =F38-F42 -> 0 | H47: =G38-G42 -> 0 | I47: =H38-H42 -> 0 | J47: =I38-I42 -> 0 | K47: =J38-J42 -> 0 | L47: =K38-K42 -> 0 | ... O47: =N38-N42 -> 0 | P47: =SUM(D47:O47) -> 0
B48: + Steuern | D48: ='Ertragsv. 2026'!C25 -> 0 | E48: ='Ertragsv. 2026'!D25 -> 0 | F48: ='Ertragsv. 2026'!E25 -> 0 | G48: ='Ertragsv. 2026'!F25 -> 0 | H48: ='Ertragsv. 2026'!G25 -> 0 | I48: ='Ertragsv. 2026'!H25 -> 0 | J48: ='Ertragsv. 2026'!I25 -> 0 | K48: ='Ertragsv. 2026'!J25 -> 0 | ... O48: ='Ertragsv. 2026'!N25 -> 0 | P48: =SUM(D48:O48) -> 0
B49: + UnternehmerInnen- Lohn | D49: ='Ertragsv. 2026'!C27 -> 0 | E49: ='Ertragsv. 2026'!D27 -> 0 | F49: ='Ertragsv. 2026'!E27 -> 0 | G49: ='Ertragsv. 2026'!F27 -> 0 | H49: ='Ertragsv. 2026'!G27 -> 0 | I49: ='Ertragsv. 2026'!H27 -> 0 | J49: ='Ertragsv. 2026'!I27 -> 0 | K49: ='Ertragsv. 2026'!J27 -> 0 | ... O49: ='Ertragsv. 2026'!N27 -> 0 | P49: =SUM(D49:O49) -> 0
B50: + sonstige Auszahlungen | P50: =SUM(D50:O50) -> 0
B51: = Summe Liquiditätsabgang | D51: =SUM(D40:D50) -> 0 | E51: =SUM(E40:E50) -> 0 | F51: =SUM(F40:F50) -> 0 | G51: =SUM(G40:G50) -> 0 | H51: =SUM(H40:H50) -> 0 | I51: =SUM(I40:I50) -> 0 | J51: =SUM(J40:J50) -> 0 | K51: =SUM(K40:K50) -> 0 | ... O51: =SUM(O40:O50) -> 0 | P51: =SUM(D51:O51) -> 0
B52: Liquiditätssaldo | D52: =D39-D51 -> 0 | E52: =E39-E51 -> 0 | F52: =F39-F51 -> 0 | G52: =G39-G51 -> 0 | H52: =H39-H51 -> 0 | I52: =I39-I51 -> 0 | J52: =J39-J51 -> 0 | K52: =K39-K51 -> 0 | ... O52: =O39-O51 -> 0 | P52: =SUM(D52:O52) -> 0
B53: Liquiditätssaldo (kumuliert) | D53: =D52+P24 -> 0 | E53: =D53+E52 -> 0 | F53: =E53+F52 -> 0 | G53: =F53+G52 -> 0 | H53: =G53+H52 -> 0 | I53: =H53+I52 -> 0 | J53: =I53+J52 -> 0 | K53: =J53+K52 -> 0 | L53: =K53+L52 -> 0 | ... O53: =N53+O52 -> 0 | P53: =O53 -> 0
B55: Kontokorrentlinie | D55: =O26 -> 0 | E55: =D55 -> 0 | F55: =E55 -> 0 | G55: =F55 -> 0 | H55: =G55 -> 0 | I55: =H55 -> 0 | J55: =I55 -> 0 | K55: =J55 -> 0 | L55: =K55 -> 0 | ... O55: =N55 -> 0
B57: Saldo | D57: =D53+D55 -> 0 | E57: =E53+E55 -> 0 | F57: =F53+F55 -> 0 | G57: =G53+G55 -> 0 | H57: =H53+H55 -> 0 | I57: =I53+I55 -> 0 | J57: =J53+J55 -> 0 | K57: =K53+K55 -> 0 | ... O57: =O53+O55 -> 0
B59: LIQUIDITÄTSPLANUNG Jahr 3
B60: 1 | C60: Bei Umsatzeingang bar "0" eintragen,bei Eingang nach 30 Tagen "1", bei Eingang nach 60 Tagen "2" eintragen,bei Eingang nach 45 Tagen "3" eintragen
B61: =ZusammenführErgebn!E3 -> 2027 | D61: =D32 -> Jan. | E61: =E32 -> Febr. | F61: =F32 -> März | G61: =G32 -> April | H61: =H32 -> Mai | I61: =I32 -> Juni | J61: =J32 -> Juli | K61: =K32 -> Aug. | ... O61: =O32 -> Dez. | P61: Summe
B62: EINZAHLUNGEN
B63: + Umsatz | D63: =IF($B$60=0,'Ertragsv. 2027'!C3,IF($B$60=1,'Ertragsv. 2026'!N3,IF($B$60=2,'Ertragsv. 2026'!M3,IF($B$60=3,'Ertragsv. 2026'!M3*50%+'Ertragsv. 2026'!N3*50%)))) -> 0 | E63: =IF($B$60=0,'Ertragsv. 2027'!D3,IF($B$60=1,'Ertragsv. 2027'!C3,IF($B$60=2,'Ertragsv. 2026'!N3,IF($B$60=3,'Ertragsv. 2026'!N3*50%+'Ertragsv. 2027'!C3*50%)))) -> 0 | F63: =IF($B$60=0,'Ertragsv. 2027'!E3,IF($B$60=1,'Ertragsv. 2027'!D3,IF($B$60=2,'Ertragsv. 2027'!C3,IF($B$60=3,'Ertragsv. 2027'!C3*50%+'Ertragsv. 2027'!D3*50%)))) -> 0 | G63: =IF($B$60=0,'Ertragsv. 2027'!F3,IF($B$60=1,'Ertragsv. 2027'!E3,IF($B$60=2,'Ertragsv. 2027'!D3,IF($B$60=3,'Ertragsv. 2027'!D3*50%+'Ertragsv. 2027'!E3*50%)))) -> 0 | H63: =IF($B$60=0,'Ertragsv. 2027'!G3,IF($B$60=1,'Ertragsv. 2027'!F3,IF($B$60=2,'Ertragsv. 2027'!E3,IF($B$60=3,'Ertragsv. 2027'!E3*50%+'Ertragsv. 2027'!F3*50%)))) -> 0 | I63: =IF($B$60=0,'Ertragsv. 2027'!H3,IF($B$60=1,'Ertragsv. 2027'!G3,IF($B$60=2,'Ertragsv. 2027'!F3,IF($B$60=3,'Ertragsv. 2027'!F3*50%+'Ertragsv. 2027'!G3*50%)))) -> 0 | J63: =IF($B$60=0,'Ertragsv. 2027'!I3,IF($B$60=1,'Ertragsv. 2027'!H3,IF($B$60=2,'Ertragsv. 2027'!G3,IF($B$60=3,'Ertragsv. 2027'!G3*50%+'Ertragsv. 2027'!H3*50%)))) -> 0 | K63: =IF($B$60=0,'Ertragsv. 2027'!J3,IF($B$60=1,'Ertragsv. 2027'!I3,IF($B$60=2,'Ertragsv. 2027'!H3,IF($B$60=3,'Ertragsv. 2027'!H3*50%+'Ertragsv. 2027'!I3*50%)))) -> 0 | L63: =IF($B$60=0,'Ertragsv. 2027'!K3,IF($B$60=1,'Ertragsv. 2027'!J3,IF($B$60=2,'Ertragsv. 2027'!I3,IF($B$60=3,'Ertragsv. 2027'!I3*50%+'Ertragsv. 2027'!J3*50%)))) -> 0 | M63: =IF($B$60=0,'Ertragsv. 2027'!L3,IF($B$60=1,'Ertragsv. 2027'!K3,IF($B$60=2,'Ertragsv. 2027'!J3,IF($B$60=3,'Ertragsv. 2027'!J3*50%+'Ertragsv. 2027'!K3*50%)))) -> 0 | ... O63: =IF($B$60=0,'Ertragsv. 2027'!N3,IF($B$60=1,'Ertragsv. 2027'!M3,IF($B$60=2,'Ertragsv. 2027'!L3,IF($B$60=3,'Ertragsv. 2027'!L3*50%+'Ertragsv. 2027'!M3*50%)))) -> 0 | P63: =SUM(D63:O63) -> 0
B64: + Einzahlungen-Eigenkapital | P64: =SUM(D64:O64) -> 0
B65: + Kredite / Darlehen | P65: =SUM(D65:O65) -> 0
B66: + Gründungszuschuß | P66: =SUM(D66:O66) -> 0
B67: + MwSt | D67: =IF($P$2<0,0,IF($P$2>0,D63*19%,0)) -> 0 | E67: =IF($P$2<0,0,IF($P$2>0,E63*19%,0)) -> 0 | F67: =IF($P$2<0,0,IF($P$2>0,F63*19%,0)) -> 0 | G67: =IF($P$2<0,0,IF($P$2>0,G63*19%,0)) -> 0 | H67: =IF($P$2<0,0,IF($P$2>0,H63*19%,0)) -> 0 | I67: =IF($P$2<0,0,IF($P$2>0,I63*19%,0)) -> 0 | J67: =IF($P$2<0,0,IF($P$2>0,J63*19%,0)) -> 0 | K67: =IF($P$2<0,0,IF($P$2>0,K63*19%,0)) -> 0 | ... O67: =IF($P$2<0,0,IF($P$2>0,O63*19%,0)) -> 0 | P67: =SUM(D67:O67) -> 0
B68: = Summe Liquiditätszugang | D68: =SUM(D63:D67) -> 0 | E68: =SUM(E63:E67) -> 0 | F68: =SUM(F63:F67) -> 0 | G68: =SUM(G63:G67) -> 0 | H68: =SUM(H63:H67) -> 0 | I68: =SUM(I63:I67) -> 0 | J68: =SUM(J63:J67) -> 0 | K68: =SUM(K63:K67) -> 0 | ... O68: =SUM(O63:O67) -> 0 | P68: =SUM(D68:O68) -> 0
B69: AUSZAHLUNGEN
B70: + Anlageninvestition | P70: =SUM(D70:O70) -> 0
B71: + Vorsteuer | D71: =IF($P$2>0,(D72)*$P$2+(D70+D73)*19%-('Ertragsv. 2027'!C7+'Ertragsv. 2027'!C14+'Ertragsv. 2027'!C17+'Ertragsv. 2027'!C18)*19%,0) -> 0 | E71: =IF($P$2>0,(E72)*$P$2+(E70+E73)*19%-('Ertragsv. 2027'!D7+'Ertragsv. 2027'!D14+'Ertragsv. 2027'!D17+'Ertragsv. 2027'!D18)*19%,0) -> 0 | F71: =IF($P$2>0,(F72)*$P$2+(F70+F73)*19%-('Ertragsv. 2027'!E7+'Ertragsv. 2027'!E14+'Ertragsv. 2027'!E17+'Ertragsv. 2027'!E18)*19%,0) -> 0 | G71: =IF($P$2>0,(G72)*$P$2+(G70+G73)*19%-('Ertragsv. 2027'!F7+'Ertragsv. 2027'!F14+'Ertragsv. 2027'!F17+'Ertragsv. 2027'!F18)*19%,0) -> 0 | H71: =IF($P$2>0,(H72)*$P$2+(H70+H73)*19%-('Ertragsv. 2027'!G7+'Ertragsv. 2027'!G14+'Ertragsv. 2027'!G17+'Ertragsv. 2027'!G18)*19%,0) -> 0 | I71: =IF($P$2>0,(I72)*$P$2+(I70+I73)*19%-('Ertragsv. 2027'!H7+'Ertragsv. 2027'!H14+'Ertragsv. 2027'!H17+'Ertragsv. 2027'!H18)*19%,0) -> 0 | J71: =IF($P$2>0,(J72)*$P$2+(J70+J73)*19%-('Ertragsv. 2027'!I7+'Ertragsv. 2027'!I14+'Ertragsv. 2027'!I17+'Ertragsv. 2027'!I18)*19%,0) -> 0 | K71: =IF($P$2>0,(K72)*$P$2+(K70+K73)*19%-('Ertragsv. 2027'!J7+'Ertragsv. 2027'!J14+'Ertragsv. 2027'!J17+'Ertragsv. 2027'!J18)*19%,0) -> 0 | ... O71: =IF($P$2>0,(O72)*$P$2+(O70+O73)*19%-('Ertragsv. 2027'!N7+'Ertragsv. 2027'!N14+'Ertragsv. 2027'!N17+'Ertragsv. 2027'!N18)*19%,0) -> 0 | P71: =SUM(D71:O71) -> 0
B72: + Material/Wareneinkaurf | D72: ='Ertragsv. 2027'!C4 -> 0 | E72: ='Ertragsv. 2027'!D4 -> 0 | F72: ='Ertragsv. 2027'!E4 -> 0 | G72: ='Ertragsv. 2027'!F4 -> 0 | H72: ='Ertragsv. 2027'!G4 -> 0 | I72: ='Ertragsv. 2027'!H4 -> 0 | J72: ='Ertragsv. 2027'!I4 -> 0 | K72: ='Ertragsv. 2027'!J4 -> 0 | ... O72: ='Ertragsv. 2027'!N4 -> 0 | P72: =SUM(D72:O72) -> 0
B73: + Betriebsausgaben (PK+SK) | D73: ='Ertragsv. 2027'!C20-'Ertragsv. 2027'!C4 -> 0 | E73: ='Ertragsv. 2027'!D20-'Ertragsv. 2027'!D4 -> 0 | F73: ='Ertragsv. 2027'!E20-'Ertragsv. 2027'!E4 -> 0 | G73: ='Ertragsv. 2027'!F20-'Ertragsv. 2027'!F4 -> 0 | H73: ='Ertragsv. 2027'!G20-'Ertragsv. 2027'!G4 -> 0 | I73: ='Ertragsv. 2027'!H20-'Ertragsv. 2027'!H4 -> 0 | J73: ='Ertragsv. 2027'!I20-'Ertragsv. 2027'!I4 -> 0 | K73: ='Ertragsv. 2027'!J20-'Ertragsv. 2027'!J4 -> 0 | ... O73: ='Ertragsv. 2027'!N20-'Ertragsv. 2027'!N4 -> 0 | P73: =SUM(D73:O73) -> 0
B74: + Kredittilgung | D74: =Finanz_AfA_Investitionen!G38-Finanz_AfA_Investitionen!G37+'Mikrostarter Geschäftsplan'!C46 -> 0 | E74: =Finanz_AfA_Investitionen!G38-Finanz_AfA_Investitionen!G37+'Mikrostarter Geschäftsplan'!C47 -> 0 | F74: =Finanz_AfA_Investitionen!G38-Finanz_AfA_Investitionen!G37+'Mikrostarter Geschäftsplan'!C48 -> 0 | G74: =Finanz_AfA_Investitionen!G38-Finanz_AfA_Investitionen!G37+'Mikrostarter Geschäftsplan'!C49 -> 0 | H74: =Finanz_AfA_Investitionen!G38-Finanz_AfA_Investitionen!G37+'Mikrostarter Geschäftsplan'!C50 -> 0 | I74: =Finanz_AfA_Investitionen!G38-Finanz_AfA_Investitionen!G37+'Mikrostarter Geschäftsplan'!C51 -> 0 | J74: =Finanz_AfA_Investitionen!G38-Finanz_AfA_Investitionen!G37+'Mikrostarter Geschäftsplan'!C52 -> 0 | K74: =Finanz_AfA_Investitionen!G38-Finanz_AfA_Investitionen!G37+'Mikrostarter Geschäftsplan'!C53 -> 0 | L74: =Finanz_AfA_Investitionen!G38-Finanz_AfA_Investitionen!G37+'Mikrostarter Geschäftsplan'!C54 -> 0 | M74: =Finanz_AfA_Investitionen!G38-Finanz_AfA_Investitionen!G37+'Mikrostarter Geschäftsplan'!C55 -> 0 | N74: =Finanz_AfA_Investitionen!G38-Finanz_AfA_Investitionen!G37+'Mikrostarter Geschäftsplan'!C56 -> 0 | O74: =Finanz_AfA_Investitionen!G38-Finanz_AfA_Investitionen!G37+'Mikrostarter Geschäftsplan'!C57 -> 0 | P74: =SUM(D74:O74) -> 0
B75: +Sonst. | D75: =Finanz_AfA_Investitionen!C24+Finanz_AfA_Investitionen!C25 -> 0 | P75: =SUM(D75:O75) -> 0
B76: + MwSt Zahllast | D76: =O38-O42 -> 0 | E76: =D67-D71 -> 0 | F76: =E67-E71 -> 0 | G76: =F67-F71 -> 0 | H76: =G67-G71 -> 0 | I76: =H67-H71 -> 0 | J76: =I67-I71 -> 0 | K76: =J67-J71 -> 0 | L76: =K67-K71 -> 0 | ... O76: =N67-N71 -> 0 | P76: =SUM(D76:O76) -> 0
B77: + Steuern | D77: ='Ertragsv. 2027'!C25 -> 0 | E77: ='Ertragsv. 2027'!D25 -> 0 | F77: ='Ertragsv. 2027'!E25 -> 0 | G77: ='Ertragsv. 2027'!F25 -> 0 | H77: ='Ertragsv. 2027'!G25 -> 0 | I77: ='Ertragsv. 2027'!H25 -> 0 | J77: ='Ertragsv. 2027'!I25 -> 0 | K77: ='Ertragsv. 2027'!J25 -> 0 | ... O77: ='Ertragsv. 2027'!N25 -> 0 | P77: =SUM(D77:O77) -> 0
B78: + UnternehmerInnen- Lohn | D78: ='Ertragsv. 2027'!C27 -> 0 | E78: ='Ertragsv. 2027'!D27 -> 0 | F78: ='Ertragsv. 2027'!E27 -> 0 | G78: ='Ertragsv. 2027'!F27 -> 0 | H78: ='Ertragsv. 2027'!G27 -> 0 | I78: ='Ertragsv. 2027'!H27 -> 0 | J78: ='Ertragsv. 2027'!I27 -> 0 | K78: ='Ertragsv. 2027'!J27 -> 0 | ... O78: ='Ertragsv. 2027'!N27 -> 0 | P78: =SUM(D78:O78) -> 0
B79: + sonstige Auszahlungen | P79: =SUM(D79:O79) -> 0
B80: = Summe Liquiditätsabgang | D80: =SUM(D70:D79) -> 0 | E80: =SUM(E70:E79) -> 0 | F80: =SUM(F70:F79) -> 0 | G80: =SUM(G70:G79) -> 0 | H80: =SUM(H70:H79) -> 0 | I80: =SUM(I70:I79) -> 0 | J80: =SUM(J70:J79) -> 0 | K80: =SUM(K70:K79) -> 0 | ... P80: =SUM(P70:P79) -> 0
B81: Liquiditätssaldo | D81: =D68-D80 -> 0 | E81: =E68-E80 -> 0 | F81: =F68-F80 -> 0 | G81: =G68-G80 -> 0 | H81: =H68-H80 -> 0 | I81: =I68-I80 -> 0 | J81: =J68-J80 -> 0 | K81: =K68-K80 -> 0 | ... O81: =O68-O80 -> 0 | P81: =SUM(D81:O81) -> 0
B82: Liquiditätssaldo (kumuliert) | D82: =D81+P53 -> 0 | E82: =D82+E81 -> 0 | F82: =E82+F81 -> 0 | G82: =F82+G81 -> 0 | H82: =G82+H81 -> 0 | I82: =H82+I81 -> 0 | J82: =I82+J81 -> 0 | K82: =J82+K81 -> 0 | L82: =K82+L81 -> 0 | ... O82: =N82+O81 -> 0 | P82: =O82 -> 0
B84: Kontokorrentlinie | D84: =O55 -> 0 | E84: =D84 -> 0 | F84: =E84 -> 0 | G84: =F84 -> 0 | H84: =G84 -> 0 | I84: =H84 -> 0 | J84: =I84 -> 0 | K84: =J84 -> 0 | L84: =K84 -> 0 | ... O84: =N84 -> 0
B86: Saldo | D86: =D82+D84 -> 0 | E86: =E82+E84 -> 0 | F86: =F82+F84 -> 0 | G86: =G82+G84 -> 0 | H86: =H82+H84 -> 0 | I86: =I82+I84 -> 0 | J86: =J82+J84 -> 0 | K86: =K82+K84 -> 0 | ... O86: =O82+O84 -> 0

Sheet Finanz_AfA_Investitionen
B1: FINANZEN / LEASING / ABSCHREIBUNGEN | F1: =Deckblatt!C7 -> 2025
B2: INVESTITIONEN | C2: Investitionsbetrag | D2: Abschrei-bungsjahre | E2: AfA Satz in % | F2: AfA Betrag pro Monat | G2: Investion-Leasing betrag | H2: Leasing Rate p.M. | I2: Leasingsatz p.M. in % | J2: Kommentare / Erläuterungen
B3: Unternehmenskauf | D3: 15 | E3: =IF(D3>0,100/D3,0) -> 6.6666667 | F3: =IF(AND(C3>0,D3>0),C3/D3/12,0) -> 0 | G3: 0 | H3: =G3*I3 -> 0
B4: Grundstücke | D4: 0
B5: Gebäude | D5: 33 | E5: =IF(D5>0,100/D5,0) -> 3.030303 | F5: =IF(AND(C5>0,D5>0),C5/D5/12,0) -> 0 | G5: 0 | H5: =G5*I5 -> 0
B6: Maschinen/ Anlagen/ Geräte | D6: 8 | E6: =IF(D6>0,100/D6,0) -> 12.5 | F6: =IF(AND(C6>0,D6>0),C6/D6/12,0) -> 0 | G6: 0 | H6: =G6*I6 -> 0 | I6: 0.015 | J6: als Beispiel aufgelistet
B7: Betriebsausst/Werkstatteinr. | D7: 8 | E7: =IF(D7>0,100/D7,0) -> 12.5 | F7: =IF(AND(C7>0,D7>0),C7/D7/12,0) -> 0 | H7: =G7*I7 -> 0 | J7: als Beispiel aufgelistet
B8: Fahrzeuge (PKW etc.) | D8: 6 | E8: =IF(D8>0,100/D8,0) -> 16.666667 | F8: =IF(AND(C8>0,D8>0),C8/D8/12,0) -> 0 | G8: 0 | H8: =G8*I8 -> 0 | I8: 0.013
B9: Fahrzeuge (LKW etc.) | D9: 9 | E9: =IF(D9>0,100/D9,0) -> 11.111111 | F9: =IF(AND(C9>0,D9>0),C9/D9/12,0) -> 0 | H9: =G9*I9 -> 0
B10: Büroausst. / Möbel/Theken | D10: 8 | E10: =IF(D10>0,100/D10,0) -> 12.5 | F10: =IF(AND(C10>0,D10>0),C10/D10/12,0) -> 0 | G10: 0 | H10: =G10*I10 -> 0 | J10: als Beispiel aufgelistet
B11: Büromaschinen | D11: 8 | E11: =IF(D11>0,100/D11,0) -> 12.5 | F11: =IF(AND(C11>0,D11>0),C11/D11/12,0) -> 0 | G11: 0 | H11: =G11*I11 -> 0 | J11: als Beispiel aufgelistet
B12: DV/Laptop / PC/ | D12: 3 | E12: =IF(D12>0,100/D12,0) -> 33.333333 | F12: =IF(AND(C12>0,D12>0),C12/D12/12,0) -> 0 | G12: 0 | H12: =G12*I12 -> 0
B13: GWG 2018 | D13: 1 | E13: =IF(D13>0,100/D13,0) -> 100 | F13: =IF(AND(C13>0,D13>0),C13/D13/12,0) -> 0 | G13: 0 | H13: =G13*I13 -> 0 | J13: < 410€; ab 1.1.2018 €800,00
B14: GWG Pool 2018 | D14: 5 | E14: =IF(D14>0,100/D14,0) -> 20 | F14: =IF(AND(C14>0,D14>0),C14/D14/12,0) -> 0 | G14: 0 | H14: =G14*I14 -> 0 | J14: > 250€ < 1000€
B15: ImmaterielleVG/Lizenzen | E15: =IF(D15>0,100/D15,0) -> 0 | F15: =IF(AND(C15>0,D15>0),C15/D15/12,0) -> 0 | G15: 0 | H15: =G15*I15 -> 0 | I15: 0.01
B16: Sonstiges | E16: =IF(D16>0,100/D16,0) -> 0 | F16: =IF(AND(C16>0,D16>0),C16/D16/12,0) -> 0 | G16: 0 | H16: =G16*I16 -> 0
B17: Gründungskosten
B18: Beratungen
B19: Notar/Handelsregister/ HWK | C19: 0
B20: Markteinführung
B21: Mietsicherheit / Provision | C21: 0
B22: Sonstiges | C22: 0
B23: Betriebsmittel
B24: Roh-Hilfs-Betriebsstoffe
B25: Material-Warenlager
B26: unfertige Erzeugn./Leistungen | C26: 0
B27: Sonstige | C27: 0
B28: Gesamt | C28: =SUM(C3:C27) -> 0 | F28: =SUM(F3:F16) -> 0 | G28: =SUM(G3:G16) -> 0 | H28: =SUM(H3:H16) -> 0
B29: FINANZIERUNG | C29: FINANZMITTEL | D29: LAUFZEIT IN JAHREN | E29: ZINSATZ IN % | F29: ZINSAUFWAND 1. PJ p.M. | G29: TILGUNG | H29: ZINSAUFWAND 2. PJ p.M. | I29: ZINSAUFWAND 3. PJ p.M.
B30: Kapitalherkunft
B31: Eigenkapital (bar)
B32: Eigenleistung (unbar)
B33: Sachleistung/Sacheinlage (unbar)
B34: KK Hausbank | C34: 0 | D34: unbefristet | E34: 0.11 | F34: =C34*E34/12 -> 0
B35: Darlehen Hausbank | D35: 6 | E35: 0.05 | F35: =C35*$E$35/12 -> 0 | G35: =IF(C35>0,C35/D35/12,0) -> 0 | H35: =(C35-(G35*12))*$E$35/12 -> 0 | I35: =(C35-(G35*24))*$E$35/12 -> 0
B36: Darlehen Familie | D36: 15 | E36: 0.03 | F36: =C36*E36/12 -> 0 | G36: =IF(C36>0,C36/D36/12,0) -> 0 | H36: =(C36-(G36*12))*$E$36/12 -> 0 | I36: =(C36-(G36*24))*$E$36/12 -> 0
B37: MicroSTARTer | C37: ='Mikrostarter Geschäftsplan'!E8 -> 0 | D37: ='Mikrostarter Geschäftsplan'!E9 -> 5 | E37: ='Mikrostarter Geschäftsplan'!E10 -> 0.035 | F37: ='Mikrostarter Geschäftsplan'!D32/12 -> 0 | G37: =C37/(12*D37) -> 0 | H37: ='Mikrostarter Geschäftsplan'!D45/12 -> 0 | I37: =+'Mikrostarter Geschäftsplan'!D50 -> 0 | J37: Ø monatl. Zins bzw. Ø monatl Tilgung
B38: Gesamt | C38: =SUM(C31:C37) -> 0 | F38: =SUM(F34:F37) -> 0 | G38: =SUM(G35:G37) -> 0 | H38: =SUM(H34:H37) -> 0 | I38: =SUM(I34:I37) -> 0
C54: =IF(H18=0,C18,0) -> 0

Sheet Mikrostarter Geschäftsplan
B1: ZINS- UND TILGUNGSRECHNER (STAND 01.07.2015)
A3: Geschäftsplan Antrag | B3: MikroSTARTer Niedersachsen
B5: Bitte beachten Sie: Diese Kalkulation stellt kein verbindliches Angebot der NBank dar. Es handelt sich lediglich um eine Beispielrechnung.
C8: Kreditsumme | E8: 0
C9: Laufzeit in Jahren | E9: 5
C10: Zinssatz (nominal) | E10: 0.035 | F10: p.a.
C11: Tilgung
C12: 1.-6. Monat | E12: 0
C13: 7-18. Monat | E13: 0.01 | F13: p.M. des zugesagten Darl.
C14: ab 19. Monat (gerundet) | E14: =88/(E9*12-18)/100 -> 0.020952381 | F14: p.M. verteilt auf Restlaufzeit | J14: 2
B15: Monat | C15: Tilgung | D15: Zinsen | E15: Rate | F15: Restschuld | J15: 3
B16: 1 | C16: =ROUND($E$8,1)*$E$12 -> 0 | D16: =E8*E10/12 -> 0 | E16: =ROUND(C16,2)+ROUND(D16,2) -> 0 | F16: =E8-C16 -> 0 | J16: 4
B17: 2 | C17: =ROUND($E$8,1)*$E$12 -> 0 | D17: =ROUND(F16,2)*$E$10/12 -> 0 | E17: =ROUND(C17,2)+ROUND(D17,2) -> 0 | F17: =ROUND(F16,2)-C17 -> 0 | J17: 5
B18: 3 | C18: =ROUND($E$8,1)*$E$12 -> 0 | D18: =ROUND(F17,2)*$E$10/12 -> 0 | E18: =ROUND(C18,2)+ROUND(D18,2) -> 0 | F18: =ROUND(F17,2)-C18 -> 0
B19: 1.Quartal | C19: =SUM(C16:C18) -> 0 | D19: =SUM(D16:D18) -> 0 | E19: =SUM(E16:E18) -> 0
B20: 4 | C20: =ROUND($E$8,1)*$E$12 -> 0 | D20: =ROUND(F18,2)*$E$10/12 -> 0 | E20: =ROUND(C20,2)+ROUND(D20,2) -> 0 | F20: =ROUND(F18,2)-C20 -> 0
B21: 5 | C21: =ROUND($E$8,1)*$E$12 -> 0 | D21: =ROUND(F20,2)*$E$10/12 -> 0 | E21: =ROUND(C21,2)+ROUND(D21,2) -> 0 | F21: =ROUND(F20,2)-C21 -> 0
B22: 6 | C22: =ROUND($E$8,1)*$E$12 -> 0 | D22: =ROUND(F21,2)*$E$10/12 -> 0 | E22: =ROUND(C22,2)+ROUND(D22,2) -> 0 | F22: =ROUND(F21,2)-C22 -> 0
B23: 2.Quartal | C23: =SUM(C20:C22) -> 0 | D23: =SUM(D20:D22) -> 0 | E23: =SUM(E20:E22) -> 0
B24: 7 | C24: =ROUND($E$8,1)*$E$13 -> 0 | D24: =ROUND(F22,2)*$E$10/12 -> 0 | E24: =ROUND(C24,2)+ROUND(D24,2) -> 0 | F24: =ROUND(F22,2)-C24 -> 0
B25: 8 | C25: =ROUND($E$8,1)*$E$13 -> 0 | D25: =ROUND(F24,2)*$E$10/12 -> 0 | E25: =ROUND(C25,2)+ROUND(D25,2) -> 0 | F25: =ROUND(F24,2)-C25 -> 0
B26: 9 | C26: =ROUND($E$8,1)*$E$13 -> 0 | D26: =ROUND(F25,2)*$E$10/12 -> 0 | E26: =ROUND(C26,2)+ROUND(D26,2) -> 0 | F26: =ROUND(F25,2)-C26 -> 0
B27: 3.Quartal | C27: =SUM(C24:C26) -> 0 | D27: =SUM(D24:D26) -> 0 | E27: =SUM(E24:E26) -> 0
B28: 10 | C28: =ROUND($E$8,1)*$E$13 -> 0 | D28: =ROUND(F26,2)*$E$10/12 -> 0 | E28: =ROUND(C28,2)+ROUND(D28,2) -> 0 | F28: =ROUND(F26,2)-C28 -> 0
B29: 11 | C29: =ROUND($E$8,1)*$E$13 -> 0 | D29: =ROUND(F28,2)*$E$10/12 -> 0 | E29: =ROUND(C29,2)+ROUND(D29,2) -> 0 | F29: =ROUND(F28,2)-C29 -> 0
B30: 12 | C30: =ROUND($E$8,1)*$E$13 -> 0 | D30: =ROUND(F29,2)*$E$10/12 -> 0 | E30: =ROUND(C30,2)+ROUND(D30,2) -> 0 | F30: =ROUND(F29,2)-C30 -> 0
B31: 4.Quartal | C31: =SUM(C28:C30) -> 0 | D31: =SUM(D28:D30) -> 0 | E31: =ROUND(C31,2)+ROUND(D31,2) -> 0
B32: 1.Planjahr | C32: =C19+C23+C27+C31 -> 0 | D32: =D19+D23+D27+D31 -> 0 | E32: =E19+E23+E27+E31 -> 0
B33: 13 | C33: =ROUND($E$8,1)*$E$13 -> 0 | D33: =ROUND(F30,2)*$E$10/12 -> 0 | E33: =ROUND(C33,2)+ROUND(D33,2) -> 0 | F33: =ROUND(F30,2)-C33 -> 0
B34: 14 | C34: =ROUND($E$8,1)*$E$13 -> 0 | D34: =ROUND(F33,2)*$E$10/12 -> 0 | E34: =ROUND(C34,2)+ROUND(D34,2) -> 0 | F34: =ROUND(F33,2)-C34 -> 0
B35: 15 | C35: =ROUND($E$8,1)*$E$13 -> 0 | D35: =ROUND(F34,2)*$E$10/12 -> 0 | E35: =ROUND(C35,2)+ROUND(D35,2) -> 0 | F35: =ROUND(F34,2)-C35 -> 0
B36: 16 | C36: =ROUND($E$8,1)*$E$13 -> 0 | D36: =ROUND(F35,2)*$E$10/12 -> 0 | E36: =ROUND(C36,2)+ROUND(D36,2) -> 0 | F36: =ROUND(F35,2)-C36 -> 0
B37: 17 | C37: =ROUND($E$8,1)*$E$13 -> 0 | D37: =ROUND(F36,2)*$E$10/12 -> 0 | E37: =ROUND(C37,2)+ROUND(D37,2) -> 0 | F37: =ROUND(F36,2)-C37 -> 0
B38: 18 | C38: =ROUND($E$8,1)*$E$13 -> 0 | D38: =ROUND(F37,2)*$E$10/12 -> 0 | E38: =ROUND(C38,2)+ROUND(D38,2) -> 0 | F38: =ROUND(F37,2)-C38 -> 0
B39: 19 | C39: =$E$8*ROUNDUP($E$14,4) -> 0 | D39: =ROUND(F38,2)*$E$10/12 -> 0 | E39: =ROUND(C39,2)+ROUND(D39,2) -> 0 | F39: =ROUND(F38,2)-C39 -> 0
B40: 20 | C40: =$E$8*ROUNDUP($E$14,4) -> 0 | D40: =ROUND(F39,2)*$E$10/12 -> 0 | E40: =ROUND(C40,2)+ROUND(D40,2) -> 0 | F40: =ROUND(F39,2)-C40 -> 0
B41: 21 | C41: =$E$8*ROUNDUP($E$14,4) -> 0 | D41: =ROUND(F40,2)*$E$10/12 -> 0 | E41: =ROUND(C41,2)+ROUND(D41,2) -> 0 | F41: =ROUND(F40,2)-C41 -> 0
B42: 22 | C42: =$E$8*ROUNDUP($E$14,4) -> 0 | D42: =ROUND(F41,2)*$E$10/12 -> 0 | E42: =ROUND(C42,2)+ROUND(D42,2) -> 0 | F42: =ROUND(F41,2)-C42 -> 0
B43: 23 | C43: =$E$8*ROUNDUP($E$14,4) -> 0 | D43: =ROUND(F42,2)*$E$10/12 -> 0 | E43: =ROUND(C43,2)+ROUND(D43,2) -> 0 | F43: =ROUND(F42,2)-C43 -> 0
B44: 24 | C44: =IF(F43>0.01,IF(F43>C43,$E$8*ROUNDUP($E$14,4),F43),0) -> 0 | D44: =ROUND(F43,2)*$E$10/12 -> 0 | E44: =ROUND(C44,2)+ROUND(D44,2) -> 0 | F44: =ROUND(F43,2)-C44 -> 0
B45: 2.Planjahr | C45: =SUM(C33:C44) -> 0 | D45: =SUM(D33:D44) -> 0 | E45: =SUM(E33:E44) -> 0
B46: =IF($E$9>2,25,0) -> 25 | C46: =IF(F44>0.01,$E$8*ROUNDUP($E$14,4),0) -> 0 | D46: =IF(F44>0.01,ROUND(F44,2)*$E$10/12,0) -> 0 | E46: =IF(F44>0.01,ROUND(C46,2)+ROUND(D46,2),0) -> 0 | F46: =IF(F44>0.01,ROUND(F44,2)-C46,0) -> 0
B47: =IF($E$9>2,26,0) -> 26 | C47: =IF(F46>0.01,$E$8*ROUNDUP($E$14,4),0) -> 0 | D47: =IF(F46>0.01,ROUND(F46,2)*$E$10/12,0) -> 0 | E47: =IF(F46>0.01,ROUND(C47,2)+ROUND(D47,2),0) -> 0 | F47: =IF(F46>0.01,ROUND(F46,2)-C47,0) -> 0
B48: =IF($E$9>2,27,0) -> 27 | C48: =IF(F47>0.01,$E$8*ROUNDUP($E$14,4),0) -> 0 | D48: =IF(F47>0.01,ROUND(F47,2)*$E$10/12,0) -> 0 | E48: =IF(F47>0.01,ROUND(C48,2)+ROUND(D48,2),0) -> 0 | F48: =IF(F47>0.01,ROUND(F47,2)-C48,0) -> 0
B49: =IF($E$9>2,28,0) -> 28 | C49: =IF(F48>0.01,$E$8*ROUNDUP($E$14,4),0) -> 0 | D49: =IF(F48>0.01,ROUND(F48,2)*$E$10/12,0) -> 0 | E49: =IF(F48>0.01,ROUND(C49,2)+ROUND(D49,2),0) -> 0 | F49: =IF(F48>0.01,ROUND(F48,2)-C49,0) -> 0
B50: =IF($E$9>2,29,0) -> 29 | C50: =IF(F49>0.01,$E$8*ROUNDUP($E$14,4),0) -> 0 | D50: =IF(F49>0.01,ROUND(F49,2)*$E$10/12,0) -> 0 | E50: =IF(F49>0.01,ROUND(C50,2)+ROUND(D50,2),0) -> 0 | F50: =IF(F49>0.01,ROUND(F49,2)-C50,0) -> 0
B51: =IF($E$9>2,30,0) -> 30 | C51: =IF(F50>0.01,$E$8*ROUNDUP($E$14,4),0) -> 0 | D51: =IF(F50>0.01,ROUND(F50,2)*$E$10/12,0) -> 0 | E51: =IF(F50>0.01,ROUND(C51,2)+ROUND(D51,2),0) -> 0 | F51: =IF(F50>0.01,ROUND(F50,2)-C51,0) -> 0
B52: =IF($E$9>2,31,0) -> 31 | C52: =IF(F51>0.01,$E$8*ROUNDUP($E$14,4),0) -> 0 | D52: =IF(F51>0.01,ROUND(F51,2)*$E$10/12,0) -> 0 | E52: =IF(F51>0.01,ROUND(C52,2)+ROUND(D52,2),0) -> 0 | F52: =IF(F51>0.01,ROUND(F51,2)-C52,0) -> 0
B53: =IF($E$9>2,32,0) -> 32 | C53: =IF(F52>0.01,$E$8*ROUNDUP($E$14,4),0) -> 0 | D53: =IF(F52>0.01,ROUND(F52,2)*$E$10/12,0) -> 0 | E53: =IF(F52>0.01,ROUND(C53,2)+ROUND(D53,2),0) -> 0 | F53: =IF(F52>0.01,ROUND(F52,2)-C53,0) -> 0
B54: =IF($E$9>2,33,0) -> 33 | C54: =IF(F53>0.01,$E$8*ROUNDUP($E$14,4),0) -> 0 | D54: =IF(F53>0.01,ROUND(F53,2)*$E$10/12,0) -> 0 | E54: =IF(F53>0.01,ROUND(C54,2)+ROUND(D54,2),0) -> 0 | F54: =IF(F53>0.01,ROUND(F53,2)-C54,0) -> 0
B55: =IF($E$9>2,34,0) -> 34 | C55: =IF(F54>0.01,$E$8*ROUNDUP($E$14,4),0) -> 0 | D55: =IF(F54>0.01,ROUND(F54,2)*$E$10/12,0) -> 0 | E55: =IF(F54>0.01,ROUND(C55,2)+ROUND(D55,2),0) -> 0 | F55: =IF(F54>0.01,ROUND(F54,2)-C55,0) -> 0
B56: =IF($E$9>2,35,0) -> 35 | C56: =IF(F55>0.01,$E$8*ROUNDUP($E$14,4),0) -> 0 | D56: =IF(F55>0.01,ROUND(F55,2)*$E$10/12,0) -> 0 | E56: =IF(F55>0.01,ROUND(C56,2)+ROUND(D56,2),0) -> 0 | F56: =IF(F55>0.01,ROUND(F55,2)-C56,0) -> 0
B57: =IF($E$9>2,36,0) -> 36 | C57: =IF(F56>0.01,IF(F56>C56,$E$8*ROUNDUP($E$14,4),F56),0) -> 0 | D57: =IF(F56>0.01,ROUND(F56,2)*$E$10/12,0) -> 0 | E57: =IF(F56>0.01,ROUND(C57,2)+ROUND(D57,2),0) -> 0 | F57: =IF(F56>0.01,ROUND(F56,2)-C57,0) -> 0
B58: 3.Planjahr | C58: =SUM(C46:C57) -> 0 | D58: =SUM(D46:D57) -> 0 | E58: =SUM(E46:E57) -> 0
B59: =IF($E$9>3,37,0) -> 37 | C59: =IF(F57>0.01,$E$8*ROUNDUP($E$14,4),0) -> 0 | D59: =IF(F57>0.01,ROUND(F57,2)*$E$10/12,0) -> 0 | E59: =IF(F57>0.01,ROUND(C59,2)+ROUND(D59,2),0) -> 0 | F59: =IF(F57>0.01,ROUND(F57,2)-C59,0) -> 0
B60: =IF($E$9>3,38,0) -> 38 | C60: =IF(F59>0.01,$E$8*ROUNDUP($E$14,4),0) -> 0 | D60: =IF(F59>0.01,ROUND(F59,2)*$E$10/12,0) -> 0 | E60: =IF(F59>0.01,ROUND(C60,2)+ROUND(D60,2),0) -> 0 | F60: =IF(F59>0.01,ROUND(F59,2)-C60,0) -> 0
B61: =IF($E$9>3,39,0) -> 39 | C61: =IF(F60>0.01,$E$8*ROUNDUP($E$14,4),0) -> 0 | D61: =IF(F60>0.01,ROUND(F60,2)*$E$10/12,0) -> 0 | E61: =IF(F60>0.01,ROUND(C61,2)+ROUND(D61,2),0) -> 0 | F61: =IF(F60>0.01,ROUND(F60,2)-C61,0) -> 0
B62: =IF($E$9>3,40,0) -> 40 | C62: =IF(F61>0.01,$E$8*ROUNDUP($E$14,4),0) -> 0 | D62: =IF(F61>0.01,ROUND(F61,2)*$E$10/12,0) -> 0 | E62: =IF(F61>0.01,ROUND(C62,2)+ROUND(D62,2),0) -> 0 | F62: =IF(F61>0.01,ROUND(F61,2)-C62,0) -> 0
B63: =IF($E$9>3,41,0) -> 41 | C63: =IF(F62>0.01,$E$8*ROUNDUP($E$14,4),0) -> 0 | D63: =IF(F62>0.01,ROUND(F62,2)*$E$10/12,0) -> 0 | E63: =IF(F62>0.01,ROUND(C63,2)+ROUND(D63,2),0) -> 0 | F63: =IF(F62>0.01,ROUND(F62,2)-C63,0) -> 0
B64: =IF($E$9>3,42,0) -> 42 | C64: =IF(F63>0.01,$E$8*ROUNDUP($E$14,4),0) -> 0 | D64: =IF(F63>0.01,ROUND(F63,2)*$E$10/12,0) -> 0 | E64: =IF(F63>0.01,ROUND(C64,2)+ROUND(D64,2),0) -> 0 | F64: =IF(F63>0.01,ROUND(F63,2)-C64,0) -> 0
B65: =IF($E$9>3,43,0) -> 43 | C65: =IF(F64>0.01,$E$8*ROUNDUP($E$14,4),0) -> 0 | D65: =IF(F64>0.01,ROUND(F64,2)*$E$10/12,0) -> 0 | E65: =IF(F64>0.01,ROUND(C65,2)+ROUND(D65,2),0) -> 0 | F65: =IF(F64>0.01,ROUND(F64,2)-C65,0) -> 0
B66: =IF($E$9>3,44,0) -> 44 | C66: =IF(F65>0.01,$E$8*ROUNDUP($E$14,4),0) -> 0 | D66: =IF(F65>0.01,ROUND(F65,2)*$E$10/12,0) -> 0 | E66: =IF(F65>0.01,ROUND(C66,2)+ROUND(D66,2),0) -> 0 | F66: =IF(F65>0.01,ROUND(F65,2)-C66,0) -> 0
B67: =IF($E$9>3,45,0) -> 45 | C67: =IF(F66>0.01,$E$8*ROUNDUP($E$14,4),0) -> 0 | D67: =IF(F66>0.01,ROUND(F66,2)*$E$10/12,0) -> 0 | E67: =IF(F66>0.01,ROUND(C67,2)+ROUND(D67,2),0) -> 0 | F67: =IF(F66>0.01,ROUND(F66,2)-C67,0) -> 0
B68: =IF($E$9>3,46,0) -> 46 | C68: =IF(F67>0.01,$E$8*ROUNDUP($E$14,4),0) -> 0 | D68: =IF(F67>0.01,ROUND(F67,2)*$E$10/12,0) -> 0 | E68: =IF(F67>0.01,ROUND(C68,2)+ROUND(D68,2),0) -> 0 | F68: =IF(F67>0.01,ROUND(F67,2)-C68,0) -> 0
B69: =IF($E$9>3,47,0) -> 47 | C69: =IF(F68>0.01,$E$8*ROUNDUP($E$14,4),0) -> 0 | D69: =IF(F68>0.01,ROUND(F68,2)*$E$10/12,0) -> 0 | E69: =IF(F68>0.01,ROUND(C69,2)+ROUND(D69,2),0) -> 0 | F69: =IF(F68>0.01,ROUND(F68,2)-C69,0) -> 0
B70: =IF($E$9>3,48,0) -> 48 | C70: =IF(F69>0.01,IF(F69>C69,$E$8*ROUNDUP($E$14,4),F69),0) -> 0 | D70: =IF(F69>0.01,ROUND(F69,2)*$E$10/12,0) -> 0 | E70: =IF(F69>0.01,ROUND(C70,2)+ROUND(D70,2),0) -> 0 | F70: =IF(F69>0.01,ROUND(F69,2)-C70,0) -> 0
B71: =IF($E$9>4,49,0) -> 49 | C71: =IF(F70>0.01,$E$8*ROUNDUP($E$14,4),0) -> 0 | D71: =IF(F70>0.01,ROUND(F70,2)*$E$10/12,0) -> 0 | E71: =IF(F70>0.01,ROUND(C71,2)+ROUND(D71,2),0) -> 0 | F71: =IF(F70>0.01,ROUND(F70,2)-C71,0) -> 0
B72: =IF($E$9>4,50,0) -> 50 | C72: =IF(F71>0.01,$E$8*ROUNDUP($E$14,4),0) -> 0 | D72: =IF(F71>0.01,ROUND(F71,2)*$E$10/12,0) -> 0 | E72: =IF(F71>0.01,ROUND(C72,2)+ROUND(D72,2),0) -> 0 | F72: =IF(F71>0.01,ROUND(F71,2)-C72,0) -> 0
B73: =IF($E$9>4,51,0) -> 51 | C73: =IF(F72>0.01,$E$8*ROUNDUP($E$14,4),0) -> 0 | D73: =IF(F72>0.01,ROUND(F72,2)*$E$10/12,0) -> 0 | E73: =IF(F72>0.01,ROUND(C73,2)+ROUND(D73,2),0) -> 0 | F73: =IF(F72>0.01,ROUND(F72,2)-C73,0) -> 0
B74: =IF($E$9>4,52,0) -> 52 | C74: =IF(F73>0.01,$E$8*ROUNDUP($E$14,4),0) -> 0 | D74: =IF(F73>0.01,ROUND(F73,2)*$E$10/12,0) -> 0 | E74: =IF(F73>0.01,ROUND(C74,2)+ROUND(D74,2),0) -> 0 | F74: =IF(F73>0.01,ROUND(F73,2)-C74,0) -> 0
B75: =IF($E$9>4,53,0) -> 53 | C75: =IF(F74>0.01,$E$8*ROUNDUP($E$14,4),0) -> 0 | D75: =IF(F74>0.01,ROUND(F74,2)*$E$10/12,0) -> 0 | E75: =IF(F74>0.01,ROUND(C75,2)+ROUND(D75,2),0) -> 0 | F75: =IF(F74>0.01,ROUND(F74,2)-C75,0) -> 0
B76: =IF($E$9>4,54,0) -> 54 | C76: =IF(F75>0.01,$E$8*ROUNDUP($E$14,4),0) -> 0 | D76: =IF(F75>0.01,ROUND(F75,2)*$E$10/12,0) -> 0 | E76: =IF(F75>0.01,ROUND(C76,2)+ROUND(D76,2),0) -> 0 | F76: =IF(F75>0.01,ROUND(F75,2)-C76,0) -> 0
B77: =IF($E$9>4,55,0) -> 55 | C77: =IF(F76>0.01,$E$8*ROUNDUP($E$14,4),0) -> 0 | D77: =IF(F76>0.01,ROUND(F76,2)*$E$10/12,0) -> 0 | E77: =IF(F76>0.01,ROUND(C77,2)+ROUND(D77,2),0) -> 0 | F77: =IF(F76>0.01,ROUND(F76,2)-C77,0) -> 0 | J77: Kreditsumme
B78: =IF($E$9>4,56,0) -> 56 | C78: =IF(F77>0.01,$E$8*ROUNDUP($E$14,4),0) -> 0 | D78: =IF(F77>0.01,ROUND(F77,2)*$E$10/12,0) -> 0 | E78: =IF(F77>0.01,ROUND(C78,2)+ROUND(D78,2),0) -> 0 | F78: =IF(F77>0.01,ROUND(F77,2)-C78,0) -> 0 | J78: Laufzeit in Jahren
B79: =IF($E$9>4,57,0) -> 57 | C79: =IF(F78>0.01,$E$8*ROUNDUP($E$14,4),0) -> 0 | D79: =IF(F78>0.01,ROUND(F78,2)*$E$10/12,0) -> 0 | E79: =IF(F78>0.01,ROUND(C79,2)+ROUND(D79,2),0) -> 0 | F79: =IF(F78>0.01,ROUND(F78,2)-C79,0) -> 0 | J79: Zinssatz (nominal)
B80: =IF($E$9>4,58,0) -> 58 | C80: =IF(F79>0.01,$E$8*ROUNDUP($E$14,4),0) -> 0 | D80: =IF(F79>0.01,ROUND(F79,2)*$E$10/12,0) -> 0 | E80: =IF(F79>0.01,ROUND(C80,2)+ROUND(D80,2),0) -> 0 | F80: =IF(F79>0.01,ROUND(F79,2)-C80,0) -> 0
B81: =IF($E$9>4,59,0) -> 59 | C81: =IF(F80>0.01,$E$8*ROUNDUP($E$14,4),0) -> 0 | D81: =IF(F80>0.01,ROUND(F80,2)*$E$10/12,0) -> 0 | E81: =IF(F80>0.01,ROUND(C81,2)+ROUND(D81,2),0) -> 0 | F81: =IF(F80>0.01,ROUND(F80,2)-C81,0) -> 0
B82: =IF($E$9>4,60,0) -> 60 | C82: =IF(F81>0.01,IF(F81>C81,$E$8*ROUNDUP($E$14,4),F81),0) -> 0 | D82: =IF(F81>0.01,ROUND(F81,2)*$E$10/12,0) -> 0 | E82: =IF(F81>0.01,ROUND(C82,2)+ROUND(D82,2),0) -> 0 | F82: =IF(F81>0.01,ROUND(F81,2)-C82,0) -> 0
B83: Gesamt | C83: =SUM(C16:C82)-C58-C45-C32-C31-C27-C19 -> 0 | D83: =SUM(D16:D82)-D58-D45-D32-D31-D27-D19 -> 0 | E83: =SUM(E16:E82)-E58-E45-E32-E31-E27-E19 -> 0
A92: zurück | C92: Geschäftsplanrechnung Antrag Mikrostarter
A93: Angaben in € | C93: 1. Quartal | D93: 2. Quartal | E93: 3. Quartal | F93: 4. Quartal | G93: Summe 1.GJ | H93: 2.GJ | I93: 3.GJ
A94: Umsatzerlöse | C94: ='Ertragsv. 2025'!C3+'Ertragsv. 2025'!D3+'Ertragsv. 2025'!E3 -> 0 | D94: ='Ertragsv. 2025'!F3+'Ertragsv. 2025'!G3+'Ertragsv. 2025'!H3 -> 0 | E94: ='Ertragsv. 2025'!I3+'Ertragsv. 2025'!J3+'Ertragsv. 2025'!K3 -> 0 | F94: ='Ertragsv. 2025'!L3+'Ertragsv. 2025'!M3+'Ertragsv. 2025'!N3 -> 0 | G94: =SUM(C94:F94) -> 0 | H94: ='Ertragsv. 2026'!O3 -> 0 | I94: ='Ertragsv. 2027'!O3 -> 0
A95: Aufwand Waren-/ Material, Fremdleistungen | C95: ='Ertragsv. 2025'!C4+'Ertragsv. 2025'!D4+'Ertragsv. 2025'!E4 -> 0 | D95: ='Ertragsv. 2025'!F4+'Ertragsv. 2025'!G4+'Ertragsv. 2025'!H4 -> 0 | E95: ='Ertragsv. 2025'!I4+'Ertragsv. 2025'!J4+'Ertragsv. 2025'!K4 -> 0 | F95: ='Ertragsv. 2025'!L4+'Ertragsv. 2025'!M4+'Ertragsv. 2025'!N4 -> 0 | G95: =SUM(C95:F95) -> 0 | H95: ='Ertragsv. 2026'!O4 -> 0 | I95: ='Ertragsv. 2027'!O4 -> 0
A96: Rohertrag | C96: =C94-C95 -> 0 | D96: =D94-D95 -> 0 | E96: =E94-E95 -> 0 | F96: =F94-F95 -> 0 | G96: =G94-G95 -> 0 | H96: =H94-H95 -> 0 | I96: =I94-I95 -> 0
A97: sonstige betriebliche Erträge
A98: Personalaufwand | C98: ='Ertragsv. 2025'!C18+'Ertragsv. 2025'!D18+'Ertragsv. 2025'!E18 -> 0 | D98: ='Ertragsv. 2025'!F18+'Ertragsv. 2025'!G18+'Ertragsv. 2025'!H18 -> 0 | E98: ='Ertragsv. 2025'!I18+'Ertragsv. 2025'!J18+'Ertragsv. 2025'!K18 -> 0 | F98: ='Ertragsv. 2025'!L18+'Ertragsv. 2025'!M18+'Ertragsv. 2025'!N18 -> 0 | G98: =SUM(C98:F98) -> 0 | H98: ='Ertragsv. 2026'!O18 -> 0 | I98: ='Ertragsv. 2027'!O18 -> 0
A99: Abschreibungen | C99: ='Ertragsv. 2025'!C22+'Ertragsv. 2025'!D22+'Ertragsv. 2025'!E22 -> 0 | D99: ='Ertragsv. 2025'!F22+'Ertragsv. 2025'!G22+'Ertragsv. 2025'!H22 -> 0 | E99: ='Ertragsv. 2025'!I22+'Ertragsv. 2025'!J22+'Ertragsv. 2025'!K22 -> 0 | F99: ='Ertragsv. 2025'!L22+'Ertragsv. 2025'!M22+'Ertragsv. 2025'!N22 -> 0 | G99: =SUM(C99:F99) -> 0 | H99: ='Ertragsv. 2026'!O22 -> 0 | I99: ='Ertragsv. 2027'!O22 -> 0
A100: Raumkosten | C100: ='Ertragsv. 2025'!C6+'Ertragsv. 2025'!D6+'Ertragsv. 2025'!E6 -> 0 | D100: ='Ertragsv. 2025'!F6+'Ertragsv. 2025'!G6+'Ertragsv. 2025'!H6 -> 0 | E100: ='Ertragsv. 2025'!I6+'Ertragsv. 2025'!J6+'Ertragsv. 2025'!K6 -> 0 | F100: ='Ertragsv. 2025'!L6+'Ertragsv. 2025'!M6+'Ertragsv. 2025'!N6 -> 0 | G100: =SUM(C100:F100) -> 0 | H100: ='Ertragsv. 2026'!O6 -> 0 | I100: ='Ertragsv. 2027'!O6 -> 0
A101: Fahrzeugkosten | C101: ='Ertragsv. 2025'!C8+'Ertragsv. 2025'!D8+'Ertragsv. 2025'!E8+'Ertragsv. 2025'!C7+'Ertragsv. 2025'!D7+'Ertragsv. 2025'!E7 -> 0 | D101: ='Ertragsv. 2025'!F8+'Ertragsv. 2025'!G8+'Ertragsv. 2025'!H8+'Ertragsv. 2025'!F7+'Ertragsv. 2025'!G7+'Ertragsv. 2025'!H7 -> 0 | E101: ='Ertragsv. 2025'!I8+'Ertragsv. 2025'!J8+'Ertragsv. 2025'!K8+'Ertragsv. 2025'!I7+'Ertragsv. 2025'!J7+'Ertragsv. 2025'!K7 -> 0 | F101: ='Ertragsv. 2025'!L8+'Ertragsv. 2025'!M8+'Ertragsv. 2025'!N8+'Ertragsv. 2025'!L7+'Ertragsv. 2025'!M7+'Ertragsv. 2025'!N7 -> 0 | G101: =SUM(C101:F101) -> 0 | H101: ='Ertragsv. 2026'!O8+'Ertragsv. 2026'!O7 -> 0 | I101: ='Ertragsv. 2027'!O7+'Ertragsv. 2027'!O8 -> 0
A102: Versicherungen | C102: ='Ertragsv. 2025'!C14+'Ertragsv. 2025'!D14+'Ertragsv. 2025'!E14 -> 0 | D102: ='Ertragsv. 2025'!F14+'Ertragsv. 2025'!G14+'Ertragsv. 2025'!H14 -> 0 | E102: ='Ertragsv. 2025'!I14+'Ertragsv. 2025'!J14+'Ertragsv. 2025'!K14 -> 0 | F102: ='Ertragsv. 2025'!L14+'Ertragsv. 2025'!M14+'Ertragsv. 2025'!N14 -> 0 | G102: =SUM(C102:F102) -> 0 | H102: ='Ertragsv. 2026'!O14 -> 0 | I102: ='Ertragsv. 2027'!O14 -> 0
A103: Werbung/Vertrieb | C103: ='Ertragsv. 2025'!C10+'Ertragsv. 2025'!D10+'Ertragsv. 2025'!E10 -> 0 | D103: ='Ertragsv. 2025'!F10+'Ertragsv. 2025'!G10+'Ertragsv. 2025'!H10 -> 0 | E103: ='Ertragsv. 2025'!I10+'Ertragsv. 2025'!J10+'Ertragsv. 2025'!K10 -> 0 | F103: ='Ertragsv. 2025'!L10+'Ertragsv. 2025'!M10+'Ertragsv. 2025'!N10 -> 0 | G103: =SUM(C103:F103) -> 0 | H103: ='Ertragsv. 2026'!O10 -> 0 | I103: ='Ertragsv. 2027'!O10 -> 0
A104: weitere betriebliche Aufwendungen | C104: ='Ertragsv. 2025'!C9+'Ertragsv. 2025'!D9+'Ertragsv. 2025'!E9+'Ertragsv. 2025'!C11+'Ertragsv. 2025'!D11+'Ertragsv. 2025'!E11+'Ertragsv. 2025'!C12+'Ertragsv. 2025'!D12+'Ertragsv. 2025'!E12+'Ertragsv. 2025'!C13+'Ertragsv. 2025'!D13+'Ertragsv. 2025'!E13+'Ertragsv. 2025'!C15+'Ertragsv. 2025'!D15+'Ertragsv. 2025'!E15+'Ertragsv. 2025'!C16+'Ertragsv. 2025'!D16+'Ertragsv. 2025'!E16+'Ertragsv. 2025'!C19+'Ertragsv. 2025'!D19+'Ertragsv. 2025'!E19 -> 0 | D104: ='Ertragsv. 2025'!F9+'Ertragsv. 2025'!G9+'Ertragsv. 2025'!H9+'Ertragsv. 2025'!F11+'Ertragsv. 2025'!G11+'Ertragsv. 2025'!H11+'Ertragsv. 2025'!F12+'Ertragsv. 2025'!G12+'Ertragsv. 2025'!H12+'Ertragsv. 2025'!F13+'Ertragsv. 2025'!G13+'Ertragsv. 2025'!H13+'Ertragsv. 2025'!F15+'Ertragsv. 2025'!G15+'Ertragsv. 2025'!H15+'Ertragsv. 2025'!F16+'Ertragsv. 2025'!G16+'Ertragsv. 2025'!H16+'Ertragsv. 2025'!F19+'Ertragsv. 2025'!G19+'Ertragsv. 2025'!H19 -> 0 | E104: ='Ertragsv. 2025'!I9+'Ertragsv. 2025'!J9+'Ertragsv. 2025'!K9+'Ertragsv. 2025'!I11+'Ertragsv. 2025'!J11+'Ertragsv. 2025'!K11+'Ertragsv. 2025'!I12+'Ertragsv. 2025'!J12+'Ertragsv. 2025'!K12+'Ertragsv. 2025'!I13+'Ertragsv. 2025'!J13+'Ertragsv. 2025'!K13+'Ertragsv. 2025'!I15+'Ertragsv. 2025'!J15+'Ertragsv. 2025'!K15+'Ertragsv. 2025'!I16+'Ertragsv. 2025'!J16+'Ertragsv. 2025'!K16+'Ertragsv. 2025'!I19+'Ertragsv. 2025'!J19+'Ertragsv. 2025'!K19 -> 0 | F104: ='Ertragsv. 2025'!L9+'Ertragsv. 2025'!M9+'Ertragsv. 2025'!N9+'Ertragsv. 2025'!L11+'Ertragsv. 2025'!M11+'Ertragsv. 2025'!N11+'Ertragsv. 2025'!L12+'Ertragsv. 2025'!M12+'Ertragsv. 2025'!N12+'Ertragsv. 2025'!L13+'Ertragsv. 2025'!M13+'Ertragsv. 2025'!N13+'Ertragsv. 2025'!L15+'Ertragsv. 2025'!M15+'Ertragsv. 2025'!N15+'Ertragsv. 2025'!L16+'Ertragsv. 2025'!M16+'Ertragsv. 2025'!N16+'Ertragsv. 2025'!L19+'Ertragsv. 2025'!M19+'Ertragsv. 2025'!N19 -> 0 | G104: =SUM(C104:F104) -> 0 | H104: ='Ertragsv. 2026'!O11+'Ertragsv. 2026'!O12+'Ertragsv. 2026'!O13+'Ertragsv. 2026'!O15+'Ertragsv. 2026'!O16+'Ertragsv. 2026'!O9 -> 0 | I104: ='Ertragsv. 2027'!O9+'Ertragsv. 2027'!O11+'Ertragsv. 2027'!O12+'Ertragsv. 2027'!O13+'Ertragsv. 2027'!O15+'Ertragsv. 2027'!O16 -> 0
A105: Zinsaufwand | C105: ='Ertragsv. 2025'!C17+'Ertragsv. 2025'!D17+'Ertragsv. 2025'!E17-D19 -> 0 | D105: ='Ertragsv. 2025'!F17+'Ertragsv. 2025'!G17+'Ertragsv. 2025'!H17-D23 -> 0 | E105: ='Ertragsv. 2025'!I17+'Ertragsv. 2025'!J17+'Ertragsv. 2025'!K17-D27 -> 0 | F105: ='Ertragsv. 2025'!L17+'Ertragsv. 2025'!M17+'Ertragsv. 2025'!N17-D31 -> 0 | G105: =SUM(C105:F105) -> 0 | H105: ='Ertragsv. 2026'!O17-D45 -> 0 | I105: ='Ertragsv. 2027'!O17-D58 -> 0
A106: Betriebsergebnis | C106: =C94-C95+C97-C98-C99-C100-C101-C102-C103-C104-C105 -> 0 | D106: =D94-D95+D97-D98-D99-D100-D101-D102-D103-D104-D105 -> 0 | E106: =E94-E95+E97-E98-E99-E100-E101-E102-E103-E104-E105 -> 0 | F106: =F94-F95+F97-F98-F99-F100-F101-F102-F103-F104-F105 -> 0 | G106: =G94-G95+G97-G98-G99-G100-G101-G102-G103-G104-G105 -> 0 | H106: =H94-H95+H97-H98-H99-H100-H101-H102-H103-H104-H105 -> 0 | I106: =I94-I95+I97-I98-I99-I100-I101-I102-I103-I104-I105 -> 0
A107: EE-Steuern | C107: ='Ertragsv. 2025'!C25+'Ertragsv. 2025'!D25+'Ertragsv. 2025'!E25 -> 0 | D107: ='Ertragsv. 2025'!F25+'Ertragsv. 2025'!G25+'Ertragsv. 2025'!H25 -> 0 | E107: ='Ertragsv. 2025'!I25+'Ertragsv. 2025'!J25+'Ertragsv. 2025'!K25 -> 0 | F107: ='Ertragsv. 2025'!L25+'Ertragsv. 2025'!M25+'Ertragsv. 2025'!N25 -> 0 | G107: =SUM(C107:F107) -> 0 | H107: ='Ertragsv. 2026'!O25 -> 0 | I107: ='Ertragsv. 2027'!O25 -> 0
A108: außerordentliche Erträge
A109: außerordentliche Aufwendungen
A110: Jahresergebnis | C110: =C106-C107+C108-C109 -> 0 | D110: =D106-D107+D108-D109 -> 0 | E110: =E106-E107+E108-E109 -> 0 | F110: =F106-F107+F108-F109 -> 0 | G110: =G106-G107+G108-G109 -> 0 | H110: =H106-H107+H108-H109 -> 0 | I110: =I106-I107+I108-I109 -> 0
A112: vereinfachter Cash-Flow | C112: =C106+C99 -> 0 | D112: =D106+D99 -> 0 | E112: =E106+E99 -> 0 | F112: =F106+F99 -> 0 | G112: =G106+G99 -> 0 | H112: =H106+H99 -> 0 | I112: =I106+I99 -> 0
A113: Zins u. Tilgung MikroSTARTer | C113: =E19 -> 0 | D113: =E23 -> 0 | E113: =E27 -> 0 | F113: =E31 -> 0 | G113: =SUM(C113:F113) -> 0 | H113: =E45 -> 0 | I113: =E58 -> 0
...

Sheet ArbStd_MA
B1: ERMITTLUNG DER PRODUKTIVEN STUNDEN
C3: ERMITTLUNG VERKAUFBARER STUNDEN | D3: =ZusammenführErgebn!C3 -> 2025 | F3: =ZusammenführErgebn!D3 -> 2026 | H3: =ZusammenführErgebn!E3 -> 2027
B4: 1a) | E4: 12
D5: Monat | E5: Jahr | F5: Monat | G5: Jahr | H5: Monat | I5: Jahr
C6: verfügbare Arbeitsstd. je Tag | D6: 8 | E6: =D6 -> 8 | F6: =D6 -> 8 | G6: =F6 -> 8 | H6: =F6 -> 8 | I6: =H6 -> 8
C7: Anzahl Tage | D7: =E7/12 -> 30.416667 | E7: =365/12*E4 -> 365 | F7: =G7/12 -> 30.416667 | G7: =365 -> 365 | H7: =I7/12 -> 30.416667 | I7: =365 -> 365
C8: - Wochenenden | D8: =E8/$E$4 -> 8.6666667 | E8: =104/12*E4 -> 104 | F8: =G8/12 -> 8.6666667 | G8: =104 -> 104 | H8: =I8/12 -> 8.6666667 | I8: =104 -> 104
C9: - Feiertage | D9: =E9/12 -> 0.83333333 | E9: 10 | F9: =G9/12 -> 0.83333333 | G9: 10 | H9: =I9/12 -> 0.83333333 | I9: 10
C10: - Urlaubstage | D10: =E10/$E$4 -> 1.6666667 | E10: 20 | F10: =G10/12 -> 1.6666667 | G10: 20 | H10: =I10/12 -> 1.6666667 | I10: 20
C11: - Krankheit | D11: =E11/$E$4 -> 1.25 | E11: 15 | F11: =G11/12 -> 1.25 | G11: 15 | H11: =I11/12 -> 1.25 | I11: 15
C12: Anzahl Arbeitstage | D12: =D7-SUM(D8:D11) -> 18 | E12: =E7-SUM(E8:E11) -> 216 | F12: =F7-SUM(F8:F11) -> 18 | G12: =G7-SUM(G8:G11) -> 216 | H12: =H7-SUM(H8:H11) -> 18 | I12: =I7-SUM(I8:I11) -> 216
C14: Anzahl mögliche Arbeits-Std. | D14: =D12*D6 -> 144 | E14: =E12*E6 -> 1728 | F14: =F12*F6 -> 144 | G14: =G12*G6 -> 1728 | H14: =H12*H6 -> 144 | I14: =I12*I6 -> 1728
C16: - Tage Akquisition, Networking | E16: =D16*$E$4 -> 0 | G16: =F16*12 -> 0 | I16: =H16*12 -> 0
C17: - Tage Verwaltung, Organisation | E17: =D17*$E$4 -> 0 | G17: =F17*12 -> 0 | I17: =H17*12 -> 0
C18: - Tage Fortbildung | E18: =D18*$E$4 -> 0 | G18: =F18*12 -> 0 | I18: =H18*12 -> 0
C19: - Tage Besprechung, Vorbereitung | E19: =D19*$E$4 -> 0 | G19: =F19*12 -> 0 | I19: =H19*12 -> 0
C20: - Tage Sonst. oder saisonale Unterauslastung | E20: =D20*$E$4 -> 0 | G20: =F20*12 -> 0 | I20: =H20*12 -> 0
C21: Summe nicht verkaufb. Stunden | D21: =SUM(D16:D20)*D6 -> 0 | E21: =SUM(E16:E20) -> 0 | F21: =SUM(F16:F20)*F6 -> 0 | G21: =SUM(G16:G20) -> 0 | H21: =SUM(H16:H20)*H6 -> 0 | I21: =SUM(I16:I20) -> 0
C23: Anzahl verkaufbare Stunden | D23: =(D14-D21) -> 144 | E23: =(E12-E21)*E6 -> 1728 | F23: =(F14-F21) -> 144 | G23: =(G12-G21)*G6 -> 1728 | H23: =(H14-H21) -> 144 | I23: =(I12-I21)*I6 -> 1728
C25: Auslastung in Prozent | E25: =E23/E14 -> 1 | G25: =G23/G14 -> 1 | I25: =I23/I14 -> 1
B26: 1b) | C26: ERMITTLUNG VERKAUFBARER STUNDEN | D26: 1. JAHR | F26: 2. JAHR | H26: 3.JAHR
C27: bei Durchschn. Auslastung von mehreren Mitgründern-Mitarbeitern | D27: Anzahl ver-kaufbarer Stunden/ Monat | E27: durchschnittl. verkaufbare Stunden/ Monat | F27: Anzahl ver-kaufbarer Stunden/ Monat | G27: durchschnittl. verkaufbare Stunden/ Monat | H27: Anzahl ver-kaufbarer Stunden/ Monat | I27: durchschnittl. verkaufbare Stunden/ Monat
C28: verkaufbare Std produkt Mitgründer(arbeiter 1)
C29: verkaufbare Std produkt Mitgründer(arbeiter 2) | E29: =(D28+D29+D30+D31+D32)/K29 -> 0 | G29: =(F28+F29+F30+F31+F32)/K30 -> 0 | I29: =(H28+H29+H30+H31+H32)/K31 -> 0 | K29: 1 | L29: Anzahl MA 1. Jahr
C30: verkaufbare Std produkt Mitgründer(arbeiter 3) | K30: 1 | L30: Anzahl MA 2. Jahr
C31: verkaufbare Std produkt Mitgründer(arbeiter 4) | K31: 1 | L31: Anzahl MA 3. Jahr
C32: verkaufbare Std produkt Mitgründer(arbeiter 5)
C33: Anzahl verkaufbare Stunden als Durchschnitt | D33: =SUM(D28:D32) -> 0 | E33: =E29 -> 0 | F33: =SUM(F28:F32) -> 0 | G33: =G29 -> 0 | H33: =SUM(H28:H32) -> 0 | I33: =I29 -> 0
C36: Auslastung in Prozent | E36: =E33/D14 -> 0 | G36: =G33/F14 -> 0 | I36: =I33/H14 -> 0
B37: 2. | C37: ERMITTLUNG PRODUKTIVEN MITARBEITER | D37: Anzahl der Mitarbeiter | F37: =D3 -> 2025 | G37: =F3 -> 2026 | H37: =H3 -> 2027
C39: Mitarbeitender Inhaber | D39: 1 | F39: =D39 -> 1 | G39: =D39 -> 1 | H39: =D39 -> 1
C40: Meister
C41: Gesellen - Mitarbeiter Produktion
C42: Auszubildende Produktion
C43: Mitarbeiter Büro
C44: Auszubildende Büro
C45: Mitarbeiter Sonstige
C47: Gesamtzahl Mitarbeiter | D47: =SUM(D39:D46) -> 1
C49: Produktive Mitarbeiter | F49: =SUM(F39:F47) -> 1 | G49: =SUM(G39:G47) -> 1 | H49: =SUM(H39:H47) -> 1
B50: 3. | C50: ERMITTLUNG DER PERSONALKOSTEN / PERSONALNEBENKOSTEN
D52: Angestellte | E52: Mini Job
C53: Arbeitgeberanteil Sozialbeiträge | D53: % | E53: %
C54: Krankenversicherung (durchschnittlich) | D54: 7.3 | G54: BeitrBemessGrenze 2020 € 4688
C55: Pflegeversicherung | D55: 1.525 | F55: ab 1.1.2020
C56: Umlage KV (U1+U2 )durchschnittlich | D56: 2.3
C57: Rentenversicherung | D57: 9.3 | F57: ab 1.1.2020 | G57: BeitrBemessGrenze 2020 € 6900
C58: Arbeitslosenversicherung | D58: 1.25 | F58: ab 1.1.2020
C59: Berufsgenossenschaft-Insolvenzgeldumlage | D59: 0.06 | F59: ab 1.1.2020
C60: Zusatzversorgungskasse
C61: Berufsgenossenschaft_Gefahrenklasse x | D61: 0.44 | F61: Beispiel Gefahrenklasse 1
C63: Summe Arbeitgeberanteil Sozialbeiträge | D63: =SUM(D54:D61) -> 22.175 | E63: 32.59
B65: 4. | C65: LÖHNE UND GEHÄLTER 1. JAHR | D65: Anzahl der Mitarbeiter | E65: Verdienst pro Monat | F65: Urlaubs-, Weih.-Geld | G65: Sonst. | H65: Jahres-summe | I65: zuzügl.Sozial beiträge
C66: Geschäftsführer GmbH | H66: =(D66*E66*12)+(D66*F66)+(D66*G66) -> 0 | I66: =(H66*$D$63%)+H66 -> 0
C67: Meister | H67: =(D67*E67*12)+(D67*F67)+(D67*G67) -> 0 | I67: =(H67*$D$63%)+H67 -> 0
C68: Gesellen - Mitarbeiter Produktion | H68: =(D68*E68*12)+(D68*F68)+(D68*G68) -> 0 | I68: =(H68*$D$63%)+H68 -> 0
C69: Auszubildende Produktion | H69: =(D69*E69*12)+(D69*F69)+(D69*G69) -> 0 | I69: =(H69*$D$63%)+H69 -> 0
C70: Mitarbeiter Büro | H70: =(D70*E70*12)+(D70*F70)+(D70*G70) -> 0 | I70: =(H70*$D$63%)+H70 -> 0
C71: Auszubildende Büro | H71: =(D71*E71*12)+(D71*F71)+(D71*G71) -> 0 | I71: =(H71*$D$63%)+H71 -> 0
C72: Mitarbeiter Sonstige | H72: =(D72*E72*12)+(D72*F72)+(D72*G72) -> 0 | I72: =(H72*$D$63%)+H72 -> 0
C74: Summe Personalkosten im Jahr | H74: =SUM(H66:H73) -> 0 | I74: =SUM(I66:I73) -> 0
C76: Summe Personalkosten im Monat | I76: =I74/12 -> 0
C77: Mini Jobs | D77: 0 | E77: 450 | F77: Achtung: ab 1.1.2013 bis 450€ möglich | H77: =(D77*E77)*12 -> 0 | I77: =(H77*$E$63%)+H77 -> 0
C79: Summe Mini Jobs im Jahr | H79: =H77 -> 0 | I79: =I77 -> 0
C81: Summe Mini Jobs im Monat | I81: =I79/12 -> 0
B83: 5. | C83: LÖHNE UND GEHÄLTER 2. JAHR | D83: Anzahl der Mitarbeiter | E83: Verdienst pro Monat | F83: Urlaubs-, Weih.-Geld | G83: Sonst. | H83: Jahres-summe | I83: zuzügl.Sozial beiträge
C84: Geschäftsführer GmbH | H84: =(D84*E84*12)+(D84*F84)+(D84*G84) -> 0 | I84: =(H84*$D$63%)+H84 -> 0
C85: Meister | H85: =(D85*E85*12)+(D85*F85)+(D85*G85) -> 0 | I85: =(H85*$D$63%)+H85 -> 0
C86: Gesellen - Mitarbeiter Produktion | H86: =(D86*E86*12)+(D86*F86)+(D86*G86) -> 0 | I86: =(H86*$D$63%)+H86 -> 0
C87: Auszubildende Produktion | H87: =(D87*E87*12)+(D87*F87)+(D87*G87) -> 0 | I87: =(H87*$D$63%)+H87 -> 0
C88: Mitarbeiter Büro | H88: =(D88*E88*12)+(D88*F88)+(D88*G88) -> 0 | I88: =(H88*$D$63%)+H88 -> 0
C89: Auszubildende Büro | H89: =(D89*E89*12)+(D89*F89)+(D89*G89) -> 0 | I89: =(H89*$D$63%)+H89 -> 0
C90: Mitarbeiter Sonstige | H90: =(D90*E90*12)+(D90*F90)+(D90*G90) -> 0 | I90: =(H90*$D$63%)+H90 -> 0
C92: Summe Personalkosten im Jahr | H92: =SUM(H84:H91) -> 0 | I92: =SUM(I84:I91) -> 0
C94: Summe Personalkosten im Monat | I94: =I92/12 -> 0
C95: Mini Jobs | D95: 0 | E95: 400 | F95: Achtung: ab 1.1.2013 bis 450€ möglich | H95: =(D95*E95)*12 -> 0 | I95: =(H95*$E$63%)+H95 -> 0
C97: Summe Mini Jobs im Jahr | H97: =H95 -> 0 | I97: =I95 -> 0
C99: Summe Mini Jobs im Monat | I99: =I97/12 -> 0
B101: 6. | C101: LÖHNE UND GEHÄLTER 3. JAHR | D101: Anzahl der Mitarbeiter | E101: Verdienst pro Monat | F101: Urlaubs-, Weih.-Geld | G101: Sonst. | H101: Jahres-summe | I101: zuzügl.Sozial beiträge
C102: Geschäftsführer GmbH | H102: =(D102*E102*12)+(D102*F102)+(D102*G102) -> 0 | I102: =(H102*$D$63%)+H102 -> 0
C103: Meister | H103: =(D103*E103*12)+(D103*F103)+(D103*G103) -> 0 | I103: =(H103*$D$63%)+H103 -> 0
C104: Gesellen - Mitarbeiter Produktion | H104: =(D104*E104*12)+(D104*F104)+(D104*G104) -> 0 | I104: =(H104*$D$63%)+H104 -> 0
C105: Auszubildende Produktion | H105: =(D105*E105*12)+(D105*F105)+(D105*G105) -> 0 | I105: =(H105*$D$63%)+H105 -> 0
C106: Mitarbeiter Büro | H106: =(D106*E106*12)+(D106*F106)+(D106*G106) -> 0 | I106: =(H106*$D$63%)+H106 -> 0
C107: Auszubildende Büro | H107: =(D107*E107*12)+(D107*F107)+(D107*G107) -> 0 | I107: =(H107*$D$63%)+H107 -> 0
C108: Mitarbeiter Sonstige | H108: =(D108*E108*12)+(D108*F108)+(D108*G108) -> 0 | I108: =(H108*$D$63%)+H108 -> 0
C110: Summe Personalkosten im Jahr | H110: =SUM(H102:H109) -> 0 | I110: =SUM(I102:I109) -> 0
C112: Summe Personalkosten im Monat | I112: =I110/12 -> 0
C113: Anzahl der Mini Jobs | D113: 0 | E113: 400 | F113: Achtung: ab 1.1.2013 bis 450€ möglich | H113: =(D113*E113)*12 -> 0 | I113: =(H113*E63%)+H113 -> 0
C115: Summe Mini Jobs im Jahr | H115: =H113 -> 0 | I115: =I113 -> 0
C117: Summe Mini Jobs im Monat | I117: =I115/12 -> 0

Sheet ArbSt_MA II
A1: 3)Ermittlung der umsatzlosen | F1: VZ Stellen | G1: TZ Stellen50% | H1: Mini Jobs25% | I1: Azubis | J1: Inhaber | K1: Std.
A2: (unproduktiven) Zeiten : Std pro Monat | F2: 1 | G2: 1 | H2: 1 | J2: 1 | K2: Summen
A3: Saisonausfallstunden | F3: 4 | J3: 2
A4: Stunden der ferienbedingten Unterauslastung | F4: 4 | H4: 1
A6: Seminare - Fortbildung an neuen Maschinen
A7: und in neuer Organsiation | F7: 2 | G7: 2 | H7: 1 | I7: 4
A8: Stunden für Aquisitionen ohne Abschluß | J8: 32
A9: Stunden für Besprechungen ohne Abschluß | J9: 32
A10: Umsatzlose Zeiten durch Verwaltung | F10: 4 | J10: 5
A11: Umsatzlose Zeiten durch
A12: Entwicklung und Einführung neuer Produkte | G12: 2 | J12: 4
A13: Umsatzlose Zeiten durch über lange
A14: Einarbeitungszeiten/Qualifizierung | I14: 1
A15: Langzeitkranke - Anzahl x Stunden
A16: Umsatzlose Zeiten durch Sonstiges
A17: Summe nicht verkaufbare Std ( umsatzlose Zeit) | F17: =SUM(F3:F16) -> 14 | G17: =SUM(G3:G16) -> 4 | H17: =SUM(H3:H16) -> 2 | I17: =SUM(I3:I16) -> 5 | J17: =SUM(J3:J16) -> 75 | K17: =SUM(F17:J17) -> 100
A19: Summe der Unterlastung in Prozent | E19: % | F19: =F17/F21% -> 9.7222222 | G19: =G17/G21% -> 5.5555556 | H19: =H17/H21% -> 5.5555556 | I19: =I17/I21% -> 4.4247788 | J19: =J17/J21% -> 52.083333
A21: Anzahl mögl. Arbeitsstunden (D14) pro Monat | F21: =ArbStd_MA!D14*'ArbSt_MA II'!F2 -> 144 | G21: =ArbStd_MA!D14*'ArbSt_MA II'!G2/2 -> 72 | H21: =ArbStd_MA!D14*'ArbSt_MA II'!H2/4 -> 36 | I21: 113 | J21: =ArbStd_MA!D14*'ArbSt_MA II'!J2 -> 144 | K21: =SUM(F21:J21) -> 509
A24: 4) Ermittlung der verkaufbaren Stunden im Mehrpersonenbetrieb
F25: =F21-F17 -> 130 | G25: =G21-G17 -> 68 | H25: =H21-H17 -> 34 | I25: =I21-I17 -> 108 | J25: =J21-J17 -> 69 | K25: =SUM(F25:J25) -> 409

Sheet Einzelkalk Gastro
B1: KALKULATION GASTRONOMIE | M1: =ZusammenführErgebn!C3 -> 2025 | P1: =ZusammenführErgebn!D3 -> 2026 | S1: =ZusammenführErgebn!E3 -> 2027
L2: Kalkulation des Verkaufspreises | M2: Einkaufspreis/ Beispiel | N2: Kalkulations-aufschl. Soll-Vollkosten | O2: Verkaufs preis | P2: Einkaufspreis / Beispiel | Q2: Kalkulations-aufschl. Soll-Vollkosten | R2: Verkaufspreis | S2: Einkaufspreis / Beispiel | T2: Kalkulations-aufschl. Soll-Vollkosten | U2: Verkaufspreis | X2: Verkaufspreis
B3: Bezeichnung des Menues: | D3: Wildschwein mit Pfifferlingen, Kartoffeln und Salat | L3: realisierter Aufschlag | M3: 3.5 | N3: =('Ertragsv. 2025'!O20-'Ertragsv. 2025'!O4+'Ertragsv. 2025'!O22+'Ertragsv. 2025'!O23)*100/'Ertragsv. 2025'!O4 -> #DIV/0! | O3: =M3*N3%+M3 -> #DIV/0! | P3: 3.5 | Q3: =('Ertragsv. 2026'!O20-'Ertragsv. 2026'!O4+'Ertragsv. 2026'!O22+'Ertragsv. 2026'!O23)*100/'Ertragsv. 2026'!O4 -> #DIV/0! | R3: =P3*Q3%+P3 -> #DIV/0! | S3: 3.5 | T3: =('Ertragsv. 2027'!O20-'Ertragsv. 2027'!O4+'Ertragsv. 2027'!O22+'Ertragsv. 2027'!O23)*100/'Ertragsv. 2027'!O4 -> #DIV/0! | U3: =S3*T3%+S3 -> #DIV/0! | X3: =S3*T3%+S3 -> #DIV/0!
D4: Zutaten | E4: Menge | F4: Einheit | G4: Preis/Einh | H4: Waren-Einstands preis | I4: Kalkulations- aufschlag Soll | J4: Verkaufs- preis | L4: kalkulierter notw. Aufschlag | M4: 3.5 | N4: ='Ertragsv. 2025'!M43 -> 0 | O4: =M4*N4%+M4 -> 3.5 | P4: 3.5 | Q4: ='Ertragsv. 2026'!M42 -> 0 | R4: =P4*Q4%+P4 -> 3.5 | S4: 3.5 | T4: ='Ertragsv. 2027'!M42 -> 0 | U4: =S4*T4%+S4 -> 3.5 | X4: =S4*T4%+S4 -> 3.5
B5: Kalkulation Basis I Wareneinkauf
D7: Fleisch | E7: 5 | F7: kg | G7: 12.6 | H7: =E7*G7 -> 63 | I7: 0.55 | J7: =H7*I7+H7 -> 97.65
D8: Kartoffeln | E8: 5 | F8: kg | G8: 0.99 | H8: =E8*G8 -> 4.95 | I8: 0.55 | J8: =H8*I8+H8 -> 7.6725 | L8: Realisierte Aufschlag aus nebenstehender Einzelkalkulation | M8: EK | N8: =H20 -> 107.385
D9: Pfifferlinge | E9: 1 | F9: kg | G9: 16.8 | H9: =E9*G9 -> 16.8 | I9: 0.55 | J9: =H9*I9+H9 -> 26.04 | M9: VK | N9: =J44 -> 169.84362
D10: Eier | E10: 12 | F10: Stück | G10: 0.25 | H10: =E10*G10 -> 3 | I10: 0.55 | J10: =H10*I10+H10 -> 4.65
D11: Mehl | E11: 0.5 | F11: kg | G11: 2.25 | H11: =E11*G11 -> 1.125 | I11: 0.55 | J11: =H11*I11+H11 -> 1.74375 | M11: RASch % | N11: =(N9-N8)/N8*100 -> 58.163265
D12: Öl | E12: 1 | F12: Liter | G12: 1.25 | H12: =E12*G12 -> 1.25 | I12: 0.55 | J12: =H12*I12+H12 -> 1.9375
D13: Salat | E13: 3 | F13: Köpfe | G13: 0.45 | H13: =E13*G13 -> 1.35 | I13: 0.55 | J13: =H13*I13+H13 -> 2.0925
D14: Zwiebeln | E14: 0.5 | F14: kg | G14: 1.5 | H14: =E14*G14 -> 0.75 | I14: 0.55 | J14: =H14*I14+H14 -> 1.1625
D15: Gurke | E15: 2 | F15: Stück | G15: 1.29 | H15: =E15*G15 -> 2.58 | I15: 0.55 | J15: =H15*I15+H15 -> 3.999
D16: Rote Grütze | E16: 2 | F16: kg | G16: 4.99 | H16: =E16*G16 -> 9.98 | I16: 0.55 | J16: =H16*I16+H16 -> 15.469
D17: Sahne | E17: 1 | F17: Liter | G17: 2.6 | H17: =E17*G17 -> 2.6 | I17: 0.55 | J17: =H17*I17+H17 -> 4.03
D18: Produkt x | H18: =E18*G18 -> 0 | I18: 0.55 | J18: =H18*I18+H18 -> 0
B20: Summe / Waren: | H20: =SUM(H7:H18) -> 107.385 | I20: =(J20-H20)/H20 -> 0.55 | J20: =SUM(J7:J18) -> 166.44675
B22: Kalkulation Basis II Stundensatz | D22: Tätigkeiten | E22: Zeiteinsatz in Stunden | G22: kalk. Durchschnitts- stundensatz
D23: Einkaufszeit | E23: 0.5
D24: Vorbereiten | E24: 1
D25: Kochen | E25: 1
D26: Sonstiges | E26: 0
E27: 0
D28: usw. | E28: 0
D29: usw. | E29: 0
D30: usw. | E30: 0
D32: Summe: | E32: =SUM(E23:E31) -> 2.5 | G32: ='Ertragsv. 2025'!M41 -> 0
B35: Summe / Arbeitszeit: | J35: =E32*G32 -> 0
B37: Kalkulation Basis III Preiskalkulation incl. Skonti und Rabatte
D38: Verkaufspreis netto I | J38: =J20+J35 -> 166.44675
D39: Kundenskonto | H39: % v. ZVP | I39: 0.02 | J39: =I39*J40 -> 3.3968724
D40: Zielverkaufspreis (ZVP) | J40: =J38/(1-I39) -> 169.84362
D41: Kundenrabatt | H41: % v. VK II | I41: 0 | J41: =I41*J42 -> 0
D42: Verkaufspreis netto II | J42: =J40/(1-I41) -> 169.84362
B44: Summe (Angebotspreis netto incl. Skonti und Rabatte): | J44: =SUM(J42:J43) -> 169.84362
B46: Kalkulations Basis IV Zusätzliche kalk. Kosten | D46: Kostenpositionen | J46: Preis
D47: Tischschmuck | J47: 27
D48: Getränke | J48: 38
D49: Sonst.
D50: usw
D51: usw
B56: Summe (zusätzliche Kosten): | J56: =SUM(J47:J55) -> 65
B58: Summe Basis I bisIV | J58: =J44+J56 -> 234.84362
B60: Summe mit Mehrwertsteuer: | I60: 0.19 | J60: =J58*I60 -> 44.620288
B62: Angebotspreis: | D62: angenommene Anzahl der Menues: | G62: 10 | J62: =J58+J60 -> 279.46391
B63: Angebotspreis pro Menue: | J63: =J62/G62 -> 27.946391
B66: Preise aus Markterkundung:

Sheet Einzelkalk_Handwerk
B1: KALKULATION HANDWERK
B3: Kalkulation Basis I Wareneinkauf | D3: Waren Gattungen | E3: Anzahl in Stunden | F3: Stunden- satz | G3: Einkaufs- preis | H3: Kalkulations- aufschlag Soll | I3: Verkaufs- preis | L3: realisierter Stundensatz | N3: =ZusammenführErgebn!C3 -> 2025 | O3: =('Ertragsv. 2025'!O20-'Ertragsv. 2025'!O4+'Ertragsv. 2025'!O22+'Ertragsv. 2025'!O23)/12/ArbStd_MA!D23/ArbStd_MA!F49 -> 0 | P3: Kalkul. notwend. | R3: ='Ertragsv. 2025'!M41 -> 0
L4: realisierter Stundensatz | N4: =ZusammenführErgebn!D3 -> 2026 | O4: =('Ertragsv. 2026'!O20-'Ertragsv. 2026'!O4+'Ertragsv. 2026'!O22+'Ertragsv. 2026'!O23)/12/ArbStd_MA!F23/ArbStd_MA!F49 -> 0 | P4: Kalkul. notwend. | R4: ='Ertragsv. 2026'!M40 -> 0
L5: realisierter Stundensatz | N5: =ZusammenführErgebn!E3 -> 2027 | O5: =('Ertragsv. 2027'!O20-'Ertragsv. 2027'!O4+'Ertragsv. 2027'!O22+'Ertragsv. 2027'!O23)/12/ArbStd_MA!H49/ArbStd_MA!H23 -> 0 | P5: Kalkul. notwend. | R5: ='Ertragsv. 2027'!M40 -> 0
D8: Produkt 1 | G8: 125 | H8: 0.4 | I8: =G8*H8+G8 -> 175 | L8: Verhältnisrechnung zwischen
D9: Produkt 2 | G9: 8 | H9: 0.2 | I9: =G9*H9+G9 -> 9.6 | L9: Std.-Sätze zu Handelsergebnis in € :
D10: Produkt 3 | G10: 15.5 | H10: 0.15 | I10: =G10*H10+G10 -> 17.825 | L10: Aufschlag Waren | N10: =(I14-G14)/E26 -> 10.465854
D11: Produkt 4 | G11: 85 | H11: 0.55 | I11: =G11*H11+G11 -> 131.75 | L11: Offener Stundensatz | N11: =F26 -> 37
D12: Produkt 5 | G12: 12 | H12: 0.55 | I12: =G12*H12+G12 -> 18.6 | L12: Angebotsstundensatz | N12: =N10+N11 -> 47.465854
B14: Summe / Ware | G14: =SUM(G8:G13) -> 245.5 | H14: =(I14-G14)/G14 -> 0.43696538 | I14: =SUM(I8:I13) -> 352.775
B16: Kalkulations Basis II Stundensatz
D17: z.B. Messen
D18: z.B. Sägen | E18: 1
D19: z.B. Hobeln | E19: 1
D20: weitere Arbeits- | E20: 1
D21: schritte | E21: 1
D22: usw. | E22: 3
D23: usw. | E23: 0.25
D24: usw. | E24: 3
D26: Summe | E26: =SUM(E17:E25) -> 10.25 | F26: 37
B29: Summe / Stuneneinsatz: | I29: =E26*F26 -> 379.25
B31: Kalkulation Basis III Preiskalkulation incl. Skonti und Rabatte
D32: Verkaufspreis netto I | I32: =I14+I29 -> 732.025
D33: Kundenskonto | G33: % v. ZVP | H33: 0 | I33: =H33*I34 -> 0
D34: Zielverkaufspreis (ZVP) | I34: =I32/(1-H33) -> 732.025
D35: Kundenrabatt | G35: % v. VK II | H35: 0 | I35: =H35*I36 -> 0
D36: Verkaufspreis netto II | I36: =I34/(1-H35) -> 732.025
B38: Summe (Angebotspreis netto incl. Skonti und Rabatte): | I38: =SUM(I36:I37) -> 732.025
B39: Kalkulations Basis IV Zusätzliche kalk. Kosten
D41: Versicher. | I41: 15
D42: Frachten | I42: 38
D43: Sonst.
D44: usw
D45: usw
B50: Summe (zusätzliche Kosten): | I50: =SUM(I41:I49) -> 53
B52: Summe Basis I bisIV: | I52: =I38+I50 -> 785.025
B54: Summe mit Mehrwertsteuer: | H54: =Deckblatt!C9 -> 0.19 | I54: =I52*H54 -> 149.15475
B56: ANGEBOTSPREIS: | I56: =I52+I54 -> 934.17975

Sheet Einzelkalk_Handel
B1: KALKULATION HANDEL
C3: =ZusammenführErgebn!C3 -> 2025 | F3: =ZusammenführErgebn!D3 -> 2026 | I3: =ZusammenführErgebn!E3 -> 2027
B4: Kalkulation des Verkaufspreises | C4: Einkaufspreis/ Beispiel | D4: Kalkulations-aufschl. Soll-Vollkosten | E4: Verkaufspreis | F4: Einkaufspreis / Beispiel | G4: Kalkulations-aufschl. Soll-Vollkosten | H4: Verkaufspreis | I4: Einkaufspreis / Beispiel | J4: Kalkulations-aufschl. Soll-Vollkosten | K4: Verkaufspreis
B5: realisierter Aufschlag | C5: 3.5 | D5: =IF('Ertragsv. 2025'!P4>0,('Ertragsv. 2025'!P20-'Ertragsv. 2025'!P4+'Ertragsv. 2025'!P22+'Ertragsv. 2025'!P23)*100/'Ertragsv. 2025'!P4,"0") -> #DIV/0! | E5: =C5*D5%+C5 -> #DIV/0! | F5: 3.5 | G5: =IF('Ertragsv. 2026'!P4>0,('Ertragsv. 2026'!P20-'Ertragsv. 2026'!P4+'Ertragsv. 2026'!P22+'Ertragsv. 2026'!P23)*100/'Ertragsv. 2026'!P4,"0") -> #DIV/0! | H5: =F5*G5%+F5 -> #DIV/0! | I5: 3.5 | J5: =IF('Ertragsv. 2027'!P4>0,('Ertragsv. 2027'!P20-'Ertragsv. 2027'!P4+'Ertragsv. 2027'!P22+'Ertragsv. 2027'!P23)*100/'Ertragsv. 2027'!P4,"0") -> #DIV/0! | K5: =I5*J5%+I5 -> #DIV/0!
B6: kalkulierter notw. Aufschlag | C6: 3.5 | D6: =IF('Ertragsv. 2025'!P4>0,('Ertragsv. 2025'!C43+'Ertragsv. 2025'!D43+'Ertragsv. 2025'!E43+'Ertragsv. 2025'!F43+'Ertragsv. 2025'!G43+'Ertragsv. 2025'!H43+'Ertragsv. 2025'!I43+'Ertragsv. 2025'!J43+'Ertragsv. 2025'!K43)*12/'Ertragsv. 2025'!O4%,"0") -> #DIV/0! | E6: =C6*D6%+C6 -> #DIV/0! | F6: 3.5 | G6: =IF('Ertragsv. 2026'!P4>0,('Ertragsv. 2026'!C42+'Ertragsv. 2026'!D42+'Ertragsv. 2026'!E42+'Ertragsv. 2026'!F42+'Ertragsv. 2026'!G42+'Ertragsv. 2026'!H42+'Ertragsv. 2026'!I42+'Ertragsv. 2026'!J42+'Ertragsv. 2026'!K42)*12/'Ertragsv. 2026'!O4%,"0") -> #DIV/0! | H6: =F6*G6%+F6 -> #DIV/0! | I6: 3.5 | J6: =IF('Ertragsv. 2027'!P4>0,('Ertragsv. 2027'!C42+'Ertragsv. 2027'!D42+'Ertragsv. 2027'!E42+'Ertragsv. 2027'!F42+'Ertragsv. 2027'!G42+'Ertragsv. 2027'!H42+'Ertragsv. 2027'!K42+'Ertragsv. 2027'!I42+'Ertragsv. 2027'!J42)*12/'Ertragsv. 2027'!O4%,"0") -> #DIV/0! | K6: =I6*J6%+I6 -> #DIV/0!
B8: Preiskalkulation incl. Skonti und Rabatte
B9: Einkaufspreis | C9: EK | E9: =C6 -> 3.5 | F9: EK | H9: =F6 -> 3.5 | I9: EK | K9: =I6 -> 3.5
B10: Kalkulationszuschlag | C10: % v. EK | D10: =D6 -> #DIV/0! | E10: =D10%*E9 -> #DIV/0! | F10: % v. EK | G10: =G6 -> #DIV/0! | H10: =G10%*H9 -> #DIV/0! | I10: % v.EK | J10: =J6 -> #DIV/0! | K10: =J10%*K9 -> #DIV/0!
B11: Verkaufspreis netto I | E11: =SUM(E9:E10) -> #DIV/0! | H11: =SUM(H9:H10) -> #DIV/0! | K11: =SUM(K9:K10) -> #DIV/0!
B12: Kundenskonto | C12: % v. ZVP | D12: 0.02 | E12: =D12*E13 -> #DIV/0! | F12: % v. ZVP | G12: 0.02 | H12: =G12*H13 -> #DIV/0! | I12: % v. ZVP | J12: 0.02 | K12: =J12*K13 -> #DIV/0!
B13: Zielverkaufspreis (ZVP) | E13: =E11/(1-D12) -> #DIV/0! | H13: =H11/(1-G12) -> #DIV/0! | K13: =K11/(1-J12) -> #DIV/0!
B14: Kundenrabatt | C14: % v. VK II | D14: 0.08 | E14: =D14*E15 -> #DIV/0! | F14: % v.VK II | G14: 0.08 | H14: =G14*H15 -> #DIV/0! | I14: % v. VK II | J14: 0.08 | K14: =J14*K15 -> #DIV/0!
B15: Verkaufspreis netto II | E15: =E13/(1-D14) -> #DIV/0! | H15: =H13/(1-G14) -> #DIV/0! | K15: =K13/(1-J14) -> #DIV/0!
B16: Umsatzsteuer | C16: % | D16: =Deckblatt!C9 -> 0.19 | E16: =D16*E15 -> #DIV/0! | F16: % | G16: =Deckblatt!C9 -> 0.19 | H16: =G16*H15 -> #DIV/0! | I16: % | J16: =Deckblatt!C9 -> 0.19 | K16: =J16*K15 -> #DIV/0!
B17: Angebotspreis ( brutto) | E17: =SUM(E15:E16) -> #DIV/0! | H17: =SUM(H15:H16) -> #DIV/0! | K17: =SUM(K15:K16) -> #DIV/0!
B20: SORTIMENTSKALKULATION
C21: 1. Jahr | F21: 2. Jahr | I21: 3. Jahr
B22: Kalk.notwend.Aufschl | D22: =D6 -> #DIV/0! | G22: =G6 -> #DIV/0! | J22: =J6 -> #DIV/0!
B23: Produkt | C23: Einkaufs preis | D23: Aufschlag | E23: Verkaufspreis | F23: Einkaufspreis | G23: Aufschlag | H23: Verkaufs preis | I23: Einkaufspreis | J23: Aufschlag | K23: Verkaufs preis
B25: Artikel 1 | C25: 12 | D25: 1.25 | E25: =C25*D25+C25 -> 27 | F25: 12 | G25: 2.2 | H25: =F25*G25+F25 -> 38.4 | I25: 12 | J25: 2.2 | K25: =I25*J25+I25 -> 38.4
B26: Artikel 2 | C26: 25 | D26: 1.5 | E26: =C26*D26+C26 -> 62.5 | F26: 25 | G26: 0.2 | H26: =F26*G26+F26 -> 30 | I26: 25 | J26: 0.2 | K26: =I26*J26+I26 -> 30
B27: Artikel 3 | C27: 30 | D27: 1.5 | E27: =C27*D27+C27 -> 75 | F27: 30 | G27: 0.15 | H27: =F27*G27+F27 -> 34.5 | I27: 30 | J27: 0.15 | K27: =I27*J27+I27 -> 34.5
B28: Artikel 4 | C28: 15 | D28: 1.6 | E28: =C28*D28+C28 -> 39 | F28: 15 | G28: 1.6 | H28: =F28*G28+F28 -> 39 | I28: 15 | J28: 1.6 | K28: =I28*J28+I28 -> 39
B29: Artikel 5 | C29: 125 | D29: 2.5 | E29: =C29*D29+C29 -> 437.5 | F29: 125 | G29: 3.09 | H29: =F29*G29+F29 -> 511.25 | I29: 125 | J29: 3.09 | K29: =I29*J29+I29 -> 511.25
B30: Summe: | C30: =SUM(C25:C29) -> 207 | D30: =(E30-C30)/C30 -> 2.0966184 | E30: =SUM(E25:E29) -> 641 | F30: =SUM(F25:F29) -> 207 | G30: =(H30-F30)/F30 -> 2.155314 | H30: =SUM(H25:H29) -> 653.15 | I30: =SUM(I25:I29) -> 207 | J30: =(K30-I30)/I30 -> 2.155314 | K30: =SUM(K25:K29) -> 653.15
B32: Preiskalkulation incl. Skonti und Rabatte
B33: Einkaufspreis | C33: EK | E33: =C30 -> 207 | F33: EK | H33: =F30 -> 207 | I33: EK | K33: =I30 -> 207
B34: Kalkulationszuschlag | C34: % v.EK | D34: =D22 -> #DIV/0! | E34: =D34%*E33 -> #DIV/0! | F34: % v. EK | G34: =G22 -> #DIV/0! | H34: =G34%*H33 -> #DIV/0! | I34: % v.EK | J34: =J22 -> #DIV/0! | K34: =J34%*K33 -> #DIV/0!
B35: Verkaufspreis netto I | E35: =SUM(E33:E34) -> #DIV/0! | H35: =SUM(H33:H34) -> #DIV/0! | K35: =SUM(K33:K34) -> #DIV/0!
B36: Kundenskonto | C36: % v. ZVP | D36: 0.02 | E36: =D36*E37 -> #DIV/0! | F36: % v. ZVP | G36: 0.02 | H36: =G36*H37 -> #DIV/0! | I36: % v. ZVP | J36: 0.02 | K36: =J36*K37 -> #DIV/0!
B37: Zielverkaufspreis (ZVP) | E37: =E35/(1-D36) -> #DIV/0! | H37: =H35/(1-G36) -> #DIV/0! | K37: =K35/(1-J36) -> #DIV/0!
B38: Kundenrabatt | C38: % v. VK II | D38: 0.08 | E38: =D38*E39 -> #DIV/0! | F38: % v. VK II | G38: 0.08 | H38: =G38*H39 -> #DIV/0! | I38: % v. VK II | J38: 0.08 | K38: =J38*K39 -> #DIV/0!
B39: Verkaufspreis netto II | E39: =E37/(1-D38) -> #DIV/0! | H39: =H37/(1-G38) -> #DIV/0! | K39: =K37/(1-J38) -> #DIV/0!
B40: Umsatzsteuer | C40: % | D40: =Deckblatt!C9 -> 0.19 | E40: =D40*E39 -> #DIV/0! | F40: % | G40: =Deckblatt!C9 -> 0.19 | H40: =G40*H39 -> #DIV/0! | I40: % | J40: =Deckblatt!C9 -> 0.19 | K40: =J40*K39 -> #DIV/0!
B41: Angebotspreis ( brutto) | E41: =SUM(E39:E40) -> #DIV/0! | H41: =SUM(H39:H40) -> #DIV/0! | K41: =SUM(K39:K40) -> #DIV/0!
B44: VERGLEICHSPREISE
B47: Produkt | C47: Preis | D47: MWSt. | E47: Endpreis
B49: Artikel 1 | C49: 125 | D49: =C49*19% -> 23.75 | E49: =C49+D49 -> 148.75
B50: Artikel 2 | C50: 16.5 | D50: =C50*19% -> 3.135 | E50: =C50+D50 -> 19.635
B51: Artikel 3 | C51: 12 | D51: =C51*19% -> 2.28 | E51: =C51+D51 -> 14.28
B52: Artikel 4 | C52: 33 | D52: =C52*19% -> 6.27 | E52: =C52+D52 -> 39.27
B53: Artikel 5 | C53: 12.8 | D53: =C53*19% -> 2.432 | E53: =C53+D53 -> 15.232
B54: Artikel 6 | C54: 98 | D54: =C54*19% -> 18.62 | E54: =C54+D54 -> 116.62

Sheet Nachkalkulation Handel
B1: EINZEL - KALKULATION HANDEL | K1: 1 | M1: NACHKALKULATION - HANDEL
C3: Einkaufspreis / Beispiel | D3: Kalkulations-aufschl. Soll-Vollkosten | E3: Verkaufs-preis | F3: Einkaufspreis / Beispiel | G3: Kalkulations-aufschl. Soll-Vollkosten | H3: Verkaufs-preis | I3: Einkaufspreis / Beispiel | J3: Kalkulations-aufschl. Soll-Vollkosten | K3: Verkaufs-preis | M3: Beispielrechnung: | O3: Rückwärtskalkulation | Q3: Basis: Controllingrechnung 20..
Q4: wichtige Zahlen
C5: =ZusammenführErgebn!C3 -> 2025 | F5: =ZusammenführErgebn!D3 -> 2026 | I5: =ZusammenführErgebn!E3 -> 2027 | M5: Verkaufspreis Brutto | O5: 7192
B6: realisierter Aufschlag | C6: 3.5 | D6: =Einzelkalk_Handel!D5 -> #DIV/0! | E6: =C6*D6%+C6 -> #DIV/0! | F6: 3.5 | G6: =Einzelkalk_Handel!G5 -> #DIV/0! | H6: =F6*G6%+F6 -> #DIV/0! | I6: 3.5 | J6: =Einzelkalk_Handel!J5 -> #DIV/0! | K6: =I6*J6%+I6 -> #DIV/0! | M6: MWSt | O6: =O5*P6/(1+P6) -> 1148.3025 | P6: =E19 -> 0.19
M7: Verkaufspreis Netto | O7: =O5/(1+P6) -> 6043.6975
B8: kalkulierter notw. Aufschlag | C8: 3.5 | D8: =Einzelkalk_Handel!D6 -> #DIV/0! | E8: =C8*D8%+C8 -> #DIV/0! | F8: 3.5 | G8: =Einzelkalk_Handel!G6 -> #DIV/0! | H8: =F8*G8%+F8 -> #DIV/0! | I8: 3.5 | J8: =Einzelkalk_Handel!J6 -> #DIV/0! | K8: =I8*J8%+I8 -> #DIV/0! | M8: Kundenskonti | O8: =O7*P8 -> 0 | P8: 0
M9: Zielverkaufspreis | O9: =O7-O8 -> 6043.6975
B10: Beispielrechnung mit vorgerechneten Rabatten und Skonti | M10: Rabatte/Vertreterboni | O10: =O9*P10 -> 0 | P10: 0
M11: Barverkaufspreis | O11: =O9-O10 -> 6043.6975
B12: Einkaufspreis | D12: EK | F12: 3.5 | M12: Risiko,Steuer,Gewinn | O12: =O7*P12 -> 725.2437 | P12: 0.12
B13: Kalkulationszuschlag | D13: % | E13: =IF($K$1=1,D8,IF($K$1=2,G8,IF($K$1=3,J8,))) -> #DIV/0! | F13: =E13%*F12 -> #DIV/0! | M13: Selbstkostenpreis | O13: =O11-O12 -> 5318.4538
B14: Verkaufspreis netto I | F14: =SUM(F12:F13) -> #DIV/0! | M14: Betriebskosten | O14: =O7*P14/100 -> 2650.6203 | P14: ='[5]2014'!R19 -> 43.857593
B15: Kundenskonto | D15: % | E15: 0.02 | F15: =E15*F16 -> #DIV/0! | M15: Rechn. Einkaufspreis | O15: =O13-O14 -> 2667.8335 | Q15: =O15/O7 -> 0.44142407
B16: Zielverkaufspreis | F16: =F14/(1-E15) -> #DIV/0!
B17: Kundenrabatt | D17: % | E17: 0.03 | F17: =E17*F18 -> #DIV/0!
B18: Verkaufspreis netto II | F18: =F16/(1-E17) -> #DIV/0! | M18: Tatsächl. EK Satz | O18: =O7*Q18 -> 2900.9748 | Q18: 0.48
B19: Umsatzsteuer | D19: % | E19: =[5]Deckblatt!B13 -> 0.19 | F19: =E19*F18 -> #DIV/0!
B20: Verkaufspreis ( brutto) | F20: =SUM(F18:F19) -> #DIV/0! | M20: Tatsächlicher Gewinn/Verlust aus diesem Geschäft | O20: =O15-O18 -> -233.14127
B21: Handelsspanne | E21: =(F18-F12)/F18 -> #DIV/0!
B23: SORTIMENTSKALKULATION Beispiel bei nicht vorgerechneten Rabatten und Skonti
C24: 1. Jahr | F24: 2. Jahr | I24: 3. Jahr
B25: Kalk.notwend.Aufschl | G25: =E13 -> #DIV/0! | I25: Akunde | J25: Bkunde | K25: Ckunde
B26: Produkt | F26: Einkaufs preis | G26: Aufschlag | H26: Verkaufs preis | I26: 0.11 | J26: 0.08 | K26: 0.03
B28: Gürtel | F28: 50 | G28: 0.85 | H28: =F28*G28+F28 -> 92.5 | I28: =H28-(H28*$I$26) -> 82.325 | J28: =H28-(H28*$J$26) -> 85.1 | K28: =H28-(H28*$K$26) -> 89.725
B29: Taschen | H29: =F29*G29+F29 -> 0 | I29: =H29-(H29*$I$26) -> 0 | J29: =H29-(H29*$J$26) -> 0 | K29: =H29-(H29*$K$26) -> 0
B30: Trolley | H30: =F30*G30+F30 -> 0 | I30: =H30-(H30*$I$26) -> 0 | J30: =H30-(H30*$J$26) -> 0 | K30: =H30-(H30*$K$26) -> 0
B31: usw | H31: =F31*G31+F31 -> 0 | I31: =H31-(H31*$I$26) -> 0 | J31: =H31-(H31*$J$26) -> 0 | K31: =H31-(H31*$K$26) -> 0
B32: usw | H32: =F32*G32+F32 -> 0 | I32: =H32-(H32*$I$26) -> 0 | J32: =H32-(H32*$J$26) -> 0 | K32: =H32-(H32*$K$26) -> 0
B34: Summe: | F34: =SUM(F28:F33) -> 50 | H34: =SUM(H28:H33) -> 92.5 | I34: =SUM(I28:I32) -> 82.325 | J34: =SUM(J28:J32) -> 85.1 | K34: =SUM(K28:K32) -> 89.725
C35: Real Rohaufschlag je Gruppe | G35: =(H34-F34)/F34 -> 0.85 | I35: =(I34-$F$34)/F34 -> 0.6465 | J35: =(J34-$F$34)/F34 -> 0.702 | K35: =(K34-$F$34)/F34 -> 0.7945
B38: Notwendiger Mindestaufschlag: | C38: Basis: bereinigte Zahlen 2012
B39: Notwendiger Mindestaufschlag: | C39: Basis: bereinigte Zahlen 2013 | F39: cirka | I39: unbereinigt

Sheet Einzelkalk_DL
B1: KALKULATION DIENSTLEISTUNG
B4: Preiskalkulation-Leistungsbeschreibung
D6: =ZusammenführErgebn!C3 -> 2025 | F6: =ZusammenführErgebn!D3 -> 2026 | H6: =ZusammenführErgebn!E3 -> 2027
B7: Art / Beschreibung | C7: Stunden | D7: Stundensatz | E7: Preis | F7: Stundensatz | G7: Preis | H7: Stundensatz | I7: Preis
B9: Vorbereitung / Kundengespräche | C9: 0.25 | D9: ='Ertragsv. 2025'!M41 -> 0 | E9: =C9*D9 -> 0 | F9: ='Ertragsv. 2026'!M40 -> 0 | G9: =C9*F9 -> 0 | H9: ='Ertragsv. 2027'!M40 -> 0 | I9: =C9*H9 -> 0
B10: Diverse/ Kreativer Input für den jew.Auftrag | C10: 1 | E10: =C10*D9 -> 0 | G10: =C10*F9 -> 0 | I10: =C10*H9 -> 0
B11: Unterlagen erstellen / anpassen | C11: 2.5 | E11: =C11*D9 -> 0 | G11: =C11*F9 -> 0 | I11: =C11*H9 -> 0
B12: Auftragsausführung / Leistung erbringen | C12: 3 | E12: =C12*D9 -> 0 | G12: =C12*F9 -> 0 | I12: =C12*H9 -> 0
B13: Schlußbespr.mit Kunden / Rechnungslegung | E13: =C13*D9 -> 0 | G13: =C13*F9 -> 0 | I13: =C13*H9 -> 0
B14: SonstigesFahrt | C14: 0.5 | E14: =C14*D9 -> 0 | G14: =C14*F9 -> 0 | I14: =C14*H9 -> 0
B15: Sonstiges | E15: =C15*D9 -> 0 | G15: =C15*F9 -> 0 | I15: =C15*H9 -> 0
B16: Sonstiges | E16: =C16*D10 -> 0 | G16: =C16*F10 -> 0 | I16: =C16*H10 -> 0
B17: Sonstiges | E17: =C17*D11 -> 0 | G17: =C17*F11 -> 0 | I17: =C17*H11 -> 0
B19: Angebots- / Verkaufspreis (netto): | E19: =SUM(E9:E17) -> 0 | G19: =SUM(G9:G17) -> 0 | I19: =SUM(I9:I17) -> 0
B21: Mehrwertsteuer | C21: =Deckblatt!C9 -> 0.19 | E21: =E19*C21 -> 0 | G21: =G19*C21 -> 0 | I21: =I19*C21 -> 0
B23: Angebots- / Rechnungssumme | E23: =E19+E21 -> 0 | G23: =G19+G21 -> 0 | I23: =I19+I21 -> 0

Sheet Kalkul.Einzelpreise 
B2: PRODUKTKALKULATION_PREISLISTE
B3: Anmerkung:
B4: - Bevor eine Preisliste entstehen kann, ist eine Produktbeschreibung darzustellen, die Struktur und das Produktprofil zu entwickeln
B5: - Basis für diese Kalkulation sind zum einen die notwendigen Rohaufschläge sowie die kalkulierten Stundensätze
B6: - Es ist möglich, im Produkt 1 und 2 unterschiedliche Preise einzusetzen.
B7: - im Produkt 3 kann jeder Arbeitsschritt unterschiedlich bepreist werden.
B9: Kalkulation alternativer Stundensätze | I9: 1 | J9: 2 | K9: 3 | L9: 4 | N9: 5 | O9: 6
B10: Kalkulatorisch notwendiger Stundensatz | H10: =ZusammenführErgebn!C3 -> 2025 | I10: ='Ertragsv. 2025'!M41 -> 0
B11: %-Satz vom kalk. notw. Stundensatz | I11: 80 | J11: 95 | K11: 100 | L11: 115
B12: Alternative Stundensätze | I12: =I10/100*I11 -> 0 | J12: =I10/100*J11 -> 0 | K12: =I10/100*K11 -> 0 | L12: =I10/100*L11 -> 0 | N12: =I10/100*N11 -> 0 | O12: =I10/100*O11 -> 0
V13: 5
B14: Preis aus Markterkundung | I14: =Einzelkalk_Handwerk!U3 -> 0
B16: Produkt/DL 1 | F16: Produkt/DL 2 | K16: Produkt/DL 3
B17: Name | F17: Name | K17: Name
B18: Besonderheit | F18: Besonderheit | K18: Besonderheit
B19: Profil | F19: Profil | K19: Profil
B20: Potentieller Nutzer | F20: Potenzieller Nutzer | K20: Potenzieller Nutzer
B21: Stundensatz | D21: 4 | F21: Stundensatz | I21: 2
B22: Arbeitsschritt | C22: Pers | D22: Std | F22: Arbeitsschritt | H22: Pers | I22: Std | K22: Arbeitsschritt | M22: Pers | N22: Stundensatz | O22: Std
B23: Vorbereitung | C23: 1 | F23: Arbeitsschritt 1 | I23: 1 | K23: Arbeitsschritt 1 | N23: 1 | O23: 1 | P23: =IF(N23=1,$I$12,IF(N23=2,$J$12,IF(N23=3,$K$12,IF(N23=4,$L$12,IF(N23=5,$N$12,IF(N23=6,$O$12))))))*O23 -> 0
B24: Arbeitschritt 2 | C24: 2 | F24: Arbeitsschritt 2 | I24: 0 | K24: Arbeitsschritt 2 | N24: 3 | O24: 2 | P24: =IF(N24=1,$I$12,IF(N24=2,$J$12,IF(N24=3,$K$12,IF(N24=4,$L$12,IF(N24=5,$N$12,IF(N24=6,$O$12))))))*O24 -> 0
B25: Arbeitschritt 3 | F25: Arbeitsschritt 3 | I25: 0 | K25: Arbeitsschritt 3 | N25: 4 | O25: 3 | P25: =IF(N25=1,$I$12,IF(N25=2,$J$12,IF(N25=3,$K$12,IF(N25=4,$L$12,IF(N25=5,$N$12,IF(N25=6,$O$12))))))*O25 -> 0
B26: Arbeitschritt 4 | F26: Arbeitsschritt 4 | I26: 0 | K26: Arbeitsschritt 4 | O26: 0 | P26: =IF(N26=1,$I$12,IF(N26=2,$J$12,IF(N26=3,$K$12,IF(N26=4,$L$12,IF(N26=5,$N$12,IF(N26=6,$O$12))))))*O26 -> 0
B27: Arbeitschritt 5 | F27: Arbeitsschritt 5 | I27: 0 | K27: Arbeitsschritt 5 | O27: 0 | P27: =IF(N27=1,$I$12,IF(N27=2,$J$12,IF(N27=3,$K$12,IF(N27=4,$L$12,IF(N27=5,$N$12,IF(N27=6,$O$12))))))*O27 -> 0
B28: Arbeitschritt 6 | F28: Arbeitsschritt 6 | I28: 0 | K28: Arbeitsschritt 6 | O28: 0 | P28: =IF(N28=1,$I$12,IF(N28=2,$J$12,IF(N28=3,$K$12,IF(N28=4,$L$12,IF(N28=5,$N$12,IF(N28=6,$O$12))))))*O28 -> 0
B29: Arbeitschritt 7 | F29: Arbeitsschritt 7 | I29: 0 | K29: Arbeitsschritt 7 | O29: 0 | P29: =IF(N29=1,$I$12,IF(N29=2,$J$12,IF(N29=3,$K$12,IF(N29=4,$L$12,IF(N29=5,$N$12,IF(N29=6,$O$12))))))*O29 -> 0
B30: Arbeitschritt 8 | F30: Arbeitsschritt 8 | I30: 0 | K30: Arbeitsschritt 8 | O30: 0 | P30: =IF(N30=1,$I$12,IF(N30=2,$J$12,IF(N30=3,$K$12,IF(N30=4,$L$12,IF(N30=5,$N$12,IF(N30=6,$O$12))))))*O30 -> 0
B31: Arbeitschritt 9 | D31: 1 | F31: Arbeitsschritt 9 | I31: 0 | K31: Arbeitsschritt 9 | O31: 0 | P31: =IF(N31=1,$I$12,IF(N31=2,$J$12,IF(N31=3,$K$12,IF(N31=4,$L$12,IF(N31=5,$N$12,IF(N31=6,$O$12))))))*O31 -> 0
B32: Arbeitschritt 10 | F32: Arbeitsschritt 10 | I32: 0 | K32: Arbeitsschritt 10 | O32: 0 | P32: =IF(N32=1,$I$12,IF(N32=2,$J$12,IF(N32=3,$K$12,IF(N32=4,$L$12,IF(N32=5,$N$12,IF(N32=6,$O$12))))))*O32 -> 0
B33: Arbeitschritt 11 | F33: Arbeitsschritt 11 | I33: 0 | K33: Arbeitsschritt 11 | O33: 0 | P33: =IF(N33=1,$I$12,IF(N33=2,$J$12,IF(N33=3,$K$12,IF(N33=4,$L$12,IF(N33=5,$N$12,IF(N33=6,$O$12))))))*O33 -> 0
B34: Arbeitschritt 12 | F34: Arbeitsschritt 12 | I34: 0 | K34: Arbeitsschritt 12 | O34: 0 | P34: =IF(N34=1,$I$12,IF(N34=2,$J$12,IF(N34=3,$K$12,IF(N34=4,$L$12,IF(N34=5,$N$12,IF(N34=6,$O$12))))))*O34 -> 0
B35: Arbeitschritt 13 | F35: Arbeitsschritt 13 | I35: 0 | K35: Arbeitsschritt 13 | O35: 0 | P35: =IF(N35=1,$I$12,IF(N35=2,$J$12,IF(N35=3,$K$12,IF(N35=4,$L$12,IF(N35=5,$N$12,IF(N35=6,$O$12))))))*O35 -> 0
B36: Arbeitschritt 14 | F36: Arbeitsschritt 14 | I36: 0 | K36: Arbeitsschritt 14 | O36: 0 | P36: =IF(N36=1,$I$12,IF(N36=2,$J$12,IF(N36=3,$K$12,IF(N36=4,$L$12,IF(N36=5,$N$12,IF(N36=6,$O$12))))))*O36 -> 0
B37: Arbeitschritt 15 | F37: Arbeitsschritt 15 | I37: 0 | K37: Arbeitsschritt 15 | O37: 0 | P37: =IF(N37=1,$I$12,IF(N37=2,$J$12,IF(N37=3,$K$12,IF(N37=4,$L$12,IF(N37=5,$N$12,IF(N37=6,$O$12))))))*O37 -> 0
B38: Arbeitschritt 16 | F38: Arbeitsschritt 16 | I38: 0 | K38: Arbeitsschritt 16 | O38: 0 | P38: =IF(N38=1,$I$12,IF(N38=2,$J$12,IF(N38=3,$K$12,IF(N38=4,$L$12,IF(N38=5,$N$12,IF(N38=6,$O$12))))))*O38 -> 0
B39: Arbeitschritt 17 | F39: Arbeitsschritt 17 | I39: 0 | K39: Arbeitsschritt 17 | O39: 0 | P39: =IF(N39=1,$I$12,IF(N39=2,$J$12,IF(N39=3,$K$12,IF(N39=4,$L$12,IF(N39=5,$N$12,IF(N39=6,$O$12))))))*O39 -> 0
B40: Arbeitschritt 18 | F40: Arbeitsschritt 18 | I40: 1 | K40: Arbeitsschritt 18 | O40: 0 | P40: =IF(N40=1,$I$12,IF(N40=2,$J$12,IF(N40=3,$K$12,IF(N40=4,$L$12,IF(N40=5,$N$12,IF(N40=6,$O$12))))))*O40 -> 0
B41: Arbeitschritt 19 | F41: Arbeitsschritt 19 | I41: 0 | K41: Arbeitsschritt 19 | O41: 0 | P41: =IF(N41=1,$I$12,IF(N41=2,$J$12,IF(N41=3,$K$12,IF(N41=4,$L$12,IF(N41=5,$N$12,IF(N41=6,$O$12))))))*O41 -> 0
B42: Arbeitschritt 20 | F42: Arbeitsschritt 20 | I42: 0 | K42: Arbeitsschritt 20 | O42: 0 | P42: =IF(N42=1,$I$12,IF(N42=2,$J$12,IF(N42=3,$K$12,IF(N42=4,$L$12,IF(N42=5,$N$12,IF(N42=6,$O$12))))))*O42 -> 0
B43: Arbeitschritt 21 | F43: Arbeitsschritt 21 | I43: 0 | K43: Arbeitsschritt 21 | O43: 0 | P43: =IF(N43=1,$I$12,IF(N43=2,$J$12,IF(N43=3,$K$12,IF(N43=4,$L$12,IF(N43=5,$N$12,IF(N43=6,$O$12))))))*O43 -> 0
... B46: Arbeitschritt 24 | F46: Arbeitsschritt 24 | I46: 0 | K46: Arbeitsschritt 24 | O46: 0 | P46: =IF(N46=1,$I$12,IF(N46=2,$J$12,IF(N46=3,$K$12,IF(N46=4,$L$12,IF(N46=5,$N$12,IF(N46=6,$O$12))))))*O46 -> 0
B47: Stunden Summe | D47: =SUM(D23:E46) -> 1 | I47: =SUM(I23:J46) -> 2 | O47: =SUM(O23:O46) -> 6
B48: Stundensatz | D48: =IF(D21=1,I12,IF(D21=2,J12,IF(D21=3,K12,IF(D21=4,L12,IF(D21=5,N12,IF(D21=6,O12)))))) -> 0 | I48: =IF(I21=1,I12,IF(I21=2,J12,IF(I21=3,K12,IF(I21=4,L12,IF(I21=5,N12,IF(I21=6,O12)))))) -> 0 | N48: individuell pro Arbeitschritt
B49: Preis | D49: =IF(D21=1,I12,IF(D21=2,J12,IF(D21=3,K12,IF(D21=4,L12,IF(D21=5,N12,IF(D21=6,O12))))))*D47 -> 0 | I49: =IF(I21=1,I12,IF(I21=2,J12,IF(I21=3,K12,IF(I21=4,L12,IF(I21=5,N12,IF(I21=6,O12))))))*I47 -> 0 | P49: =SUM(P23:P47) -> 0
B50: Zuschlag für Waren | D50: 0 | I50: 10 | P50: 3
B51: Endpreise + MWSt | C51: =Deckblatt!C9 -> 0.19 | D51: =(D49+D50)*(C51+100%) -> 0 | H51: =Deckblatt!C9 -> 0.19 | I51: =(I49+I50)*(H51+100%) -> 11.9 | O51: =Deckblatt!C9 -> 0.19 | P51: =(P49+P50)*(O51+100%) -> 3.57
P55: =P49/O47 -> 0

Sheet OH Spez.Kosten (2)
F1: In Planung einbezogen
B3: OH-spezifische Kosten einer Finanzplanung
B4: Stand: 30.3.2016
E7: € einmalig/Stck, | G7: € monatlich | H7: Sonstige Kosten
B9: Einmalkosten | C9: ● | D9: Rechtsberatung Homepage | E9: 800 - 1500 €
C10: ● | D10: Design und Aufbau Homepage | E10: 8500 - 20.000 € | I10: unbegrenzte Artikel
B12: Lfd. Kosten | C12: ● | D12: Paket, Verpackung,Rechnung | E12: ca. 0,85 | I12: Verpackung, Aufkleber, Karton
B13: 1. Absatzabhängig | C13: ● | D13: Werbeaufdruckdruck pro Paket | E13: 0.6
C14: ● | D14: Porto pro Paket | E14: 3 bis 5 | I14: Kosten bei Abschluss eines Rahmenvertrags mit einem Dienstleister
C15: ● | D15: Paketbeileger | E15: 0.2 | I15: Bei Auflage 1000 Stck
C16: ● | D16: Porto Retoure | E16: 3 bis 5 | I16: Retourenquoten zwischen 20 und 50 %
C17: ● | D17: Transaktionskosten Plattform | H17: 7-15 % | I17: Prozentsatz vom Verkaufspreis ( zum Beispiel Amazon)
C18: ● | D18: Kosten Payment-Provider | H18: 3-5 % | I18: Prozentsatz vom Verkaufspreis ( Dienstleister für Bezahlsysteme wie Paypal)
B21: 2. Absatzunabhängig | C21: ● | D21: Hosting (ext. Server) | G21: 30-100
C22: ● | D22: Shop-Software | G22: 50-100 | I22: Bei SaaS Lösungen/transaktionsabhängig
C23: ● | D23: SW für Buchhaltung, WaWi etc. | G23: 40
C24: ● | D24: SW Wartungskosten | G24: 200
C26: ●
C27: ● | D27: Händlerbund | G27: ca. 10 / 40 mit Abmahnschutz | I27: Lfd. Anpassung rechtl. Änderungen, Rechtsberatung bei Angriffen
C29: ● | D29: Trusted Shop Gebühren | G29: 40
C31: ● | D31: Nutzung Newsletter SW | E31: kostenlos bis 2000 Empfänger z.B. Mailchimp
C32: ● | D32: Grundgebühr Payment-Provider | E32: 30/oder keine | G32: ca. 1,75 pro Transaktion

Sheet KapBedarf
B1: Kapitalbedarfsplan - Finanzierungsübersicht
B2: Anschaffungskosten (Anschaffungspreis o. MWSt., zzgl. Anschaffungsnebenkosten, abzgl. Skonti u. Rabatte) | I2: AfA Sätze | J2: AfA Beträge
C3: Für den Erwerb und die Neuerrichtung eines Unternehmens | F3: o. MWSt. | H3: m. MWSt.
B4: I. | D4: Unternehmensübernahme
C5: 1 | D5: Kaufpreis für das gesamte Unternehmen | F5: 0 | H5: =F5*1.19 -> 0 | I5: 0.0667 | J5: =F5*I5 -> 0
C6: 2 | H6: =F6*1.19 -> 0 | J6: =F6*I6 -> 0
C7: 3 | H7: =F7*1.19 -> 0 | J7: =F7*I7 -> 0
C8: 4 | H8: =F8*1.19 -> 0 | J8: =F8*I8 -> 0
C9: 5 | H9: =F9*1.19 -> 0 | J9: =F9*I9 -> 0
D10: Gesamt | F10: =SUM(F5:F9) -> 0 | H10: =SUM(H5:H9) -> 0 | J10: =F10*I10 -> 0
B11: II. | D11: Investitionen zur Herstellung der Leistungsbereitschaft | J11: =F11*I11 -> 0
B12: 1. | D12: Immaterielle Vermögensgegenstände | J12: =F12*I12 -> 0
C13: 1 | D13: Einmalige Gebühren f. Patente, Lizenzen, gewerbl. Schutzrechte, Franchise u.ä. | F13: 0 | H13: =F13*1.19 -> 0 | I13: 0.0667 | J13: =F13*I13 -> 0
C14: 2 | D14: Geschäfts- und Firmenwert | H14: =F14*1.19 -> 0 | I14: 0.0667 | J14: =F14*I14 -> 0
C15: 3 | D15: Software | H15: =F15*1.19 -> 0 | J15: =F15*I15 -> 0
D16: Gesamt | F16: =SUM(F13:F15) -> 0 | H16: =SUM(H13:H15) -> 0 | J16: =F16*I16 -> 0
B17: 2. | D17: Sachanlagen | J17: =F17*I17 -> 0
C18: 1 | D18: Grund und Boden | F18: 0 | H18: =F18*1.19 -> 0 | J18: =F18*I18 -> 0
C19: 2 | D19: Grundstückseinrichtungen | H19: =F19*1.19 -> 0 | J19: =F19*I19 -> 0
C20: 3 | D20: Gebäude | H20: =F20*1.19 -> 0 | I20: 0.02 | J20: =F20*I20 -> 0
C21: 4 | D21: Aus- und Umbaumaßnahmen, Modernisierungen, Renovierungen | F21: 0 | H21: =F21*1.19 -> 0 | I21: 0.2 | J21: =F21*I21 -> 0
C22: 5 | D22: Anlagen der Energieversorgung | H22: =F22*1.19 -> 0 | J22: =F22*I22 -> 0
C23: 6 | D23: Maschinen der mechanischen Materialbearbeitung, | H23: =F23*1.19 -> 0 | J23: =F23*I23 -> 0
D24: - verarbeitung und - umwandlung | H24: =F24*1.19 -> 0 | J24: =F24*I24 -> 0
C25: 7 | D25: Anlagen der Materiallagerung und - bereitstellung | H25: =F25*1.19 -> 0 | J25: =F25*I25 -> 0
C26: 8 | D26: Anlagen für Arbeitssicherheit und Umweltschutz | H26: =F26*1.19 -> 0 | J26: =F26*I26 -> 0
C27: 9 | D27: Transportanlagen (Krananlagen) | H27: =F27*1.19 -> 0 | J27: =F27*I27 -> 0
C28: 10 | D28: Versuchsanlagen | H28: =F28*1.19 -> 0 | J28: =F28*I28 -> 0
C29: 11 | D29: Kleinmaschinen und - geräte | H29: =F29*1.19 -> 0 | J29: =F29*I29 -> 0
C30: 12 | D30: Geringwertige Anlagen und Maschinen | H30: =F30*1.19 -> 0 | J30: =F30*I30 -> 0
D31: Gesamt | F31: =SUM(F18:F30) -> 0 | H31: =SUM(H18:H30) -> 0 | J31: =F31*I31 -> 0
B32: 3. | D32: Betriebsausstattung | J32: =F32*I32 -> 0
C33: 1 | D33: Werkstätteneinrichtung | F33: 0 | H33: =F33*1.19 -> 0 | I33: 0.1 | J33: =F33*I33 -> 0
C34: 2 | D34: Werkzeuge, Modelle, Prüf- und Messmittel | H34: =F34*1.19 -> 0 | I34: 0.1 | J34: =F34*I34 -> 0
C35: 3 | D35: Lagereinrichtungen | F35: 0 | H35: =F35*1.19 -> 0 | I35: 0.072 | J35: =F35*I35 -> 0
C36: 4 | D36: Geräte und Einrichtungen des innerbetriebl.Transports | H36: =F36*1.19 -> 0 | J36: =F36*I36 -> 0
C37: 5 | D37: Firmenfahrzeuge | H37: =F37*1.19 -> 0 | I37: 0.1667 | J37: =F37*I37 -> 0
C38: 6 | D38: GWGs der Betriebsausstattung | H38: =F38*1.19 -> 0 | J38: =F38*I38 -> 0
D39: Gesamt | F39: =SUM(F33:F38) -> 0 | H39: =SUM(H33:H38) -> 0 | J39: =F39*I39 -> 0
B40: 4. | D40: Geschäftsausstattung | J40: =F40*I40 -> 0
C41: 1 | D41: Büromaschinen, Organisationsmittel und Kommunikat- | F41: 0 | H41: =F41*1.19 -> 0 | I41: 0.125 | J41: =F41*I41 -> 0
C42: 2 | D42: tionseinrichtungen | H42: =F42*1.19 -> 0 | J42: =F42*I42 -> 0
C43: 3 | D43: Büromöbel u.ä. Geschäftsausstattung, GWGs | H43: =F43*1.19 -> 0 | J43: =F43*I43 -> 0
D44: Gesamt | F44: 0 | H44: =F44*1.19 -> 0 | J44: =F44*I44 -> 0
B45: 5. | D45: Reserve für Unvorhergesehenes, Folgeinvestitionen etc. | H45: =F45*1.19 -> 0 | J45: =F45*I45 -> 0
C46: 1 | H46: =F46*1.19 -> 0 | J46: =F46*I46 -> 0
C47: 2 | H47: =F47*1.19 -> 0 | J47: =F47*I47 -> 0
D48: Gesamt | F48: =SUM(F41:F47) -> 0 | H48: =SUM(H41:H47) -> 0 | J48: =F48*I48 -> 0
B49: III. | D49: Material- und Warenlager | J49: =F49*I49 -> 0
C50: 1 | D50: RHB-Stoffe, Fremdbauteile | F50: 0 | H50: =F50*1.19 -> 0 | J50: =F50*I50 -> 0
C51: 2 | D51: Handelswaren | H51: =F51*1.19 -> 0 | J51: =F51*I51 -> 0
C52: 3 | D52: Unfertige Erzeugnisse | H52: =F52*1.19 -> 0 | J52: =F52*I52 -> 0
C53: 4 | D53: Fertige Erzeugnisse, Waren | F53: 0 | H53: =F53*1.19 -> 0 | J53: =F53*I53 -> 0
C54: 5 | D54: Übernommenes Vorräte-/ Warenlager | H54: =F54*1.19 -> 0 | J54: =F54*I54 -> 0
D55: Gesamt | F55: =SUM(F50:F54) -> 0 | H55: =SUM(H50:H54) -> 0 | J55: =F55*I55 -> 0
B56: IV. | D56: Sonstiger Mittelbedarf für die Anlaufphase | J56: =F56*I56 -> 0
C57: 1 | D57: Roh-, Hilfs- und Betriebsstoffe, Fremdbauteile, Waren | F57: 0 | H57: =F57*1.19 -> 0 | J57: =F57*I57 -> 0
C58: 2 | D58: Bezogene Leistungen für Erzeugnisse u.a. Umsatzleistungen | H58: =F58*1.19 -> 0 | J58: =F58*I58 -> 0
C59: 3 | D59: Fremdkräfte | H59: =F59*1.19 -> 0 | J59: =F59*I59 -> 0
C60: 4 | D60: Lohn- und Gehaltskosten, Soziale Abgaben | H60: =F60*1.19 -> 0 | J60: =F60*I60 -> 0
C61: 5 | D61: Versicherungen | H61: =F61*1.19 -> 0 | J61: =F61*I61 -> 0
C62: 6 | D62: Werbemaßnahmen | H62: =F62*1.19 -> 0 | J62: =F62*I62 -> 0
C63: 7 | H63: =F63*1.19 -> 0 | J63: =F63*I63 -> 0
C64: 8 | D64: Sonstige besondere Belastungen d. Anlaufphase (betriebliche Anlaufkosten) | F64: 0 | H64: =F64*1.19 -> 0 | J64: =F64*I64 -> 0
D65: Gesamt | F65: =SUM(F57:F64) -> 0 | H65: =SUM(H57:H64) -> 0 | J65: =F65*I65 -> 0
B66: V. | D66: Gründungskosten | J66: =F66*I66 -> 0
C67: 1 | D67: Beratungskosten | F67: 0 | H67: =F67*1.19 -> 0 | J67: =F67*I67 -> 0
C68: 2 | D68: Anwalts- und Notarkosten | H68: =F68*1.19 -> 0 | J68: =F68*I68 -> 0
C69: 3 | D69: Anmeldungskosten | H69: =F69*1.19 -> 0 | J69: =F69*I69 -> 0
C70: 4 | D70: Genehmigungskosten | H70: =F70*1.19 -> 0 | J70: =F70*I70 -> 0
C71: 5 | D71: Raumbeschaffungskosten | H71: =F71*1.19 -> 0 | J71: =F71*I71 -> 0
C72: 6 | D72: Aus- und Fortbildungskosten | H72: =F72*1.19 -> 0 | J72: =F72*I72 -> 0
C73: 7 | D73: Markteinführungskosten | H73: =F73*1.19 -> 0 | J73: =F73*I73 -> 0
D74: Gesamt | F74: =SUM(F67:F73) -> 0 | H74: =SUM(H67:H73) -> 0 | J74: =F74*I74 -> 0
D75: Summe aus I., II., (Investitionsmittel) | F75: =F10+F16+F31+F39+F48 -> 0 | H75: =H10+H16+H31+H39+H48 -> 0 | J75: =F75*I75 -> 0
D76: Summe aus III, IV., V. (Betriebsmittel) | F76: =F55+F65+F74 -> 0 | H76: =H55+H65+H74 -> 0 | J76: =F76*I76 -> 0
J77: =F77*I77 -> 0
J78: =F78*I78 -> 0
D79: Summe Gesamtinvestitionen | F79: =F75+F76 -> 0 | I79: jährlich | J79: =SUM(J5:J78) -> 0
I80: monatlich | J80: =J79/12 -> 0
B82: Finanzierungsmittel | F82: Betrag | G82: Satz | H82: Zinsen p.a. | I82: Tilgung p.a.
B83: Gesamt | F83: =F90+F98 -> 69350 | H83: =H86+H98 -> 4520 | I83: =I86+I98 -> 5600
B84: I | C84: 1 | D84: Eigenkapital Bar | F84: 5350
C85: 2 | D85: Sachwerte/Eigenleistung | F85: 8000
C86: 3 | D86: Beteiligungskapital | H86: =F86*G86 -> 0
C87: 4 | D87: Sonstiges | F87: 3000
D90: Gesamt Eigenkapital | F90: =SUM(F84:F89) -> 16350
B92: II | C92: 1 | D92: Förderdarlehen | F92: 15000 | G92: 0.065 | H92: =F92*G92 -> 975 | I92: 1500
C93: 2 | D93: Hausbankdarlehen I | F93: 15000 | G93: 0.085 | H93: =F93*G93 -> 1275 | I93: 1500
C94: 3 | D94: Hausbankdarlehen II | F94: 13000 | G94: 0.09 | H94: =F94*G94 -> 1170 | I94: 2600
C95: 4 | D95: Private Darlehen | G95: 0.04 | H95: =F95*G95 -> 0
C96: 5 | D96: KK Hausbank | F96: 10000 | G96: 0.11 | H96: =F96*G96 -> 1100
C97: 6 | D97: Sonstiges | G97: 0.065 | H97: =F97*G97 -> 0
D98: Gesamt Fremdkapital | F98: =SUM(F92:F97) -> 53000 | G98: =H98/F98 -> 0.085283019 | H98: =SUM(H92:H97) -> 4520 | I98: =SUM(I92:I97) -> 5600

Sheet GwSt-Re
A2: Gewerbesteuer Muster Berechnung: Einzelfirma GmbH
D4: Multipliaktor
A6: Gewinn | C6: ='Ertragsv. 2027'!O23 -> 0 | E6: ='Ertragsv. 2027'!O23 -> 0
A7: Zurechnungen 25% aus
A8: +Zinsen
A9: +Mieten 20% Bewegl. AV
A10: +Mieten 50% Immobil. AV
A11: sofern Summe >100T€
A13: Freibetrag | C13: 24500
A15: Maßgebl.Gewerbeetrag | C15: =C6-C13 -> -24500 | E15: =E6 -> 0
A17: Steuermeßbetrag (bundeseinhl) | C17: =C15*D17 -> -857.5 | D17: 0.035 | E17: =E15*D17 -> 0
A19: GeSt = Steuermeßbetr x Hebesatz | C19: =C17*D19 -> -4116 | D19: 4.8 | E19: =E17*D19 -> 0
A21: Anrechnungsbetrag Einkommensteuer = Steuermeßbetrag x 3,8
C23: =C17*D23 -> -3258.5 | D23: 3.8
A25: Gewerbesteuer | C25: =C19-C23 -> -857.5 | E25: =E19-E23 -> 0
C26: =C25/C6 -> #DIV/0! | E26: =E25/E6 -> #DIV/0!

Sheet Vorblatt Auftragsakquise
B3: Tipps und Hinweise zur Kunden/Auftragsakquisition
B7: Umsatzplanung bei der Gründung ist der wohl schwierigste und anspruchsvollste Teil der Finanzplanung, weil keine Vergleichswerte noch Erfahrungen vorhanden sind! Trotzdem ist es notwendig dies zu tun, und dabei kaufmännische Vorsicht walten zu lassen.
A8: ►1
A12: ►2 | B12: Eine möglichst zutreffende Planung wird durch folgende Fakten untermauert: 1) welche Daten und Erkenntnisse hat die Markterkundung gebracht? 2) welche Akquisitionswege habe ich für mein Gewerk als richtig erkannt und festgelegt? 3) Welche Ansprache mache ich bei Kunden und Nichtkunden?
B17: Das beigefügte Rechentool geht davon aus, daß Ansprachen regelmäßig in gewisser Anzahl gemacht werden; und daß davon nur Teilmengen für weiterführende Akquisition und für Auftragserteilung in Frage kommen
A18: ►3 | K18: Telef.Akquiese!A1
B22: Sie erhalten bie Nutzung und Einstellung der Datei auf Ihre Werte wichtige Hindweise zur Anzahl der Ansprachen (neutral ausgedrückt, also Telefonate, Mails, Briefe usw) und zum Zeitbedarf!
A24: ►4
B27: Alle Maßnahmen und Aktionen sollten dann in einem Aktivitäten- und Marketingplan zusammengefasst werden und in monatlichen Teilen abgearbeitet werden!
A29: ►5

Sheet Telef.Akquiese
A1: Auftrags - Akquisition per Telefon oder andere Medien
A3: 1.Emittlung der benötigten Aufträge pro Monat
B5: Wieviel Umsatz möchten Sie pro Monat erzielen | I5: 3000
B7: Wie groß ist typischer Weise der Umsatz eines Autrages | I7: 300
B9: = Sie benötigen also pro Monat so viel neue Aufträge | I9: =I5/I7 -> 10
A12: 2. Ermittlung der benötigten Akquisitionen pro Monate
B14: Wieviele Angebote müssen sie abgeben um einen Auftrag zu | I14: 5
B15: erhalten
B17: Wieviele konkrete Projekt/Verkausgespräche müssen sie führen um zu einer Angebotsabgabe aufgefordert zu werden | I17: 5
B19: Wieviel Akq Telefonate müssen sie machen um ein konkretes Projekt/Verkaufsgespräch zu führen | I19: 5 | L19: Telefongespräche mit Bestandskunden je Monat
B22: Telefonate insgesamt | I22: =I19*I17*I14*I9 -> 1250 | L22: 0
A24: 3. Emittlung der Telefonate je Arbeitstag
B26: Wenn Sie sich an jedem Arbeitstag Zeit dafür nehmen
B27: sind das ( bei 20 Arbeitstagen je Monat) täglich | I27: =I22/20 -> 62.5
A31: 4. Ermittlung der Telefongespräche mit Bestandskunden
B33: Wenn Sie jeden Monat | D33: =SUM(L22) -> 0 | E33: Telefongespräche mit | I33: =SUM(I27-(D33/20)) -> 62.5
B34: Bestandskunden führen, dann Bleiben pro Tag noch
B35: Telefonate für Neukunden.
A38: 5. Ermittlung der benötigten Zeit pro Tag
B40: Wenn ein Telefonat im Durchschnitt 10 Min. dauert, dann bindet die
B41: Telefonakquise | I41: =SUM(I33)*10 -> 625 | J41: Minuten

Sheet Verfahrenswege
B3: Verfahrensweg in der Tabelle für die Ermittlung von Stundensätzen usw
B7: Kosten +++ | C7: /Produktive Std | D7: /Produktive MA | F7: >>>>>>> | G7: Stundensätze
B8: Sonst. Komponenten
B10: Produkte**** | C10: Stundensätze | F10: >>>>>>>> | G10: Preise
C11: Zeiteinheiten--- | D11: Arbeitsschritte
B14: Mengen *** | C14: Preis | F14: >>>>>>>> | G14: Umsätze
D20: Verfahrensweg für die Ermittlung von Rohaufschlägen
B23: Kosten +++ | C23: Sonst.Komponenten | E23: geteilt | F23: Wareneinsatz %

Sheet Telef.Akquiese 
A1: Auftrags - Akquisition per Telefon oder andere Medien
A3: 1.Emittlung der benötigten Aufträge pro Monat
B5: Wieviel Umsatz möchten Sie pro Monat erzielen | I5: 3000
B7: Wie groß ist typischer Weise der Umsatz eines Autrages | I7: 300
B9: = Sie benötigen also pro Monat so viel neue Aufträge | I9: =I5/I7 -> 10
A12: 2. Ermittlung der benötigten Akquisitionen pro Monate
B14: Wieviele Angebote müssen sie abgeben um einen Auftrag zu | I14: 5
B15: erhalten
B17: Wieviele konkrete Projekt/Verkausgespräche müssen sie führen um zu einer Angebotsabgabe aufgefordert zu werden | I17: 5
B19: Wieviel Akq Telefonate müssen sie machen um ein konkretes Projekt/Verkaufsgespräch zu führen | I19: 5 | L19: Telefongespräche mit Bestandskunden je Monat
B22: Telefonate insgesamt | I22: =I19*I17*I14*I9 -> 1250 | L22: 0
A24: 3. Emittlung der Telefonate je Arbeitstag
B26: Wenn Sie sich an jedem Arbeitstag Zeit dafür nehmen
B27: sind das ( bei 20 Arbeitstagen je Monat) täglich | I27: =I22/20 -> 62.5
A31: 4. Ermittlung der Telefongespräche mit Bestandskunden
B33: Wenn Sie jeden Monat | D33: =SUM(L22) -> 0 | E33: Telefongespräche mit | I33: =SUM(I27-(D33/20)) -> 62.5
B34: Bestandskunden führen, dann Bleiben pro Tag noch
B35: Telefonate für Neukunden.
A38: 5. Ermittlung der benötigten Zeit pro Tag
B40: Wenn ein Telefonat im Durchschnitt 10 Min. dauert, dann bindet die
B41: Telefonakquise | I41: =SUM(I33)*10 -> 625 | J41: Minuten

Sheet Akquisitionen
A1: Aktive Akquisitionsvorgänge | E1: Kontakt | F1: Bespre chung | G1: Angebot | H1: Nachfassen mit Bewertung | I1: Autrag
B4: Geschäftsfeld I
B6: Müller | E6: Datum | F6: Datum | G6: Datum | H6: Datum (2)
B7: Auftrag 1
B8: Auftrag 2
B10: Kunde 2
B15: Geschäftsfeld II
B17: Schulze
B18: Auftrag 1
B21: Kunde 2
B22: Autrag 1
B23: Autrag 2
H25: Legende für Bewertung | J25: 1 Autrag
J26: 2 Hohes | K26: Interesse
B27: Profil und Leistungsbreite des Verkäufers/Beraters | J27: 3 Interesse
B28: Faires Geschäftsgebahren | J28: 4 Kein | K28: Interesse
B29: Unbürokratische und flexible Reaktion auf Kundenwünsche | J29: 5.Ablehnung
B30: Vertraut mit Problemen des Kunden(Betriebes)
B31: Hat umfangreiche Branchen - Fachkenntnisse
B32: Schnelle und zuverlässige Abwicklung des Tagesgeschäftes
B33: Ist initiativ bei der Ansprache von (Neu) Kunden
